Workbook
Name IQ_CH: 110000
Name IQ_CQ: 5000
Name IQ_CY: 10000
Name IQ_DAILY: 500000
Name IQ_FH: 100000
Name IQ_FQ: 500
Name IQ_FY: 1000
Name IQ_LTM: 2000
Name IQ_MONTH: 15000
Name IQ_NTM: 6000
Name IQ_WEEK: 50000
Name IQ_YTD: 3000

Sheet __snloffice
A1: 允䅁䑁䅯䅁䍁䅁䅁䅁䡁䅁䅁䅕䅁䍁䅣睗求䍁䄴杚ㅂ䝁䄴䅚桂䝁䄰党畂䡁䅑兙獂䍁䄴䅥獂䡁䅍䅥摂䑁䅫兌歂䝁䅫兢瑁䙁䅍睙療䡁䅉党穂䍁䅣光歁䕁䅅䅊硁䅁䅁䅎䅁䝁䅁䅁湁䙁䅳党畁䝁䅙兤畂䝁䅑兙瑂䝁䅕杢あ䝁䅅䅢畁䡁䅧䅢穂䡁䅧兘㕁䍁䄰䅚灂䝁䄰兌呂䝁䅍睢祂䝁䅕督湁䍁䅅䅊䍂䍁䅑李㙁䍁䅑村歁䑁䅑䅎㉁䑁䅅䅁ㅁ䅁䅁䅘䅁䍁䅣睗求䍁䄴杚ㅂ䝁䄴䅚桂䝁䄰党畂䡁䅑兙獂䍁䄴䅥獂䡁䅍䅥摂䑁䅫兌歂䝁䅫兢瑁䙁䅍睙療䡁䅉党穂䍁䅣光歁䕁䅍䅊穁䑁䅯䅊䉂䕁䅑䅊穁䅁䅁李䅁䕁䅷䅁湁䙁䅳杚ㅂ䝁䄴䅚桂䝁䄰党畂䡁䅑兙獂䍁䄴䅥獂䡁䅍䅥摂䑁䅫兌歂䝁䅫兢瑁䙁䅍睙療䡁䅉党穂䍁䅣光歁䕁䅅䅊硁䅁䅁睎䅁䙁䅷䅁湁䙁䅳杚ㅂ䝁䄴䅚桂䝁䄰党畂䡁䅑兙獂䍁䄴䅥獂䡁䅍䅥摂䑁䅫兌歂䝁䅫兢瑁䙁䅍睙療䡁䅉党穂䍁䅣光歁䕁䅉䅊㉁䑁䅯䅊䍂䍁䅑䅎ぁ䑁䅙免䅁䑁䅧䅁奂䅁䅁睊扂䝁䅙兤畂䝁䅑兙瑂䝁䅕杢あ䝁䅅䅢畁䡁䅧䅢穂䡁䅧兘㕁䍁䄰䅚灂䝁䄰兌呂䝁䅍睢祂䝁䅕督湁䍁䅅䅊䑂䍁䅑睍㙁䍁䅑兑䕂䍁䅑睍䅁䑁䅫䅁啁䅁䅁䅐⭁䕁䅍兤祂䡁䅉党畂䡁䅑䅁䕁䅁䅁䅆䅁䑁䅷材兂䡁䅉兡瑂䝁䅅杣㕂䅁䅁允䅁䍁䅷䅁䑂䝁䅅督潂䍁䅁杚祂䝁䄸兢杁䕁䄸䅣穂䍁䄴䅉潁䍁䅑䅍睁䑁䅁克䅁䍁䅳䅁䝂䅁䅁睑療䝁䄰兢療䝁䄴䅉呂䝁䅧兙祂䝁䅕督杁䕁䄸兤あ䡁䅍䅤桂䝁䄴䅚灂䝁䄴睚杁䍁䅧兙橂䡁䅑兤桂䝁䅷克䅁䉁䅷䅁允䅁䅁睑ㅂ䡁䅉杣求䝁䄴䅤䅁䅁䅕䅁潁䅁䅁䅒桂䡁䅫䅉䑂䝁䅷睢穂䝁䅕䅉兂䡁䅉兡橂䝁䅕䅉潁䍁䅑克䅁䉁䅯䅁奁䅁䅁兒䍂䕁䅫䅖杁䍁䅧䅊睁䑁䅁䅍灁䅁䅁克䅁䉁䅷䅁䙂䕁䅉兓啂䕁䅑兑杁䍁䅧䅊睁䑁䅁䅍灁䅁䅁睊䅁䉁䅙䅁䙂䝁䄴䅤灂䡁䅑入杁䕁䅫䅒杁䅁䅁睆䅁䉁䅯䅁䙂䝁䄴䅤灂䡁䅑入杁䕁䄴兙瑂䝁䅕䅉䅁䅁䅫䅁啁䅁䅁兒㑂䝁䅍䅡桂䝁䄴睚求䍁䅁䅁呁䅁䅁杇䅁䕁䅫兕時䕁䅍兑呂䕁䅧睘偂䙁䅁兒卂䅁䅁杋䅁䉁䅧䅁䩂䙁䅅睘䩂䕁䄴䅒噂䙁䅍䅖卂䙁䅫䅁桁䅁䅁䅊䅁䕁䅫兕時䕁䅫杔䕂䙁䅕睕啂䙁䅉兗時䕁䅣杕偂䙁䅕䅕䅁䉁䄸䅁敁䅁䅁兓剂䙁䄸䅔啂䙁䄸䅒䙂䕁䅉䅖時䕁䅉杔䱂䅁䅁兄䅁䍁䅧䅁䩂䙁䅅睘兂䙁䅉兓乂䕁䅅杕婂䙁䄸兓佂䕁䅑兖呂䙁䅑杕婂䅁䅁䅆䅁䉁䅑䅁䩂䙁䅅睘呂䕁䅕睑啂䕁䄸杕䅁䉁䄰䅁啁䅁䅁兓畂䝁䅑兤穂䡁䅑杣㕂䍁䅁䅁楁䅁䅁䅉䅁䕁䅫杢歂䡁䅕督あ䡁䅉入杁䕁䅣杣療䡁䅕䅣杁䅁䅁䅉䅁䅁䅧䅁䵂䙁䅑兔䅁䅁䅳䅁䵁䅁䅁䅔啂䕁䄰兌硁䅁䅁杄䅁䍁䅷䅁䵂䝁䄸杢湂䍁䄰䅖求䡁䅉兢杁䕁䅑党楂䡁䅑䅉潁䍁䅑䅍睁䑁䅁克䅁䅁䄸䅁㉁䅁䅁兔桂䡁䅉睡求䡁䅑䅉䑂䝁䅅䅣灂䡁䅑兙獂䝁䅫来桂䡁䅑兡療䝁䄴䅉潁䍁䅑兔灁䅁䅁兇䅁䉁䅧䅁佂䕁䅅兓䑂䙁䅍䅉䑂䝁䄸䅚求䍁䅁䅁橁䅁䅁杆䅁䕁䄴兑䩂䕁䅍睕時䕁䅍睔䕂䕁䅕䅁䅁䅁䅁䅊䅁䕁䄴党あ䍁䅁兓畂䝁䅍睢瑂䝁䅕䅉潁䍁䅑䅍睁䑁䅁克䅁䍁䅕䅁䵃䅁䅁睔睂䡁䅑兡療䝁䄴督㙁䕁䅍兤祂䡁䅉児噂䙁䅍䅒獁䕁䄰兙湂䑁䄰睕あ䝁䅅杢歂䝁䅅杣歂䍁䅷睑療䝁䄴杤乂䝁䅕䅤潂䝁䄸䅚㥁䙁䅉䅌䝂䝁䅫䅢灂䝁䄴睚坂䝁䅕杣㥁䕁䅍兤祂䡁䅉党畂䡁䅑睌卂䝁䅕督あ䝁䅅䅤求䝁䅑䅁䥁䅁䅁䅅䅁䙁䅁杣灂䝁䄰兙祂䡁䅫䅁䍁䅁䅁䅊䅁䙁䅁杣灂䝁䄰兙祂䡁䅫䅉䩂䝁䄴䅚ㅂ䡁䅍䅤祂䡁䅫䅉䅁䉁䅕䅁十䅁䅁睕兂䕁䅣䅖桂䝁䅉䅢求䅁䅁睍䅁䍁䅑䅁呂䙁䅁睘䑂䙁䅕杕卂䕁䅕杔啂䙁䄸兑呂䙁䅍兒啂䙁䅍䅁畁䅁䅁䅉䅁䙁䅍䅕時䕁䅍兖卂䙁䅉兒佂䙁䅑睘䵂䕁䅫兑䍂䅁䅁䅅䅁䉁䅁䅁呂䙁䅁睘䙂䕁䅉兓啂䅁䅁䅋䅁䉁䅑䅁呂䙁䅁睘䙂䕁䅉兓啂䕁䅑兑䅁䍁䅙䅁慁䅁䅁睕兂䙁䄸兒佂䙁䅑兓啂䙁䅫睘䩂䕁䅑䅁坁䅁䅁杈䅁䙁䅍䅕時䕁䅕杔啂䕁䅫䅖婂䙁䄸杔䉂䕁䄰兒䅁䅁䅙䅁奁䅁䅁睕兂䙁䄸兒奂䕁䅍䅓䉂䕁䄴睒䙂䅁䅁杅䅁䉁䅯䅁呂䙁䅁睘乂䕁䅅杕䱂䕁䅕䅖䑂䕁䅅䅕䅁䉁䅧䅁坁䅁䅁睕兂䙁䄸杔䙂䙁䅑睘䩂䕁䄴睑䅁䍁䅑䅁敁䅁䅁睕兂䙁䄸䅕卂䕁䅫睑䙂䙁䄸睑䵂䕁䄸睕䙂䅁䅁睁䅁䑁䅉䅁呂䙁䅁睘呂䕁䅧兑卂䕁䅕睕時䕁䄸兖啂䙁䄸䅕䙂䙁䅉兓偂䕁䅑睘䙂䕁䄴䅒䅁䉁䅳䅁杁䅁䅁睕兂䙁䄸䅖偂䙁䅑兑䵂䙁䄸兑呂䙁䅍兒啂䙁䅍䅁獁䅁䅁杇䅁䙁䅍䅕時䙁䅑睔啂䕁䅅䅔時䙁䅉兒坂䅁䅁权䅁䉁䅁䅁呂䝁䅕睙あ䝁䄸杣杁䅁䅁杈䅁䍁䅧䅁啂䝁䄸䅤桂䝁䅷䅉䉂䡁䅍督求䡁䅑督杁䍁䅧䅊睁䑁䅁䅍灁䅁䅁兌䅁䑁䅧䅁啂䝁䄸䅤桂䝁䅷䅉䑂䡁䅕杣祂䝁䅕杢あ䍁䅁兑穂䡁䅍党あ䡁䅍䅉潁䍁䅑䅍睁䑁䅁克䅁䍁䄸䅁䍂䅁䅁䅖療䡁䅑兙獂䍁䅁睑ㅂ䡁䅉杣求䝁䄴䅤杁䕁䅷兡桂䝁䅉兡獂䝁䅫䅤灂䝁䅕督杁䍁䅧䅊睁䑁䅁䅍灁䅁䅁充䅁䍁䅯䅁啂䝁䄸䅤桂䝁䅷䅉卂䝁䅕杤求䝁䄴兤求䍁䅁䅋歁䑁䅁䅍睁䍁䅫䅁䵁䅁䅁䅑䅁䙁䅳党畁䝁䅙兤畂䝁䅑兙瑂䝁䅕杢あ䝁䅅䅢畁䡁䅧䅢穂䡁䅧兘呂䝁䅧党求䡁䅑杍桁䍁䅑兑歁䑁䅅䅁睁䅁䅁䅕䅁䙁䅳党畁䝁䅙兤畂䝁䅑兙瑂䝁䅕杢あ䝁䅅䅢畁䡁䅧䅢穂䡁䅧兘呂䝁䅧党求䡁䅑杍桁䍁䅑村歁䑁䅙杏歁䕁䅉䅊ぁ䑁䅑李硁䅁䅁免䅁䕁䅷䅁扂䝁䅕杌浂䡁䅕杢歂䝁䅅兢求䝁䄴䅤桂䝁䅷杌㑂䝁䅷督㑂䙁䄰睕潂䝁䅕党あ䑁䅉光歁䕁䅍䅊穁䑁䅯䅊䉂䕁䅑䅊穁䅁䅁杍䅁䍁䅅䅁䵁䅉䅅䅁䕁䅁䅁睁偁䅁䅁兂䅁䅁䅁䕎兙兑䅯䅁䅁䅁䅯允䅁䅁䅅䅁䉁䅁䅁权䍁䅁䅁䍄䉁䅁䅁䅂䅁䅁䅍睄䅁䅁䅕䅁䅁䑁䝒䕅䭅䅁䅍䅁䭁䅁䅑䅁䉁䅁䅁允䅁䅁䅯兂䅁䅁杷允䅁䅁䅙䅁䑁䅁䄸䅁䙁䅁䅁䅁ぁ桒䉂权潁䅁䅁权䱁䅁䅁权䡁䅁䅁权䥁䅁䅁允䅁䅁䅅䅁䭁䍁䅫䅁䵁䅉䅅䅁䝁䅁䅁睁偁䅁䅁兂䅁䅁䅁䕎兙兑䅯权䅁䅁䅯睃䅁䅁䅯睂䅁䅁䅯䅃䅁䅁䅅䅁䉁䅁䅁权䵁䅁䅁䍄䉁䅁䅁杂䅁䅁䅍睄䅁䅁䅕䅁䅁䑁䝒䕅䭅䅁䅙䅁䭁䅁䅣䅁䭁䅁䅣䅁䭁䅁䅧䅁䉁䅁䅁允䅁䅁䅯元䅁䅁杷允䅁䅁䅙䅁䑁䅁䄸䅁䙁䅁䅁䅁ぁ桒䉂权乁䅁䅁权佁䅁䅁权䡁䅁䅁权䥁䅁䅁允䅁䅁䅅䅁䭁䅁䄸䅁䵁䅉䅅䅁䝁䅁䅁睁偁䅁䅁兂䅁䅁䅁䕎兙兑䅯䅊䅁䅁䅯杄䅁䅁䅯睂䅁䅁䅯䅃䅁䅁䅅䅁䉁䅁䅁权汁䅁䅁䍄䉁䅁䅁杂䅁䅁䅍睄䅁䅁䅕䅁䅁䑁䝒䕅䭅䉁䅁䅁䭁䅁䄴䅁䭁䅁䅣䅁䭁䅁䅧䅁䉁䅁䅁允䅁䅁䅯充䅁䅁杷允䅁䅁䅙䅁䑁䅁䄸䅁䙁䅁䅁䅁ぁ桒䉂权十䅁䅁权䡁䅁䅁权䡁䅁䅁权䥁䅁䅁允䅁䅁䅅䅁䭁䉁䅍䅁䵁䅉䅅䅁䝁䅁䅁睁偁䅁䅁兂䅁䅁䅁䕎兙兑䅯䅆䅁䅁䅯睂䅁䅁䅯睂䅁䅁䅯䅃䅁䅁䅅䅁䉁䅁䅁权噁䅁䅁䍄䉁䅁䅁杂䅁䅁䅍睄䅁䅁䅕䅁䅁䑁䝒䕅䭅䉁䅙䅁䭁䅁䅣䅁䭁䅁䅣䅁䭁䅁䅧䅁䉁䅁䅁允䅁䅁䅯睆䅁䅁杷允䅁䅁䅙䅁䑁䅁䄸䅁䙁䅁䅁䅁ぁ桒䉂权奁䅁䅁权䡁䅁䅁权䡁䅁䅁权䥁䅁䅁允䅁䅁䅅䅁䭁䉁䅫䅁䵁䅉䅅䅁䝁䅁䅁睁偁䅁䅁兂䅁䅁䅁䕎兙兑䅯睁䅁䅁䅯兂䅁䅁䅯睂䅁䅁䅯䅃䅁䅁䅅䅁䉁䅁䅁权慁䅁䅁䍄䉁䅁䅁杂䅁䅁䅍睄䅁䅁䅕䅁䅁䑁䝒䕅䭅䍁䄴䅁䭁䅁䅳䅁䭁䅁䅣䅁䭁䅁䅧䅁䉁䅁䅁允䅁䅁䅯睌䅁䅁杷允䅁䅁䅙䅁䑁䅁䄸䅁䙁䅁䅁䅁ぁ桒䉂权扁䅁䅁权佁䅁䅁权䡁䅁䅁权䥁䅁䅁允䅁䅁䅅䅁䭁䉁䅷䅁䵁䅉䅅䅁䝁䅁䅁睁偁䅁䅁兂䅁䅁䅁䕎兙兑䅯先䅁䅁䅯睂䅁䅁䅯睂䅁䅁䅯䅃䅁䅁䅅䅁䉁䅁䅁权敁䅁䅁䍄䉁䅁䅁杂䅁䅁䅍睄䅁䅁䅕䅁䅁䑁䝒䕅䭅䉁䄸䅁䭁䅁䅣䅁䭁䅁䅣䅁䭁䅁䅧䅁䉁䅁䅁允䅁䅁䅯䅉䅁䅁杷允䅁䅁䅙䅁䑁䅁䄸䅁䙁䅁䅁䅁ぁ桒䉂权桁䅁䅁权䡁䅁䅁权䡁䅁䅁权䥁䅁䅁允䅁䅁䅅䅁䭁䍁䅉䅁䵁䅉䅅䅁䝁䅁䅁睁偁䅁䅁兂䅁䅁䅁䕎兙兑䅯杋䅁䅁䅯杄䅁䅁䅯睂䅁䅁䅯䅃䅁䅁䅅䅁䉁䅁䅁权牁䅁䅁䍄䉁䅁䅁杂䅁䅁䅍睄䅁䅁䅕䅁䅁䑁䝒䕅䭅䉁䅳䅁䭁䅁䅳䅁䭁䅁䅣䅁䭁䅁䅧䅁䉁䅁䅁允䅁䅁䅯䅈䅁䅁杷允䅁䅁䅙䅁䑁䅁䄸䅁䙁䅁䅁䅁ぁ桒䉂权䅁䅁䅁权䍁䅁䅁权䡁䅁䅁权䥁䅁䅁允䅁䅁䅅䅁䭁䍁䅍䅁䵁䅉䅅䅁䝁䅁䅁睁偁䅁䅁兂䅁䅁䅁䕎兙兑䅯杊䅁䅁䅯杄䅁䅁䅯睂䅁䅁䅯䅃䅁䅁䅅䅁䉁䅁䅁权湁䅁䅁䍄䉁䅁䅁杂䅁䅁䅍睄䅁䅁䅕䅁䅁䑁䝒䕅䭅䍁䅑䅁䭁䅁䅳䅁䭁䅁䅣䅁䭁䅁䅧䅁䉁䅁䅁允䅁䅁䅯兊䅁䅁杷允䅁䅁䅙䅁䑁䅁䄸䅁䙁䅁䅁䅁ぁ桒䉂权䭁䅁䅁权佁䅁䅁权䡁䅁䅁权䥁䅁䅁允䅁䅁䅅䅁䭁䅁䅷䅁䵁䅉䅅䅁䝁䅁䅁睁偁䅁䅁兂䅁䅁䅁䕎兙兑䅯杋䅁䅁䅯睃䅁䅁䅯睂䅁䅁䅯䅃䅁䅁䅅䅁䉁䅁䅁权牁䅁䅁䍄䉁䅁䅁杂䅁䅁䅍睄䅁䅁䅕䅁䅁䑁䝒䕅䭅䍁䅙䅁䭁䅁䅳䅁䭁䅁䅣䅁䭁䅁䅧䅁䉁䅁䅁允䅁䅁䅯睊䅁䅁杷允䅁䅁䅙䅁䑁䅁䄸䅁䙁䅁䅁䅁ぁ桒䉂权潁䅁䅁权佁䅁䅁权䡁䅁䅁权䥁䅁䅁允䅁䅁䅅䅁䭁䍁䅫䅁䵁䅉䅅䅁䝁䅁䅁睁偁䅁䅁兂䅁䅁䅁䕎兙兑䅯兄䅁䅁䅯睃䅁䅁䅯睂䅁䅁䅯䅃䅁䅁䅅䅁䉁䅁䅁权偁䅁䅁䍄䉁䅁䅁杂䅁䅁䅍睄䅁䅁䅕䅁䅁䑁䝒䕅䭅䍁䅷䅁䭁䅁䅳䅁䭁䅁䅣䅁䭁䅁䅧䅁䉁䅁䅁允䅁䅁䅯兌䅁䅁杷允䅁䅁䅙䅁䑁䅁䄸䅁䙁䅁䅁䅁ぁ桒䉂权獁䅁䅁权佁䅁䅁权䡁䅁䅁权䥁䅁䅁允䅁䅁䅅䅁䭁䍁䄰䅁䵁䅉䅅䅁䝁䅁䅁睁偁䅁䅁兂䅁䅁䅁䕎兙兑䅯杌䅁䅁䅯杄䅁䅁䅯睂䅁䅁䅯䅃䅁䅁䅅䅁䉁䅁䅁权癁䅁䅁䍄䉁䅁䅁杂䅁䅁䅍睄䅁䅁䅕䅁䅁䑁䝒䕅䭅䉁䅁䅁䭁䅁䅳䅁䭁䅁䅣䅁䭁䅁䅧䅁䉁䅁䅁允䅁䅁䅯充䅁䅁杷允䅁䅁䅧䅁䵁䅉䅅䅁䙁䅁䅁权㍁䅁䅁权㑁䅁䅁权㕁䅁䅁权䕁䅁䅋权䥁䅁䅁䅆扂硦橃塳䘴剄䅑噐塂兮䥶㍌啕䑁瘶䥐桌橶䝊䅆ぁ䌴剘儸䵉硫䅑䙚奥㍒䭦煋唰䩁婢⬵䄷牥丫䅆歂㕖䡨㡤煯兲䅅䅁䉁䅁䅁权穁䅁䅁

Sheet Score
A1: Net Income > 0 | B1: Cash flow from Op > 0 | C1: Delta RoA > 0 | D1: CFO > Net Income | E1: Delta LT Debt / Asset < 0 | F1: Delta C Asset / Liability > 0 | G1: Delta EBIT Margin > 0 | H1: Delta Rev / Asset > 0 | I1: Delta O/S shares < 0
L2: Net Income > 0 | M2: Cash flow from Op > 0 | N2: Delta RoA > 0 | O2: CFO > Net Income | P2: Delta LT Debt / Asset < 0 | Q2: Delta C Asset / Liability > 0 | R2: Delta EBIT Margin > 0 | S2: Delta Rev / Asset > 0 | T2: Delta O/S shares < 0 | U2: Sum
A5: {=_xlfn._xlws.FILTER('9-dim-Scores'!A:A,'9-dim-Scores'!AP:AP=1, "")} -> 1st Source Corporation (NASDAQGS:SRCE) | B5: {=_xlfn._xlws.FILTER('9-dim-Scores'!A:A,'9-dim-Scores'!AQ:AQ=1, "")} -> 10x Genomics, Inc. (NASDAQGS:TXG) | C5: {=_xlfn._xlws.FILTER('9-dim-Scores'!A:A,'9-dim-Scores'!AR:AR=1, "")} -> 10x Genomics, Inc. (NASDAQGS:TXG) | D5: {=_xlfn._xlws.FILTER('9-dim-Scores'!A:A,'9-dim-Scores'!AS:AS=1, "")} -> 10x Genomics, Inc. (NASDAQGS:TXG) | E5: {=_xlfn._xlws.FILTER('9-dim-Scores'!A:A,'9-dim-Scores'!AT:AT=1, "")} -> 1-800-FLOWERS.COM, Inc. (NASDAQGS:FLWS) | F5: {=_xlfn._xlws.FILTER('9-dim-Scores'!A:A,'9-dim-Scores'!AU:AU=1, "")} -> 3M Company (NYSE:MMM) | G5: {=_xlfn._xlws.FILTER('9-dim-Scores'!A:A,'9-dim-Scores'!AV:AV=1, "")} -> 10x Genomics, Inc. (NASDAQGS:TXG) | H5: {=_xlfn._xlws.FILTER('9-dim-Scores'!A:A,'9-dim-Scores'!AW:AW=1, "")} -> 1895 Bancorp of Wisconsin, Inc. (NASDAQCM:BCOW) | I5: {=_xlfn._xlws.FILTER('9-dim-Scores'!A:A,'9-dim-Scores'!AX:AX=1, "")} -> 1-800-FLOWERS.COM, Inc. (NASDAQGS:FLWS) | K5: Target
A6: 3M Company (NYSE:MMM) | B6: 1-800-FLOWERS.COM, Inc. (NASDAQGS:FLWS) | C6: 1895 Bancorp of Wisconsin, Inc. (NASDAQCM:BCOW) | D6: 1-800-FLOWERS.COM, Inc. (NASDAQGS:FLWS) | E6: A. O. Smith Corporation (NYSE:AOS) | F6: a.k.a. Brands Holding Corp. (NYSE:AKA) | G6: 1895 Bancorp of Wisconsin, Inc. (NASDAQCM:BCOW) | H6: 1st Source Corporation (NASDAQGS:SRCE) | I6: 1895 Bancorp of Wisconsin, Inc. (NASDAQCM:BCOW) | K6: Carvana Co. (NYSE:CVNA) | L6: =IF(COUNTIF(A:A,$K6)>0,1,0) -> 1 | M6: =IF(COUNTIF(B:B,$K6)>0,1,0) -> 1 | N6: =IF(COUNTIF(C:C,$K6)>0,1,0) -> 0 | O6: =IF(COUNTIF(D:D,$K6)>0,1,0) -> 1 | P6: =IF(COUNTIF(E:E,$K6)>0,1,0) -> 1 | Q6: =IF(COUNTIF(F:F,$K6)>0,1,0) -> 1 | R6: =IF(COUNTIF(G:G,$K6)>0,1,0) -> 1 | S6: =IF(COUNTIF(H:H,$K6)>0,1,0) -> 1 | T6: =IF(COUNTIF(I:I,$K6)>0,1,0) -> 0 | U6: =SUM(L6:T6) -> 7 | X6: sum
A7: A. O. Smith Corporation (NYSE:AOS) | B7: 1st Source Corporation (NASDAQGS:SRCE) | C7: 1st Source Corporation (NASDAQGS:SRCE) | D7: 1895 Bancorp of Wisconsin, Inc. (NASDAQCM:BCOW) | E7: A2Z Cust2Mate Solutions Corp. (NASDAQCM:AZ) | F7: A2Z Cust2Mate Solutions Corp. (NASDAQCM:AZ) | G7: 1st Source Corporation (NASDAQGS:SRCE) | H7: 3M Company (NYSE:MMM) | I7: 3M Company (NYSE:MMM) | K7: MicroStrategy Incorporated (NASDAQGS:MSTR) | L7: =IF(COUNTIF(A:A,$K7)>0,1,0) -> 0 | M7: =IF(COUNTIF(B:B,$K7)>0,1,0) -> 0 | N7: =IF(COUNTIF(C:C,$K7)>0,1,0) -> 0 | O7: =IF(COUNTIF(D:D,$K7)>0,1,0) -> 1 | P7: =IF(COUNTIF(E:E,$K7)>0,1,0) -> 1 | Q7: =IF(COUNTIF(F:F,$K7)>0,1,0) -> 1 | R7: =IF(COUNTIF(G:G,$K7)>0,1,0) -> 0 | S7: =IF(COUNTIF(H:H,$K7)>0,1,0) -> 0 | T7: =IF(COUNTIF(I:I,$K7)>0,1,0) -> 0 | U7: =SUM(L7:T7) -> 3
A8: A10 Networks, Inc. (NYSE:ATEN) | B8: 3M Company (NYSE:MMM) | C8: 3M Company (NYSE:MMM) | D8: 1st Source Corporation (NASDAQGS:SRCE) | E8: AAON, Inc. (NASDAQGS:AAON) | F8: AAON, Inc. (NASDAQGS:AAON) | G8: 3M Company (NYSE:MMM) | H8: A. O. Smith Corporation (NYSE:AOS) | I8: 5:01 Acquisition Corp. (NASDAQCM:FVAM) | K8: Lumen Technologies, Inc. (NYSE:LUMN) | L8: =IF(COUNTIF(A:A,$K8)>0,1,0) -> 0 | M8: =IF(COUNTIF(B:B,$K8)>0,1,0) -> 1 | N8: =IF(COUNTIF(C:C,$K8)>0,1,0) -> 0 | O8: =IF(COUNTIF(D:D,$K8)>0,1,0) -> 1 | P8: =IF(COUNTIF(E:E,$K8)>0,1,0) -> 1 | Q8: =IF(COUNTIF(F:F,$K8)>0,1,0) -> 1 | R8: =IF(COUNTIF(G:G,$K8)>0,1,0) -> 0 | S8: =IF(COUNTIF(H:H,$K8)>0,1,0) -> 0 | T8: =IF(COUNTIF(I:I,$K8)>0,1,0) -> 1 | U8: =SUM(L8:T8) -> 5 | X8: Mean | Y8: 3.9840664
A9: AAON, Inc. (NASDAQGS:AAON) | B9: A. O. Smith Corporation (NYSE:AOS) | C9: a.k.a. Brands Holding Corp. (NYSE:AKA) | D9: 4D Molecular Therapeutics, Inc. (NASDAQGS:FDMT) | E9: AAR Corp. (NYSE:AIR) | F9: Abrdn Life Sciences Investors (NYSE:HQL) | G9: a.k.a. Brands Holding Corp. (NYSE:AKA) | H9: A10 Networks, Inc. (NYSE:ATEN) | I9: A. O. Smith Corporation (NYSE:AOS) | K9: Vistra Corp. (NYSE:VST) | L9: =IF(COUNTIF(A:A,$K9)>0,1,0) -> 1 | M9: =IF(COUNTIF(B:B,$K9)>0,1,0) -> 1 | N9: =IF(COUNTIF(C:C,$K9)>0,1,0) -> 1 | O9: =IF(COUNTIF(D:D,$K9)>0,1,0) -> 1 | P9: =IF(COUNTIF(E:E,$K9)>0,1,0) -> 0 | Q9: =IF(COUNTIF(F:F,$K9)>0,1,0) -> 1 | R9: =IF(COUNTIF(G:G,$K9)>0,1,0) -> 1 | S9: =IF(COUNTIF(H:H,$K9)>0,1,0) -> 1 | T9: =IF(COUNTIF(I:I,$K9)>0,1,0) -> 1 | U9: =SUM(L9:T9) -> 8 | X9: Standard Error | Y9: 0.037791523
A10: AAR Corp. (NYSE:AIR) | B10: a.k.a. Brands Holding Corp. (NYSE:AKA) | C10: A10 Networks, Inc. (NYSE:ATEN) | D10: 5:01 Acquisition Corp. (NASDAQCM:FVAM) | E10: Abbott Laboratories (NYSE:ABT) | F10: ACADIA Pharmaceuticals Inc. (NASDAQGS:ACAD) | G10: A10 Networks, Inc. (NYSE:ATEN) | H10: AAR Corp. (NYSE:AIR) | I10: A10 Networks, Inc. (NYSE:ATEN) | K10: IES Holdings, Inc. (NASDAQGM:IESC) | L10: =IF(COUNTIF(A:A,$K10)>0,1,0) -> 1 | M10: =IF(COUNTIF(B:B,$K10)>0,1,0) -> 1 | N10: =IF(COUNTIF(C:C,$K10)>0,1,0) -> 1 | O10: =IF(COUNTIF(D:D,$K10)>0,1,0) -> 1 | P10: =IF(COUNTIF(E:E,$K10)>0,1,0) -> 0 | Q10: =IF(COUNTIF(F:F,$K10)>0,1,0) -> 1 | R10: =IF(COUNTIF(G:G,$K10)>0,1,0) -> 1 | S10: =IF(COUNTIF(H:H,$K10)>0,1,0) -> 0 | T10: =IF(COUNTIF(I:I,$K10)>0,1,0) -> 1 | U10: =SUM(L10:T10) -> 7 | X10: Median | Y10: 4
A11: Abbott Laboratories (NYSE:ABT) | B11: A10 Networks, Inc. (NYSE:ATEN) | C11: A2Z Cust2Mate Solutions Corp. (NASDAQCM:AZ) | D11: 89bio, Inc. (NASDAQGM:ETNB) | E11: AbbVie Inc. (NYSE:ABBV) | F11: Accenture plc (NYSE:ACN) | G11: A2Z Cust2Mate Solutions Corp. (NASDAQCM:AZ) | H11: Abacus Life, Inc. (NASDAQCM:ABL) | I11: Abbott Laboratories (NYSE:ABT) | K11: FTAI Aviation Ltd. (NASDAQGS:FTAI) | L11: =IF(COUNTIF(A:A,$K11)>0,1,0) -> 1 | M11: =IF(COUNTIF(B:B,$K11)>0,1,0) -> 0 | N11: =IF(COUNTIF(C:C,$K11)>0,1,0) -> 1 | O11: =IF(COUNTIF(D:D,$K11)>0,1,0) -> 0 | P11: =IF(COUNTIF(E:E,$K11)>0,1,0) -> 1 | Q11: =IF(COUNTIF(F:F,$K11)>0,1,0) -> 0 | R11: =IF(COUNTIF(G:G,$K11)>0,1,0) -> 1 | S11: =IF(COUNTIF(H:H,$K11)>0,1,0) -> 1 | T11: =IF(COUNTIF(I:I,$K11)>0,1,0) -> 0 | U11: =SUM(L11:T11) -> 5 | X11: Mode | Y11: 0
A12: AbbVie Inc. (NYSE:ABBV) | B12: AAON, Inc. (NASDAQGS:AAON) | C12: AAON, Inc. (NASDAQGS:AAON) | D12: A. O. Smith Corporation (NYSE:AOS) | E12: Abeona Therapeutics Inc. (NASDAQCM:ABEO) | F12: ACI Worldwide, Inc. (NASDAQGS:ACIW) | G12: Abacus Life, Inc. (NASDAQCM:ABL) | H12: Abrdn Global Dynamic Dividend Fund (NYSE:AGD) | I12: Abercrombie & Fitch Co. (NYSE:ANF) | K12: Sprouts Farmers Market, Inc. (NASDAQGS:SFM) | L12: =IF(COUNTIF(A:A,$K12)>0,1,0) -> 1 | M12: =IF(COUNTIF(B:B,$K12)>0,1,0) -> 1 | N12: =IF(COUNTIF(C:C,$K12)>0,1,0) -> 1 | O12: =IF(COUNTIF(D:D,$K12)>0,1,0) -> 1 | P12: =IF(COUNTIF(E:E,$K12)>0,1,0) -> 0 | Q12: =IF(COUNTIF(F:F,$K12)>0,1,0) -> 1 | R12: =IF(COUNTIF(G:G,$K12)>0,1,0) -> 1 | S12: =IF(COUNTIF(H:H,$K12)>0,1,0) -> 0 | T12: =IF(COUNTIF(I:I,$K12)>0,1,0) -> 1 | U12: =SUM(L12:T12) -> 7 | X12: Standard Deviation | Y12: 2.522708
A13: Abercrombie & Fitch Co. (NYSE:ANF) | B13: AAR Corp. (NYSE:AIR) | C13: Abbott Laboratories (NYSE:ABT) | D13: a.k.a. Brands Holding Corp. (NYSE:AKA) | E13: ABM Industries Incorporated (NYSE:ABM) | F13: ACM Research, Inc. (NASDAQGM:ACMR) | G13: Abbott Laboratories (NYSE:ABT) | H13: Abrdn Healthcare Investors (NYSE:HQH) | I13: ABM Industries Incorporated (NYSE:ABM) | K13: Brinker International, Inc. (NYSE:EAT) | L13: =IF(COUNTIF(A:A,$K13)>0,1,0) -> 1 | M13: =IF(COUNTIF(B:B,$K13)>0,1,0) -> 1 | N13: =IF(COUNTIF(C:C,$K13)>0,1,0) -> 1 | O13: =IF(COUNTIF(D:D,$K13)>0,1,0) -> 1 | P13: =IF(COUNTIF(E:E,$K13)>0,1,0) -> 0 | Q13: =IF(COUNTIF(F:F,$K13)>0,1,0) -> 0 | R13: =IF(COUNTIF(G:G,$K13)>0,1,0) -> 1 | S13: =IF(COUNTIF(H:H,$K13)>0,1,0) -> 1 | T13: =IF(COUNTIF(I:I,$K13)>0,1,0) -> 1 | U13: =SUM(L13:T13) -> 7 | X13: Sample Variance | Y13: 6.3640558
A14: ABM Industries Incorporated (NYSE:ABM) | B14: Abbott Laboratories (NYSE:ABT) | C14: Abrdn Global Dynamic Dividend Fund (NYSE:AGD) | D14: A10 Networks, Inc. (NYSE:ATEN) | E14: Academy Sports and Outdoors, Inc. (NASDAQGS:ASO) | F14: Actuate Therapeutics, Inc. (NASDAQGM:ACTU) | G14: Abercrombie & Fitch Co. (NYSE:ANF) | H14: Abrdn Income Credit Strategies Fund (NYSE:ACP) | I14: Academy Sports and Outdoors, Inc. (NASDAQGS:ASO) | K14: Semtech Corporation (NASDAQGS:SMTC) | L14: =IF(COUNTIF(A:A,$K14)>0,1,0) -> 0 | M14: =IF(COUNTIF(B:B,$K14)>0,1,0) -> 1 | N14: =IF(COUNTIF(C:C,$K14)>0,1,0) -> 1 | O14: =IF(COUNTIF(D:D,$K14)>0,1,0) -> 1 | P14: =IF(COUNTIF(E:E,$K14)>0,1,0) -> 1 | Q14: =IF(COUNTIF(F:F,$K14)>0,1,0) -> 0 | R14: =IF(COUNTIF(G:G,$K14)>0,1,0) -> 1 | S14: =IF(COUNTIF(H:H,$K14)>0,1,0) -> 1 | T14: =IF(COUNTIF(I:I,$K14)>0,1,0) -> 0 | U14: =SUM(L14:T14) -> 6 | X14: Kurtosis | Y14: -1.0396099
A15: Abrdn Global Dynamic Dividend Fund (NYSE:AGD) | B15: AbbVie Inc. (NYSE:ABBV) | C15: Abrdn Healthcare Investors (NYSE:HQH) | D15: A2Z Cust2Mate Solutions Corp. (NASDAQCM:AZ) | E15: Acadia Healthcare Company, Inc. (NASDAQGS:ACHC) | F15: Acuity Brands, Inc. (NYSE:AYI) | G15: ABM Industries Incorporated (NYSE:ABM) | H15: Abrdn Japan Equity Fund Inc (NYSE:JEQ) | I15: Accel Entertainment, Inc. (NYSE:ACEL) | K15: Coinbase Global, Inc. (NASDAQGS:COIN) | L15: =IF(COUNTIF(A:A,$K15)>0,1,0) -> 1 | M15: =IF(COUNTIF(B:B,$K15)>0,1,0) -> 1 | N15: =IF(COUNTIF(C:C,$K15)>0,1,0) -> 1 | O15: =IF(COUNTIF(D:D,$K15)>0,1,0) -> 1 | P15: =IF(COUNTIF(E:E,$K15)>0,1,0) -> 1 | Q15: =IF(COUNTIF(F:F,$K15)>0,1,0) -> 1 | R15: =IF(COUNTIF(G:G,$K15)>0,1,0) -> 1 | S15: =IF(COUNTIF(H:H,$K15)>0,1,0) -> 1 | T15: =IF(COUNTIF(I:I,$K15)>0,1,0) -> 0 | U15: =SUM(L15:T15) -> 8 | X15: Skewness | Y15: -0.35265427
A16: Abrdn Healthcare Investors (NYSE:HQH) | B16: Abercrombie & Fitch Co. (NYSE:ANF) | C16: Abrdn Income Credit Strategies Fund (NYSE:ACP) | D16: AAON, Inc. (NASDAQGS:AAON) | E16: Acadia Realty Trust (NYSE:AKR) | F16: ACV Auctions Inc. (NASDAQGS:ACVA) | G16: Abrdn Global Dynamic Dividend Fund (NYSE:AGD) | H16: Abrdn Life Sciences Investors (NYSE:HQL) | I16: Accenture plc (NYSE:ACN) | K16: Coherent Corp. (NYSE:COHR) | L16: =IF(COUNTIF(A:A,$K16)>0,1,0) -> 0 | M16: =IF(COUNTIF(B:B,$K16)>0,1,0) -> 1 | N16: =IF(COUNTIF(C:C,$K16)>0,1,0) -> 1 | O16: =IF(COUNTIF(D:D,$K16)>0,1,0) -> 1 | P16: =IF(COUNTIF(E:E,$K16)>0,1,0) -> 1 | Q16: =IF(COUNTIF(F:F,$K16)>0,1,0) -> 0 | R16: =IF(COUNTIF(G:G,$K16)>0,1,0) -> 1 | S16: =IF(COUNTIF(H:H,$K16)>0,1,0) -> 1 | T16: =IF(COUNTIF(I:I,$K16)>0,1,0) -> 0 | U16: =SUM(L16:T16) -> 6 | X16: Range | Y16: 9
A17: Abrdn Income Credit Strategies Fund (NYSE:ACP) | B17: ABM Industries Incorporated (NYSE:ABM) | C17: Abrdn Japan Equity Fund Inc (NYSE:JEQ) | D17: AAR Corp. (NYSE:AIR) | E17: Accel Entertainment, Inc. (NYSE:ACEL) | F17: AdaptHealth Corp. (NASDAQCM:AHCO) | G17: Abrdn Healthcare Investors (NYSE:HQH) | H17: Acadia Realty Trust (NYSE:AKR) | I17: ACCO Brands Corporation (NYSE:ACCO) | K17: Tenet Healthcare Corporation (NYSE:THC) | L17: =IF(COUNTIF(A:A,$K17)>0,1,0) -> 1 | M17: =IF(COUNTIF(B:B,$K17)>0,1,0) -> 1 | N17: =IF(COUNTIF(C:C,$K17)>0,1,0) -> 1 | O17: =IF(COUNTIF(D:D,$K17)>0,1,0) -> 0 | P17: =IF(COUNTIF(E:E,$K17)>0,1,0) -> 1 | Q17: =IF(COUNTIF(F:F,$K17)>0,1,0) -> 1 | R17: =IF(COUNTIF(G:G,$K17)>0,1,0) -> 1 | S17: =IF(COUNTIF(H:H,$K17)>0,1,0) -> 0 | T17: =IF(COUNTIF(I:I,$K17)>0,1,0) -> 1 | U17: =SUM(L17:T17) -> 7 | X17: Minimum | Y17: 0
A18: Abrdn Japan Equity Fund Inc (NYSE:JEQ) | B18: Abrdn Japan Equity Fund Inc (NYSE:JEQ) | C18: Abrdn Life Sciences Investors (NYSE:HQL) | D18: Abbott Laboratories (NYSE:ABT) | E18: ACCO Brands Corporation (NYSE:ACCO) | F18: Addus HomeCare Corporation (NASDAQGS:ADUS) | G18: Abrdn Income Credit Strategies Fund (NYSE:ACP) | H18: Accel Entertainment, Inc. (NYSE:ACEL) | I18: ACRES Commercial Realty Corp. (NYSE:ACR) | K18: The GEO Group, Inc. (NYSE:GEO) | L18: =IF(COUNTIF(A:A,$K18)>0,1,0) -> 1 | M18: =IF(COUNTIF(B:B,$K18)>0,1,0) -> 1 | N18: =IF(COUNTIF(C:C,$K18)>0,1,0) -> 1 | O18: =IF(COUNTIF(D:D,$K18)>0,1,0) -> 1 | P18: =IF(COUNTIF(E:E,$K18)>0,1,0) -> 1 | Q18: =IF(COUNTIF(F:F,$K18)>0,1,0) -> 0 | R18: =IF(COUNTIF(G:G,$K18)>0,1,0) -> 0 | S18: =IF(COUNTIF(H:H,$K18)>0,1,0) -> 1 | T18: =IF(COUNTIF(I:I,$K18)>0,1,0) -> 0 | U18: =SUM(L18:T18) -> 6 | X18: Maximum | Y18: 9
A19: Abrdn Life Sciences Investors (NYSE:HQL) | B19: Academy Sports and Outdoors, Inc. (NASDAQGS:ASO) | C19: Acadia Healthcare Company, Inc. (NASDAQGS:ACHC) | D19: AbbVie Inc. (NYSE:ABBV) | E19: ACRES Commercial Realty Corp. (NYSE:ACR) | F19: Adeia Inc. (NASDAQGS:ADEA) | G19: Abrdn Japan Equity Fund Inc (NYSE:JEQ) | H19: ACCO Brands Corporation (NYSE:ACCO) | I19: Acushnet Holdings Corp. (NYSE:GOLF) | K19: Carpenter Technology Corporation (NYSE:CRS) | L19: =IF(COUNTIF(A:A,$K19)>0,1,0) -> 1 | M19: =IF(COUNTIF(B:B,$K19)>0,1,0) -> 1 | N19: =IF(COUNTIF(C:C,$K19)>0,1,0) -> 1 | O19: =IF(COUNTIF(D:D,$K19)>0,1,0) -> 1 | P19: =IF(COUNTIF(E:E,$K19)>0,1,0) -> 0 | Q19: =IF(COUNTIF(F:F,$K19)>0,1,0) -> 1 | R19: =IF(COUNTIF(G:G,$K19)>0,1,0) -> 1 | S19: =IF(COUNTIF(H:H,$K19)>0,1,0) -> 1 | T19: =IF(COUNTIF(I:I,$K19)>0,1,0) -> 0 | U19: =SUM(L19:T19) -> 7 | X19: Sum | Y19: 17753
A20: Abrdn Total Dynamic Dividend Fund (NYSE:AOD) | B20: Acadia Healthcare Company, Inc. (NASDAQGS:ACHC) | C20: ACADIA Pharmaceuticals Inc. (NASDAQGS:ACAD) | D20: Abeona Therapeutics Inc. (NASDAQCM:ABEO) | E20: Acuity Brands, Inc. (NYSE:AYI) | F20: Adient plc (NYSE:ADNT) | G20: Abrdn Life Sciences Investors (NYSE:HQL) | H20: ACI Worldwide, Inc. (NASDAQGS:ACIW) | I20: Adecoagro S.A. (NYSE:AGRO) | K20: RadNet, Inc. (NASDAQGM:RDNT) | L20: =IF(COUNTIF(A:A,$K20)>0,1,0) -> 1 | M20: =IF(COUNTIF(B:B,$K20)>0,1,0) -> 1 | N20: =IF(COUNTIF(C:C,$K20)>0,1,0) -> 0 | O20: =IF(COUNTIF(D:D,$K20)>0,1,0) -> 1 | P20: =IF(COUNTIF(E:E,$K20)>0,1,0) -> 1 | Q20: =IF(COUNTIF(F:F,$K20)>0,1,0) -> 1 | R20: =IF(COUNTIF(G:G,$K20)>0,1,0) -> 0 | S20: =IF(COUNTIF(H:H,$K20)>0,1,0) -> 1 | T20: =IF(COUNTIF(I:I,$K20)>0,1,0) -> 0 | U20: =SUM(L20:T20) -> 6 | X20: Count | Y20: 4456
A21: Academy Sports and Outdoors, Inc. (NASDAQGS:ASO) | B21: ACADIA Pharmaceuticals Inc. (NASDAQGS:ACAD) | C21: Acadia Realty Trust (NYSE:AKR) | D21: Abercrombie & Fitch Co. (NYSE:ANF) | E21: Acushnet Holdings Corp. (NYSE:GOLF) | F21: ADMA Biologics, Inc. (NASDAQGM:ADMA) | G21: Acadia Healthcare Company, Inc. (NASDAQGS:ACHC) | H21: ACNB Corporation (NASDAQCM:ACNB) | I21: Adient plc (NYSE:ADNT) | K21: StepStone Group Inc. (NASDAQGS:STEP) | L21: =IF(COUNTIF(A:A,$K21)>0,1,0) -> 1 | M21: =IF(COUNTIF(B:B,$K21)>0,1,0) -> 1 | N21: =IF(COUNTIF(C:C,$K21)>0,1,0) -> 0 | O21: =IF(COUNTIF(D:D,$K21)>0,1,0) -> 0 | P21: =IF(COUNTIF(E:E,$K21)>0,1,0) -> 1 | Q21: =IF(COUNTIF(F:F,$K21)>0,1,0) -> 0 | R21: =IF(COUNTIF(G:G,$K21)>0,1,0) -> 0 | S21: =IF(COUNTIF(H:H,$K21)>0,1,0) -> 1 | T21: =IF(COUNTIF(I:I,$K21)>0,1,0) -> 0 | U21: =SUM(L21:T21) -> 4
A22: Acadia Healthcare Company, Inc. (NASDAQGS:ACHC) | B22: Acadia Realty Trust (NYSE:AKR) | C22: ACI Worldwide, Inc. (NASDAQGS:ACIW) | D22: ABM Industries Incorporated (NYSE:ABM) | E22: AdaptHealth Corp. (NASDAQCM:AHCO) | F22: ADT Inc. (NYSE:ADT) | G22: ACADIA Pharmaceuticals Inc. (NASDAQGS:ACAD) | H22: ACRES Commercial Realty Corp. (NYSE:ACR) | I22: Adobe Inc. (NASDAQGS:ADBE) | K22: Fair Isaac Corporation (NYSE:FICO) | L22: =IF(COUNTIF(A:A,$K22)>0,1,0) -> 1 | M22: =IF(COUNTIF(B:B,$K22)>0,1,0) -> 1 | N22: =IF(COUNTIF(C:C,$K22)>0,1,0) -> 1 | O22: =IF(COUNTIF(D:D,$K22)>0,1,0) -> 1 | P22: =IF(COUNTIF(E:E,$K22)>0,1,0) -> 0 | Q22: =IF(COUNTIF(F:F,$K22)>0,1,0) -> 0 | R22: =IF(COUNTIF(G:G,$K22)>0,1,0) -> 1 | S22: =IF(COUNTIF(H:H,$K22)>0,1,0) -> 1 | T22: =IF(COUNTIF(I:I,$K22)>0,1,0) -> 1 | U22: =SUM(L22:T22) -> 7
A23: ACADIA Pharmaceuticals Inc. (NASDAQGS:ACAD) | B23: Accel Entertainment, Inc. (NYSE:ACEL) | C23: ACRES Commercial Realty Corp. (NYSE:ACR) | D23: Academy Sports and Outdoors, Inc. (NASDAQGS:ASO) | E23: Adecoagro S.A. (NYSE:AGRO) | F23: Adtalem Global Education Inc. (NYSE:ATGE) | G23: Acadia Realty Trust (NYSE:AKR) | H23: Acushnet Holdings Corp. (NYSE:GOLF) | I23: AECOM (NYSE:ACM) | K23: Royal Caribbean Cruises Ltd. (NYSE:RCL) | L23: =IF(COUNTIF(A:A,$K23)>0,1,0) -> 1 | M23: =IF(COUNTIF(B:B,$K23)>0,1,0) -> 1 | N23: =IF(COUNTIF(C:C,$K23)>0,1,0) -> 1 | O23: =IF(COUNTIF(D:D,$K23)>0,1,0) -> 1 | P23: =IF(COUNTIF(E:E,$K23)>0,1,0) -> 1 | Q23: =IF(COUNTIF(F:F,$K23)>0,1,0) -> 0 | R23: =IF(COUNTIF(G:G,$K23)>0,1,0) -> 1 | S23: =IF(COUNTIF(H:H,$K23)>0,1,0) -> 1 | T23: =IF(COUNTIF(I:I,$K23)>0,1,0) -> 0 | U23: =SUM(L23:T23) -> 7
A24: Accel Entertainment, Inc. (NYSE:ACEL) | B24: Accenture plc (NYSE:ACN) | C24: Actuate Therapeutics, Inc. (NASDAQGM:ACTU) | D24: ACADIA Pharmaceuticals Inc. (NASDAQGS:ACAD) | E24: Adeia Inc. (NASDAQGS:ADEA) | F24: Advance Auto Parts, Inc. (NYSE:AAP) | G24: Accenture plc (NYSE:ACN) | H24: ACV Auctions Inc. (NASDAQGS:ACVA) | I24: AerCap Holdings N.V. (NYSE:AER) | K24: United Airlines Holdings, Inc. (NASDAQGS:UAL) | L24: =IF(COUNTIF(A:A,$K24)>0,1,0) -> 1 | M24: =IF(COUNTIF(B:B,$K24)>0,1,0) -> 1 | N24: =IF(COUNTIF(C:C,$K24)>0,1,0) -> 0 | O24: =IF(COUNTIF(D:D,$K24)>0,1,0) -> 1 | P24: =IF(COUNTIF(E:E,$K24)>0,1,0) -> 0 | Q24: =IF(COUNTIF(F:F,$K24)>0,1,0) -> 1 | R24: =IF(COUNTIF(G:G,$K24)>0,1,0) -> 0 | S24: =IF(COUNTIF(H:H,$K24)>0,1,0) -> 1 | T24: =IF(COUNTIF(I:I,$K24)>0,1,0) -> 0 | U24: =SUM(L24:T24) -> 5
A25: Accenture plc (NYSE:ACN) | B25: ACCO Brands Corporation (NYSE:ACCO) | C25: Acuity Brands, Inc. (NYSE:AYI) | D25: Acadia Realty Trust (NYSE:AKR) | E25: Adient plc (NYSE:ADNT) | F25: Advanced Drainage Systems, Inc. (NYSE:WMS) | G25: ACI Worldwide, Inc. (NASDAQGS:ACIW) | H25: AdaptHealth Corp. (NASDAQCM:AHCO) | I25: AeroVironment, Inc. (NASDAQGS:AVAV) | K25: The Baldwin Insurance Group, Inc. (NASDAQGS:BWIN) | L25: =IF(COUNTIF(A:A,$K25)>0,1,0) -> 0 | M25: =IF(COUNTIF(B:B,$K25)>0,1,0) -> 1 | N25: =IF(COUNTIF(C:C,$K25)>0,1,0) -> 1 | O25: =IF(COUNTIF(D:D,$K25)>0,1,0) -> 1 | P25: =IF(COUNTIF(E:E,$K25)>0,1,0) -> 0 | Q25: =IF(COUNTIF(F:F,$K25)>0,1,0) -> 0 | R25: =IF(COUNTIF(G:G,$K25)>0,1,0) -> 1 | S25: =IF(COUNTIF(H:H,$K25)>0,1,0) -> 1 | T25: =IF(COUNTIF(I:I,$K25)>0,1,0) -> 0 | U25: =SUM(L25:T25) -> 5
A26: ACI Worldwide, Inc. (NASDAQGS:ACIW) | B26: ACI Worldwide, Inc. (NASDAQGS:ACIW) | C26: ACV Auctions Inc. (NASDAQGS:ACVA) | D26: Accel Entertainment, Inc. (NYSE:ACEL) | E26: ADMA Biologics, Inc. (NASDAQGM:ADMA) | F26: Aehr Test Systems, Inc. (NASDAQCM:AEHR) | G26: ACM Research, Inc. (NASDAQGM:ACMR) | H26: Adaptive Biotechnologies Corporation (NASDAQGS:ADPT) | I26: Affiliated Managers Group, Inc. (NYSE:AMG) | K26: Cinemark Holdings, Inc. (NYSE:CNK) | L26: =IF(COUNTIF(A:A,$K26)>0,1,0) -> 1 | M26: =IF(COUNTIF(B:B,$K26)>0,1,0) -> 1 | N26: =IF(COUNTIF(C:C,$K26)>0,1,0) -> 1 | O26: =IF(COUNTIF(D:D,$K26)>0,1,0) -> 1 | P26: =IF(COUNTIF(E:E,$K26)>0,1,0) -> 1 | Q26: =IF(COUNTIF(F:F,$K26)>0,1,0) -> 0 | R26: =IF(COUNTIF(G:G,$K26)>0,1,0) -> 1 | S26: =IF(COUNTIF(H:H,$K26)>0,1,0) -> 0 | T26: =IF(COUNTIF(I:I,$K26)>0,1,0) -> 0 | U26: =SUM(L26:T26) -> 6
A27: ACM Research, Inc. (NASDAQGM:ACMR) | B27: ACM Research, Inc. (NASDAQGM:ACMR) | C27: Adams Diversified Equity Fund, Inc. (NYSE:ADX) | D27: Accenture plc (NYSE:ACN) | E27: Adobe Inc. (NASDAQGS:ADBE) | F27: AerCap Holdings N.V. (NYSE:AER) | G27: ACNB Corporation (NASDAQCM:ACNB) | H27: Adecoagro S.A. (NYSE:AGRO) | I27: Affinity Bancshares, Inc. (NASDAQCM:AFBI) | K27: ACI Worldwide, Inc. (NASDAQGS:ACIW) | L27: =IF(COUNTIF(A:A,$K27)>0,1,0) -> 1 | M27: =IF(COUNTIF(B:B,$K27)>0,1,0) -> 1 | N27: =IF(COUNTIF(C:C,$K27)>0,1,0) -> 1 | O27: =IF(COUNTIF(D:D,$K27)>0,1,0) -> 1 | P27: =IF(COUNTIF(E:E,$K27)>0,1,0) -> 0 | Q27: =IF(COUNTIF(F:F,$K27)>0,1,0) -> 1 | R27: =IF(COUNTIF(G:G,$K27)>0,1,0) -> 1 | S27: =IF(COUNTIF(H:H,$K27)>0,1,0) -> 1 | T27: =IF(COUNTIF(I:I,$K27)>0,1,0) -> 0 | U27: =SUM(L27:T27) -> 7
A28: ACNB Corporation (NASDAQCM:ACNB) | B28: ACNB Corporation (NASDAQCM:ACNB) | C28: Adams Natural Resources Fund, Inc. (NYSE:PEO) | D28: ACCO Brands Corporation (NYSE:ACCO) | E28: ADT Inc. (NYSE:ADT) | F28: AeroVironment, Inc. (NASDAQGS:AVAV) | G28: Acuity Brands, Inc. (NYSE:AYI) | H28: ADMA Biologics, Inc. (NASDAQGM:ADMA) | I28: Aflac Incorporated (NYSE:AFL) | K28: SL Green Realty Corp. (NYSE:SLG) | L28: =IF(COUNTIF(A:A,$K28)>0,1,0) -> 0 | M28: =IF(COUNTIF(B:B,$K28)>0,1,0) -> 1 | N28: =IF(COUNTIF(C:C,$K28)>0,1,0) -> 1 | O28: =IF(COUNTIF(D:D,$K28)>0,1,0) -> 1 | P28: =IF(COUNTIF(E:E,$K28)>0,1,0) -> 1 | Q28: =IF(COUNTIF(F:F,$K28)>0,1,0) -> 0 | R28: =IF(COUNTIF(G:G,$K28)>0,1,0) -> 1 | S28: =IF(COUNTIF(H:H,$K28)>0,1,0) -> 0 | T28: =IF(COUNTIF(I:I,$K28)>0,1,0) -> 0 | U28: =SUM(L28:T28) -> 5
A29: ACRES Commercial Realty Corp. (NYSE:ACR) | B29: ACRES Commercial Realty Corp. (NYSE:ACR) | C29: AdaptHealth Corp. (NASDAQCM:AHCO) | D29: ACI Worldwide, Inc. (NASDAQGS:ACIW) | E29: Adtalem Global Education Inc. (NYSE:ATGE) | F29: AerSale Corporation (NASDAQCM:ASLE) | G29: Acushnet Holdings Corp. (NYSE:GOLF) | H29: Adobe Inc. (NASDAQGS:ADBE) | I29: Agilent Technologies, Inc. (NYSE:A) | K29: EchoStar Corporation (NASDAQGS:SATS) | L29: =IF(COUNTIF(A:A,$K29)>0,1,0) -> 0 | M29: =IF(COUNTIF(B:B,$K29)>0,1,0) -> 1 | N29: =IF(COUNTIF(C:C,$K29)>0,1,0) -> 1 | O29: =IF(COUNTIF(D:D,$K29)>0,1,0) -> 1 | P29: =IF(COUNTIF(E:E,$K29)>0,1,0) -> 0 | Q29: =IF(COUNTIF(F:F,$K29)>0,1,0) -> 1 | R29: =IF(COUNTIF(G:G,$K29)>0,1,0) -> 0 | S29: =IF(COUNTIF(H:H,$K29)>0,1,0) -> 0 | T29: =IF(COUNTIF(I:I,$K29)>0,1,0) -> 0 | U29: =SUM(L29:T29) -> 4
A30: Acuity Brands, Inc. (NYSE:AYI) | B30: Acuity Brands, Inc. (NYSE:AYI) | C30: Adaptive Biotechnologies Corporation (NASDAQGS:ADPT) | D30: ACNB Corporation (NASDAQCM:ACNB) | E30: Advance Auto Parts, Inc. (NYSE:AAP) | F30: Affiliated Managers Group, Inc. (NYSE:AMG) | G30: ACV Auctions Inc. (NASDAQGS:ACVA) | H30: ADS-TEC Energy PLC (NASDAQCM:ADSE) | I30: Air Transport Services Group, Inc. (NASDAQGS:ATSG) | K30: Construction Partners, Inc. (NASDAQGS:ROAD) | L30: =IF(COUNTIF(A:A,$K30)>0,1,0) -> 1 | M30: =IF(COUNTIF(B:B,$K30)>0,1,0) -> 1 | N30: =IF(COUNTIF(C:C,$K30)>0,1,0) -> 0 | O30: =IF(COUNTIF(D:D,$K30)>0,1,0) -> 1 | P30: =IF(COUNTIF(E:E,$K30)>0,1,0) -> 1 | Q30: =IF(COUNTIF(F:F,$K30)>0,1,0) -> 0 | R30: =IF(COUNTIF(G:G,$K30)>0,1,0) -> 0 | S30: =IF(COUNTIF(H:H,$K30)>0,1,0) -> 0 | T30: =IF(COUNTIF(I:I,$K30)>0,1,0) -> 1 | U30: =SUM(L30:T30) -> 5
A31: Acushnet Holdings Corp. (NYSE:GOLF) | B31: Acushnet Holdings Corp. (NYSE:GOLF) | C31: Addus HomeCare Corporation (NASDAQGS:ADUS) | D31: ACRES Commercial Realty Corp. (NYSE:ACR) | E31: Advanced Drainage Systems, Inc. (NYSE:WMS) | F31: Affirm Holdings, Inc. (NASDAQGS:AFRM) | G31: AdaptHealth Corp. (NASDAQCM:AHCO) | H31: ADT Inc. (NYSE:ADT) | I31: Akamai Technologies, Inc. (NASDAQGS:AKAM) | K31: Dycom Industries, Inc. (NYSE:DY) | L31: =IF(COUNTIF(A:A,$K31)>0,1,0) -> 1 | M31: =IF(COUNTIF(B:B,$K31)>0,1,0) -> 1 | N31: =IF(COUNTIF(C:C,$K31)>0,1,0) -> 0 | O31: =IF(COUNTIF(D:D,$K31)>0,1,0) -> 1 | P31: =IF(COUNTIF(E:E,$K31)>0,1,0) -> 0 | Q31: =IF(COUNTIF(F:F,$K31)>0,1,0) -> 0 | R31: =IF(COUNTIF(G:G,$K31)>0,1,0) -> 0 | S31: =IF(COUNTIF(H:H,$K31)>0,1,0) -> 0 | T31: =IF(COUNTIF(I:I,$K31)>0,1,0) -> 0 | U31: =SUM(L31:T31) -> 3
A32: Adams Diversified Equity Fund, Inc. (NYSE:ADX) | B32: ACV Auctions Inc. (NASDAQGS:ACVA) | C32: ADMA Biologics, Inc. (NASDAQGM:ADMA) | D32: Acrivon Therapeutics, Inc. (NASDAQGM:ACRV) | E32: Advanced Energy Industries, Inc. (NASDAQGS:AEIS) | F32: Afya Limited (NASDAQGS:AFYA) | G32: Adaptive Biotechnologies Corporation (NASDAQGS:ADPT) | H32: Adtalem Global Education Inc. (NYSE:ATGE) | I32: Alaska Air Group, Inc. (NYSE:ALK) | K32: Mercury General Corporation (NYSE:MCY) | L32: =IF(COUNTIF(A:A,$K32)>0,1,0) -> 1 | M32: =IF(COUNTIF(B:B,$K32)>0,1,0) -> 1 | N32: =IF(COUNTIF(C:C,$K32)>0,1,0) -> 1 | O32: =IF(COUNTIF(D:D,$K32)>0,1,0) -> 1 | P32: =IF(COUNTIF(E:E,$K32)>0,1,0) -> 1 | Q32: =IF(COUNTIF(F:F,$K32)>0,1,0) -> 0 | R32: =IF(COUNTIF(G:G,$K32)>0,1,0) -> 1 | S32: =IF(COUNTIF(H:H,$K32)>0,1,0) -> 1 | T32: =IF(COUNTIF(I:I,$K32)>0,1,0) -> 0 | U32: =SUM(L32:T32) -> 7
... A41: Adtalem Global Education Inc. (NYSE:ATGE) | B41: Adtalem Global Education Inc. (NYSE:ATGE) | C41: AECOM (NYSE:ACM) | D41: Adeia Inc. (NASDAQGS:ADEA) | E41: Air Products and Chemicals, Inc. (NYSE:APD) | F41: Akamai Technologies, Inc. (NASDAQGS:AKAM) | G41: Advanced Micro Devices, Inc. (NASDAQGS:AMD) | H41: Affirm Holdings, Inc. (NASDAQGS:AFRM) | I41: Alpha Star Acquisition Corporation (NASDAQGM:ALSA) | K41: Nu Holdings Ltd. (NYSE:NU) | L41: =IF(COUNTIF(A:A,$K41)>0,1,0) -> 1 | M41: =IF(COUNTIF(B:B,$K41)>0,1,0) -> 1 | N41: =IF(COUNTIF(C:C,$K41)>0,1,0) -> 1 | O41: =IF(COUNTIF(D:D,$K41)>0,1,0) -> 1 | P41: =IF(COUNTIF(E:E,$K41)>0,1,0) -> 1 | Q41: =IF(COUNTIF(F:F,$K41)>0,1,0) -> 0 | R41: =IF(COUNTIF(G:G,$K41)>0,1,0) -> 1 | S41: =IF(COUNTIF(H:H,$K41)>0,1,0) -> 0 | T41: =IF(COUNTIF(I:I,$K41)>0,1,0) -> 0 | U41: =SUM(L41:T41) -> 6
A42: Advance Auto Parts, Inc. (NYSE:AAP) | B42: ADTRAN Holdings, Inc. (NASDAQGS:ADTN) | C42: AerSale Corporation (NASDAQCM:ASLE) | D42: Adient plc (NYSE:ADNT) | E42: AirSculpt Technologies, Inc. (NASDAQGM:AIRS) | F42: Albany International Corp. (NYSE:AIN) | G42: AdvanSix Inc. (NYSE:ASIX) | H42: AG Mortgage Investment Trust, Inc. (NYSE:MITT) | I42: Alphabet Inc. (NASDAQGS:GOOGL)
A43: Advanced Drainage Systems, Inc. (NYSE:WMS) | B43: Advance Auto Parts, Inc. (NYSE:AAP) | C43: Affinity Bancshares, Inc. (NASDAQCM:AFBI) | D43: ADMA Biologics, Inc. (NASDAQGM:ADMA) | E43: Akamai Technologies, Inc. (NASDAQGS:AKAM) | F43: Albertsons Companies, Inc. (NYSE:ACI) | G43: Advent Convertible and Income Fund (NYSE:AVK) | H43: AGNC Investment Corp. (NASDAQGS:AGNC) | I43: Alphatec Holdings, Inc. (NASDAQGS:ATEC)
A44: Advanced Energy Industries, Inc. (NASDAQGS:AEIS) | B44: Advanced Drainage Systems, Inc. (NYSE:WMS) | C44: Affirm Holdings, Inc. (NASDAQGS:AFRM) | D44: ADS-TEC Energy PLC (NASDAQCM:ADSE) | E44: Alamo Group Inc. (NYSE:ALG) | F44: Alico, Inc. (NASDAQGS:ALCO) | G44: Advent Technologies Holdings, Inc. (NASDAQCM:ADN) | H44: Agnico Eagle Mines Limited (NYSE:AEM) | I44: Altria Group, Inc. (NYSE:MO)
A45: Advanced Flower Capital Inc. (NASDAQGM:AFCG) | B45: Advanced Energy Industries, Inc. (NASDAQGS:AEIS) | C45: AG Mortgage Investment Trust, Inc. (NYSE:MITT) | D45: ADT Inc. (NYSE:ADT) | E45: Alarm.com Holdings, Inc. (NASDAQGS:ALRM) | F45: Align Technology, Inc. (NASDAQGS:ALGN) | G45: AECOM (NYSE:ACM) | H45: Agree Realty Corporation (NYSE:ADC) | I45: Amdocs Limited (NASDAQGS:DOX)
A46: Advanced Micro Devices, Inc. (NASDAQGS:AMD) | B46: Advanced Flower Capital Inc. (NASDAQGM:AFCG) | C46: Agios Pharmaceuticals, Inc. (NASDAQGS:AGIO) | D46: Adtalem Global Education Inc. (NYSE:ATGE) | E46: Albany International Corp. (NYSE:AIN) | F46: Alkermes plc (NASDAQGS:ALKS) | G46: AerSale Corporation (NASDAQCM:ASLE) | H46: Airbnb, Inc. (NASDAQGS:ABNB) | I46: American Express Company (NYSE:AXP)
A47: AdvanSix Inc. (NYSE:ASIX) | B47: Advanced Micro Devices, Inc. (NASDAQGS:AMD) | C47: AGNC Investment Corp. (NASDAQGS:AGNC) | D47: ADTRAN Holdings, Inc. (NASDAQGS:ADTN) | E47: Albertsons Companies, Inc. (NYSE:ACI) | F47: Allegiant Travel Company (NASDAQGS:ALGT) | G47: Affinity Bancshares, Inc. (NASDAQCM:AFBI) | H47: Airgain, Inc. (NASDAQCM:AIRG) | I47: American International Group, Inc. (NYSE:AIG)
A48: Advent Convertible and Income Fund (NYSE:AVK) | B48: AdvanSix Inc. (NYSE:ASIX) | C48: Agnico Eagle Mines Limited (NYSE:AEM) | D48: Advance Auto Parts, Inc. (NYSE:AAP) | E48: Alcoa Corporation (NYSE:AA) | F48: Allegion plc (NYSE:ALLE) | G48: Affirm Holdings, Inc. (NASDAQGS:AFRM) | H48: Alamo Group Inc. (NYSE:ALG) | I48: American Outdoor Brands, Inc. (NASDAQGS:AOUT)
A49: AECOM (NYSE:ACM) | B49: Advent Technologies Holdings, Inc. (NASDAQCM:ADN) | C49: Agriculture & Natural Solutions Acquisition Corporation (NASDAQGM:ANSC) | D49: Advanced Drainage Systems, Inc. (NYSE:WMS) | E49: Alibaba Group Holding Limited (NYSE:BABA) | F49: Alliant Energy Corporation (NASDAQGS:LNT) | G49: Afya Limited (NASDAQGS:AFYA) | H49: Albany International Corp. (NYSE:AIN) | I49: American Vanguard Corporation (NYSE:AVD)
A50: Aehr Test Systems, Inc. (NASDAQCM:AEHR) | B50: AECOM (NYSE:ACM) | C50: AI Transportation Acquisition Corp (NASDAQCM:AITR) | D50: Advanced Energy Industries, Inc. (NASDAQGS:AEIS) | E50: Allegion plc (NYSE:ALLE) | F50: Allient Inc. (NASDAQGM:ALNT) | G50: Agilent Technologies, Inc. (NYSE:A) | H50: Alcoa Corporation (NYSE:AA) | I50: American Woodmark Corporation (NASDAQGS:AMWD)
A51: AerCap Holdings N.V. (NYSE:AER) | B51: AerCap Holdings N.V. (NYSE:AER) | C51: Aimei Health Technology Co., Ltd (NASDAQGM:AFJK) | D51: Advanced Flower Capital Inc. (NASDAQGM:AFCG) | E51: ALLETE, Inc. (NYSE:ALE) | F51: Allison Transmission Holdings, Inc. (NYSE:ALSN) | G51: Agilysys, Inc. (NASDAQGS:AGYS) | H51: Alerus Financial Corporation (NASDAQCM:ALRS) | I51: Ameriprise Financial, Inc. (NYSE:AMP)
A52: AeroVironment, Inc. (NASDAQGS:AVAV) | B52: AeroVironment, Inc. (NASDAQGS:AVAV) | C52: Air Products and Chemicals, Inc. (NYSE:APD) | D52: Advanced Micro Devices, Inc. (NASDAQGS:AMD) | E52: Alliance Resource Partners, L.P. (NASDAQGS:ARLP) | F52: Ally Financial Inc. (NYSE:ALLY) | G52: Agios Pharmaceuticals, Inc. (NASDAQGS:AGIO) | H52: Alexander & Baldwin, Inc. (NYSE:ALEX) | I52: AMERISAFE, Inc. (NASDAQGS:AMSF)
A53: AerSale Corporation (NASDAQCM:ASLE) | B53: Affiliated Managers Group, Inc. (NYSE:AMG) | C53: Air T, Inc. (NASDAQCM:AIRT) | D53: AdvanSix Inc. (NYSE:ASIX) | E53: Alliant Energy Corporation (NASDAQGS:LNT) | F53: Alpha and Omega Semiconductor Limited (NASDAQGS:AOSL) | G53: Agnico Eagle Mines Limited (NYSE:AEM) | H53: Alexander's, Inc. (NYSE:ALX) | I53: AMETEK, Inc. (NYSE:AME)
... A1084: Haemonetics Corporation (NYSE:HAE) | B1084: General Motors Company (NYSE:GM) | C1084: NexPoint Diversified Real Estate Trust (NYSE:NXDT) | D1084: General Mills, Inc. (NYSE:GIS) | E1084: ReNew Energy Global Plc (NASDAQGS:RNW) | F1084: Textron Inc. (NYSE:TXT) | G1084: MongoDB, Inc. (NASDAQGM:MDB) | H1084: Oscar Health, Inc. (NYSE:OSCR) | I1084: Zymeworks Inc. (NASDAQGS:ZYME)
A1085: Hagerty, Inc. (NYSE:HGTY) | B1085: Genesco Inc. (NYSE:GCO) | C1085: NexPoint Real Estate Finance, Inc. (NYSE:NREF) | D1085: General Motors Company (NYSE:GM) | E1085: Reservoir Media, Inc. (NASDAQGM:RSVR) | F1085: TG Therapeutics, Inc. (NASDAQCM:TGTX) | G1085: Monroe Capital Corporation (NASDAQGS:MRCC) | H1085: Oshkosh Corporation (NYSE:OSK)
A1086: Halliburton Company (NYSE:HAL) | B1086: Genesis Energy, L.P. (NYSE:GEL) | C1086: Nexstar Media Group, Inc. (NASDAQGS:NXST) | D1086: Genesco Inc. (NYSE:GCO) | E1086: Resideo Technologies, Inc. (NYSE:REZI) | F1086: The Boston Beer Company, Inc. (NYSE:SAM) | G1086: Monte Rosa Therapeutics, Inc. (NASDAQGS:GLUE) | H1086: Ouster, Inc. (NYSE:OUST)
A1087: Halozyme Therapeutics, Inc. (NASDAQGS:HALO) | B1087: Genie Energy Ltd. (NYSE:GNE) | C1087: NextEra Energy, Inc. (NYSE:NEE) | D1087: Genesis Energy, L.P. (NYSE:GEL) | E1087: ResMed Inc. (NYSE:RMD) | F1087: The Brink's Company (NYSE:BCO) | G1087: Montrose Environmental Group, Inc. (NYSE:MEG) | H1087: Outbrain Inc. (NASDAQGS:OB)
A1088: Hamilton Beach Brands Holding Company (NYSE:HBB) | B1088: Genius Sports Limited (NYSE:GENI) | C1088: NextNav Inc. (NASDAQCM:NN) | D1088: Genie Energy Ltd. (NYSE:GNE) | E1088: Retail Opportunity Investments Corp. (NASDAQGS:ROIC) | F1088: The Buckle, Inc. (NYSE:BKE) | G1088: Moody's Corporation (NYSE:MCO) | H1088: OUTFRONT Media Inc. (NYSE:OUT)
A1089: Hamilton Insurance Group, Ltd. (NYSE:HG) | B1089: Genpact Limited (NYSE:G) | C1089: Nextracker Inc. (NASDAQGS:NXT) | D1089: Genius Sports Limited (NYSE:GENI) | E1089: REV Group, Inc. (NYSE:REVG) | F1089: The Cheesecake Factory Incorporated (NASDAQGS:CAKE) | G1089: Morgan Stanley (NYSE:MS) | H1089: Owens & Minor, Inc. (NYSE:OMI)
A1090: Hamilton Lane Incorporated (NASDAQGS:HLNE) | B1090: Gentex Corporation (NASDAQGS:GNTX) | C1090: Nicolet Bankshares, Inc. (NYSE:NIC) | D1090: Gentex Corporation (NASDAQGS:GNTX) | E1090: Rexford Industrial Realty, Inc. (NYSE:REXR) | F1090: The Children's Place, Inc. (NASDAQGS:PLCE) | G1090: Morgan Stanley Direct Lending Fund (NYSE:MSDL) | H1090: Owens Corning (NYSE:OC)
A1091: Hancock Whitney Corporation (NASDAQGS:HWC) | B1091: Gentherm Incorporated (NASDAQGS:THRM) | C1091: NIP Group Inc. (NASDAQGM:NIPG) | D1091: Gentherm Incorporated (NASDAQGS:THRM) | E1091: Reynolds Consumer Products Inc. (NASDAQGS:REYN) | F1091: The Eastern Company (NASDAQGM:EML) | G1091: Morgan Stanley Emerging Markets Debt Fund, Inc. (NYSE:MSD) | H1091: Oxford Lane Capital Corp. (NASDAQGS:OXLC)
A1092: Hanmi Financial Corporation (NASDAQGS:HAFC) | B1092: Genuine Parts Company (NYSE:GPC) | C1092: NL Industries, Inc. (NYSE:NL) | D1092: Genuine Parts Company (NYSE:GPC) | E1092: RGC Resources, Inc. (NASDAQGM:RGCO) | F1092: The Ensign Group, Inc. (NASDAQGS:ENSG) | G1092: Morgan Stanley India Investment Fund, Inc. (NYSE:IIF) | H1092: P10, Inc. (NYSE:PX)
A1093: Hanover Bancorp, Inc. (NASDAQGS:HNVR) | B1093: Genworth Financial, Inc. (NYSE:GNW) | C1093: nLIGHT, Inc. (NASDAQGS:LASR) | D1093: GeoPark Limited (NYSE:GPRK) | E1093: Rigel Pharmaceuticals, Inc. (NASDAQGS:RIGL) | F1093: The Gap, Inc. (NYSE:GAP) | G1093: Morningstar, Inc. (NASDAQGS:MORN) | H1093: Pacira BioSciences, Inc. (NASDAQGS:PCRX)
A1094: HarborOne Bancorp, Inc. (NASDAQGS:HONE) | B1094: GeoPark Limited (NYSE:GPRK) | C1094: Norfolk Southern Corporation (NYSE:NSC) | D1094: German American Bancorp, Inc. (NASDAQGS:GABC) | E1094: Rithm Capital Corp. (NYSE:RITM) | F1094: The Goodyear Tire & Rubber Company (NASDAQGS:GT) | G1094: Motorola Solutions, Inc. (NYSE:MSI) | H1094: Packaging Corporation of America (NYSE:PKG)
A1095: Harley-Davidson, Inc. (NYSE:HOG) | B1095: German American Bancorp, Inc. (NASDAQGS:GABC) | C1095: Northern Oil and Gas, Inc. (NYSE:NOG) | D1095: Getty Realty Corp. (NYSE:GTY) | E1095: Roblox Corporation (NYSE:RBLX) | F1095: The Greenbrier Companies, Inc. (NYSE:GBX) | G1095: MPLX LP (NYSE:MPLX) | H1095: PACS Group, Inc. (NYSE:PACS)
A1096: Harmonic Inc. (NASDAQGS:HLIT) | B1096: Getty Realty Corp. (NYSE:GTY) | C1096: Northern Trust Corporation (NASDAQGS:NTRS) | D1096: GH Research PLC (NASDAQGM:GHRS) | E1096: Rockwell Automation, Inc. (NYSE:ROK) | F1096: The Hain Celestial Group, Inc. (NASDAQGS:HAIN) | G1096: MSA Safety Incorporated (NYSE:MSA) | H1096: Pactiv Evergreen Inc. (NASDAQGS:PTVE)
... A1269: Itron, Inc. (NASDAQGS:ITRI) | B1269: IBEX Limited (NASDAQGM:IBEX) | C1269: Prosperity Bancshares, Inc. (NYSE:PB) | D1269: Illumina, Inc. (NASDAQGS:ILMN) | E1269: The Cigna Group (NYSE:CI) | F1269: Zumiez Inc. (NASDAQGS:ZUMZ) | G1269: PCB Bancorp (NASDAQGS:PCB) | H1269: Safety Insurance Group, Inc. (NASDAQGS:SAFT)
A1270: ITT Inc. (NYSE:ITT) | B1270: Ibotta, Inc. (NYSE:IBTA) | C1270: Protagonist Therapeutics, Inc. (NASDAQGM:PTGX) | D1270: IMAX Corporation (NYSE:IMAX) | E1270: The Cooper Companies, Inc. (NASDAQGS:COO) | G1270: PDF Solutions, Inc. (NASDAQGS:PDFS) | H1270: Sage Therapeutics, Inc. (NASDAQGM:SAGE)
A1271: Ituran Location and Control Ltd. (NASDAQGS:ITRN) | B1271: Icahn Enterprises L.P. (NASDAQGS:IEP) | C1271: Provident Financial Holdings, Inc. (NASDAQGS:PROV) | D1271: Immatics N.V. (NASDAQCM:IMTX) | E1271: The Duckhorn Portfolio, Inc. (NYSE:NAPA) | G1271: Peakstone Realty Trust (NYSE:PKST) | H1271: Salesforce, Inc. (NYSE:CRM)
A1272: J&J Snack Foods Corp. (NASDAQGS:JJSF) | B1272: ICC Holdings, Inc. (NASDAQCM:ICCH) | C1272: Provident Financial Services, Inc. (NYSE:PFS) | D1272: Immunocore Holdings plc (NASDAQGS:IMCR) | E1272: The Ensign Group, Inc. (NASDAQGS:ENSG) | G1272: Peapack-Gladstone Financial Corporation (NASDAQGS:PGC) | H1272: Samfine Creation Holdings Group Limited (NASDAQCM:SFHG)
A1273: J.B. Hunt Transport Services, Inc. (NASDAQGS:JBHT) | B1273: ICF International, Inc. (NASDAQGS:ICFI) | C1273: Prudential Financial, Inc. (NYSE:PRU) | D1273: Immunome, Inc. (NASDAQCM:IMNM) | E1273: The Gap, Inc. (NYSE:GAP) | G1273: Pebblebrook Hotel Trust (NYSE:PEB) | H1273: Samsara Inc. (NYSE:IOT)
A1274: J.Jill, Inc. (NYSE:JILL) | B1274: Ichor Holdings, Ltd. (NASDAQGS:ICHR) | C1274: PTC Inc. (NASDAQGS:PTC) | D1274: Immunovant, Inc. (NASDAQGS:IMVT) | E1274: The GEO Group, Inc. (NYSE:GEO) | G1274: Pediatrix Medical Group, Inc. (NYSE:MD) | H1274: Sarepta Therapeutics, Inc. (NASDAQGS:SRPT)
A1275: Jabil Inc. (NYSE:JBL) | B1275: ICON Public Limited Company (NASDAQGS:ICLR) | C1275: PTC Therapeutics, Inc. (NASDAQGS:PTCT) | D1275: Impinj, Inc. (NASDAQGS:PI) | E1275: The Gorman-Rupp Company (NYSE:GRC) | G1275: Peloton Interactive, Inc. (NASDAQGS:PTON) | H1275: Savers Value Village, Inc. (NYSE:SVV)
A1276: Jack Henry & Associates, Inc. (NASDAQGS:JKHY) | B1276: ICU Medical, Inc. (NASDAQGS:ICUI) | C1276: Public Service Enterprise Group Incorporated (NYSE:PEG) | D1276: Inari Medical, Inc. (NASDAQGS:NARI) | E1276: The Greenbrier Companies, Inc. (NYSE:GBX) | G1276: Penguin Solutions, Inc. (NASDAQGS:PENG) | H1276: Schlumberger Limited (NYSE:SLB)
A1277: Jacobs Solutions Inc. (NYSE:J) | B1277: IDACORP, Inc. (NYSE:IDA) | C1277: Pulse Biosciences, Inc. (NASDAQCM:PLSE) | D1277: Incyte Corporation (NASDAQGS:INCY) | E1277: The Hackett Group, Inc. (NASDAQGS:HCKT) | G1277: PennantPark Floating Rate Capital Ltd. (NYSE:PFLT) | H1277: Science Applications International Corporation (NASDAQGS:SAIC)
A1278: JAKKS Pacific, Inc. (NASDAQGS:JAKK) | B1278: IDEX Corporation (NYSE:IEX) | C1278: Pure Cycle Corporation (NASDAQCM:PCYO) | D1278: Independence Realty Trust, Inc. (NYSE:IRT) | E1278: The Hain Celestial Group, Inc. (NASDAQGS:HAIN) | G1278: PennantPark Investment Corporation (NYSE:PNNT) | H1278: Scienture Holdings, Inc. (NASDAQCM:SCNX)
A1279: Janus Henderson Group plc (NYSE:JHG) | B1279: IDEXX Laboratories, Inc. (NASDAQGS:IDXX) | C1279: Putnam Managed Municipal Income Trust (NYSE:PMM) | D1279: Independent Bank Corp. (NASDAQGS:INDB) | E1279: The Hanover Insurance Group, Inc. (NYSE:THG) | G1279: Penns Woods Bancorp, Inc. (NASDAQGS:PWOD) | H1279: Scorpio Tankers Inc. (NYSE:STNG)
A1280: Janus International Group, Inc. (NYSE:JBI) | B1280: IDT Corporation (NYSE:IDT) | C1280: Putnam Municipal Opportunities Trust (NYSE:PMO) | D1280: Independent Bank Corporation (NASDAQGS:IBCP) | E1280: The Hartford Financial Services Group, Inc. (NYSE:HIG) | G1280: PennyMac Mortgage Investment Trust (NYSE:PMT) | H1280: Seagate Technology Holdings plc (NASDAQGS:STX)
A1281: Japan Smaller Capitalization Fund, Inc. (NYSE:JOF) | B1281: IES Holdings, Inc. (NASDAQGM:IESC) | C1281: Q2 Holdings, Inc. (NYSE:QTWO) | D1281: Independent Bank Group, Inc. (NASDAQGS:IBTX) | E1281: The Hershey Company (NYSE:HSY) | G1281: Pentair plc (NYSE:PNR) | H1281: Seanergy Maritime Holdings Corp. (NASDAQCM:SHIP)
... A1451: Maplebear Inc. (NASDAQGS:CART) | B1451: Krispy Kreme, Inc. (NASDAQGS:DNUT) | C1451: Steel Partners Holdings L.P. (NYSE:SPLP) | D1451: Landstar System, Inc. (NASDAQGS:LSTR) | E1451: Zynex, Inc. (NASDAQGS:ZYXI) | G1451: Science Applications International Corporation (NASDAQGS:SAIC) | H1451: Travere Therapeutics, Inc. (NASDAQGM:TVTX)
A1452: MARA Holdings, Inc. (NASDAQCM:MARA) | B1452: Kronos Worldwide, Inc. (NYSE:KRO) | C1452: Stellar Bancorp, Inc. (NYSE:STEL) | D1452: Lantheus Holdings, Inc. (NASDAQGM:LNTH) | G1452: Scully Royalty Ltd. (NYSE:SRL) | H1452: Treace Medical Concepts, Inc. (NASDAQGS:TMCI)
A1453: Marathon Oil Corporation (NYSE:MRO) | B1453: Krystal Biotech, Inc. (NASDAQGS:KRYS) | C1453: Stellus Capital Investment Corporation (NYSE:SCM) | D1453: Larimar Therapeutics, Inc. (NASDAQGM:LRMR) | G1453: Sea Limited (NYSE:SE) | H1453: Tredegar Corporation (NYSE:TG)
A1454: Marathon Petroleum Corporation (NYSE:MPC) | B1454: Kulicke and Soffa Industries, Inc. (NASDAQGS:KLIC) | C1454: Stepan Company (NYSE:SCL) | D1454: Las Vegas Sands Corp. (NYSE:LVS) | G1454: Seacoast Banking Corporation of Florida (NASDAQGS:SBCF) | H1454: Tri Pointe Homes, Inc. (NYSE:TPH)
A1455: Marine Products Corporation (NYSE:MPX) | B1455: Kura Sushi USA, Inc. (NASDAQGM:KRUS) | C1455: STERIS plc (NYSE:STE) | D1455: Laser Photonics Corporation (NASDAQCM:LASE) | G1455: Seagate Technology Holdings plc (NASDAQGS:STX) | H1455: Trinity Industries, Inc. (NYSE:TRN)
A1456: MarineMax, Inc. (NYSE:HZO) | B1456: Kyndryl Holdings, Inc. (NYSE:KD) | C1456: Sterling Infrastructure, Inc. (NASDAQGS:STRL) | D1456: Latham Group, Inc. (NASDAQGS:SWIM) | G1456: Seanergy Maritime Holdings Corp. (NASDAQCM:SHIP) | H1456: Trip.com Group Limited (NASDAQGS:TCOM)
A1457: Markel Group Inc. (NYSE:MKL) | B1457: L.B. Foster Company (NASDAQGS:FSTR) | C1457: Stewart Information Services Corporation (NYSE:STC) | D1457: Lattice Semiconductor Corporation (NASDAQGS:LSCC) | G1457: SecureWorks Corp. (NASDAQGS:SCWX) | H1457: Tripadvisor, Inc. (NASDAQGS:TRIP)
A1458: MarketAxess Holdings Inc. (NASDAQGS:MKTX) | B1458: L3Harris Technologies, Inc. (NYSE:LHX) | C1458: Stifel Financial Corp. (NYSE:SF) | D1458: Laureate Education, Inc. (NASDAQGS:LAUR) | G1458: Security National Financial Corporation (NASDAQGM:SNFC.A) | H1458: Tronox Holdings plc (NYSE:TROX)
A1459: Marriott International, Inc. (NASDAQGS:MAR) | B1459: Labcorp Holdings Inc. (NYSE:LH) | C1459: Stock Yards Bancorp, Inc. (NASDAQGS:SYBT) | D1459: Lazard, Inc. (NYSE:LAZ) | G1459: SEI Investments Company (NASDAQGS:SEIC) | H1459: TruBridge, Inc. (NASDAQGS:TBRG)
A1460: Marriott Vacations Worldwide Corporation (NYSE:VAC) | B1460: Ladder Capital Corp (NYSE:LADR) | C1460: StoneCo Ltd. (NASDAQGS:STNE) | D1460: La-Z-Boy Incorporated (NYSE:LZB) | G1460: Select Medical Holdings Corporation (NYSE:SEM) | H1460: Truist Financial Corporation (NYSE:TFC)
A1461: Mars Acquisition Corp. (NASDAQCM:MARX) | B1461: Lake Shore Bancorp, Inc. (NASDAQGM:LSBK) | C1461: StoneX Group Inc. (NASDAQGS:SNEX) | D1461: LCI Industries (NYSE:LCII) | G1461: Select Water Solutions, Inc. (NYSE:WTTR) | H1461: Trupanion, Inc. (NASDAQGM:TRUP)
A1462: Marsh & McLennan Companies, Inc. (NYSE:MMC) | B1462: Lakeland Financial Corporation (NASDAQGS:LKFN) | C1462: Stratasys Ltd. (NASDAQGS:SSYS) | D1462: LCNB Corp. (NASDAQCM:LCNB) | G1462: Semtech Corporation (NASDAQGS:SMTC) | H1462: Trustmark Corporation (NASDAQGS:TRMK)
A1463: Marten Transport, Ltd. (NASDAQGS:MRTN) | B1463: Lam Research Corporation (NASDAQGS:LRCX) | C1463: Strategic Education, Inc. (NASDAQGS:STRA) | D1463: Lear Corporation (NYSE:LEA) | G1463: Sensient Technologies Corporation (NYSE:SXT) | H1463: Tsakos Energy Navigation Limited (NYSE:TEN)
... A1606: New Jersey Resources Corporation (NYSE:NJR) | B1606: Medallion Financial Corp. (NASDAQGS:MFIN) | C1606: Ultra Clean Holdings, Inc. (NASDAQGS:UCTT) | D1606: Meta Platforms, Inc. (NASDAQGS:META) | G1606: The Clorox Company (NYSE:CLX) | H1606: Zymeworks Inc. (NASDAQGS:ZYME)
A1607: New Mountain Finance Corporation (NASDAQGS:NMFC) | B1607: MediaAlpha, Inc. (NYSE:MAX) | C1607: UMH Properties, Inc. (NYSE:UMH) | D1607: Metallus Inc. (NYSE:MTUS) | G1607: The Cooper Companies, Inc. (NASDAQGS:COO)
A1608: New Oriental Education & Technology Group Inc. (NYSE:EDU) | B1608: Medifast, Inc. (NYSE:MED) | C1608: Under Armour, Inc. (NYSE:UAA) | D1608: Methode Electronics, Inc. (NYSE:MEI) | G1608: The Eastern Company (NASDAQGM:EML)
A1609: Newmark Group, Inc. (NASDAQGS:NMRK) | B1609: Medpace Holdings, Inc. (NASDAQGS:MEDP) | C1609: Unifi, Inc. (NYSE:UFI) | D1609: MetLife, Inc. (NYSE:MET) | G1609: The Estée Lauder Companies Inc. (NYSE:EL)
A1610: NewMarket Corporation (NYSE:NEU) | B1610: Medtronic plc (NYSE:MDT) | C1610: UniFirst Corporation (NYSE:UNF) | D1610: Mettler-Toledo International Inc. (NYSE:MTD) | G1610: The European Equity Fund, Inc. (NYSE:EEA)
A1611: News Corporation (NASDAQGS:NWSA) | B1611: MercadoLibre, Inc. (NASDAQGS:MELI) | C1611: Union Pacific Corporation (NYSE:UNP) | D1611: MFS Charter Income Trust (NYSE:MCR) | G1611: The First Bancorp, Inc. (NASDAQGS:FNLC)
A1612: NewtekOne, Inc. (NASDAQGM:NEWT) | B1612: Mercantile Bank Corporation (NASDAQGS:MBWM) | C1612: uniQure N.V. (NASDAQGS:QURE) | D1612: MFS Investment Grade Municipal Trust (NYSE:CXH) | G1612: The First Bancshares, Inc. (NYSE:FBMS)
A1613: NexPoint Real Estate Finance, Inc. (NYSE:NREF) | B1613: Mercer International Inc. (NASDAQGS:MERC) | C1613: United Bankshares, Inc. (NASDAQGS:UBSI) | D1613: MGE Energy, Inc. (NASDAQGS:MGEE) | G1613: The First of Long Island Corporation (NASDAQCM:FLIC)
A1614: NexPoint Residential Trust, Inc. (NYSE:NXRT) | B1614: Merck & Co., Inc. (NYSE:MRK) | C1614: United Fire Group, Inc. (NASDAQGS:UFCS) | D1614: MGM Resorts International (NYSE:MGM) | G1614: The Gabelli Utility Trust (NYSE:GUT)
A1615: Nexstar Media Group, Inc. (NASDAQGS:NXST) | B1615: Mercury General Corporation (NYSE:MCY) | C1615: United Natural Foods, Inc. (NYSE:UNFI) | D1615: MGP Ingredients, Inc. (NASDAQGS:MGPI) | G1615: The Gap, Inc. (NYSE:GAP)
A1616: NextEra Energy Partners, LP (NYSE:NEP) | B1616: Mercury Systems, Inc. (NASDAQGS:MRCY) | C1616: United Parcel Service, Inc. (NYSE:UPS) | D1616: Microchip Technology Incorporated (NASDAQGS:MCHP) | G1616: The Goldman Sachs Group, Inc. (NYSE:GS)
A1617: NextEra Energy, Inc. (NYSE:NEE) | B1617: Meridian Corporation (NASDAQGS:MRBK) | C1617: United Parks & Resorts Inc. (NYSE:PRKS) | D1617: Micron Technology, Inc. (NASDAQGS:MU) | G1617: The Goodyear Tire & Rubber Company (NASDAQGS:GT)
A1618: Nextracker Inc. (NASDAQGS:NXT) | B1618: MeridianLink, Inc. (NYSE:MLNK) | C1618: United States Lime & Minerals, Inc. (NASDAQGS:USLM) | D1618: Microsoft Corporation (NASDAQGS:MSFT) | G1618: The Gorman-Rupp Company (NYSE:GRC)
... A1756: Oxford Industries, Inc. (NYSE:OXM) | B1756: Nicolet Bankshares, Inc. (NYSE:NIC) | C1756: Zurn Elkay Water Solutions Corporation (NYSE:ZWS) | D1756: Northern Trust Corporation (NASDAQGS:NTRS) | G1756: Veris Residential, Inc. (NYSE:VRE)
A1757: Oxford Lane Capital Corp. (NASDAQGS:OXLC) | B1757: NIKE, Inc. (NYSE:NKE) | D1757: Northfield Bancorp, Inc. (Staten Island, NY) (NASDAQGS:NFBK) | G1757: VeriSign, Inc. (NASDAQGS:VRSN)
A1758: P10, Inc. (NYSE:PX) | B1758: NiSource Inc. (NYSE:NI) | D1758: Northrop Grumman Corporation (NYSE:NOC) | G1758: Verisk Analytics, Inc. (NASDAQGS:VRSK)
A1759: PACCAR Inc (NASDAQGS:PCAR) | B1759: NL Industries, Inc. (NYSE:NL) | D1759: Northwest Bancshares, Inc. (NASDAQGS:NWBI) | G1759: Veritex Holdings, Inc. (NASDAQGM:VBTX)
A1760: Packaging Corporation of America (NYSE:PKG) | B1760: nLIGHT, Inc. (NASDAQGS:LASR) | D1760: Northwest Natural Holding Company (NYSE:NWN) | G1760: Verizon Communications Inc. (NYSE:VZ)
...

Sheet 9-dim-Scores
A1: =_xll.SNL.Clients.Office.Excel.Functions.SPGTable($B$6:$B$4461,$C$3:$AD$3,,"Options:Curr=USD,Mag=Standard,ConvMethod=R,FilingVer=Current/Restated") -> SPGTable | AP1: Net Income > 0 | AQ1: Cash flow from Op > 0 | AR1: Delta RoA > 0 | AS1: CFO > Net Income | AT1: Delta LT Debt / Asset < 0 | AU1: Delta C Asset / Liability > 0 | AV1: Delta EBIT Margin > 0 | AW1: Delta Rev / Asset > 0 | AX1: Delta O/S shares < 0 | AY1: sum
A2: =_xll.SNL.Clients.Office.Excel.Functions.SPGLabel(266637,"SP_ENTITY_NAME","","","Options:Curr=USD,Mag=Standard,ConvMethod=R,FilingVer=Current/Restated") -> Entity Name | B2: =_xll.SNL.Clients.Office.Excel.Functions.SPGLabel(266637,"SP_ENTITY_ID","","","Options:Curr=USD,Mag=Standard,ConvMethod=R,FilingVer=Current/Restated") -> Entity ID | C2: =_xll.SNL.Clients.Office.Excel.Functions.SPGLabel(266637,"SP_EXCHANGE","","","Options:Curr=USD,Mag=Standard,ConvMethod=R,FilingVer=Current/Restated") -> Exchange | D2: =_xll.SNL.Clients.Office.Excel.Functions.SPGLabel(266637,"SP_PRICE_CLOSE","Current","","Options:Curr=USD,Mag=Standard,ConvMethod=R,FilingVer=Current/Restated") -> Day Close Price ($) | E2: =_xll.SNL.Clients.Office.Excel.Functions.SPGLabel(266637,"SP_MARKETCAP","","","Options:Curr=USD,Mag=Standard,ConvMethod=R,FilingVer=Current/Restated") -> Market Capitalization ($M) | F2: =_xll.SNL.Clients.Office.Excel.Functions.SPGLabel(266637,"IQ_SECTOR","","","Options:Curr=USD,Mag=Standard,ConvMethod=R,FilingVer=Current/Restated") -> Sector | G2: =_xll.SNL.Clients.Office.Excel.Functions.SPGLabel(266637,"IQ_INDUSTRY_GROUP","","","Options:Curr=USD,Mag=Standard,ConvMethod=R,FilingVer=Current/Restated") -> Industry Group | H2: =_xll.SNL.Clients.Office.Excel.Functions.SPGLabel(266637,"IQ_INDUSTRY","","","Options:Curr=USD,Mag=Standard,ConvMethod=R,FilingVer=Current/Restated") -> Industry | I2: =_xll.SNL.Clients.Office.Excel.Functions.SPGLabel(266637,"IQ_PRIMARY_INDUSTRY","","","Options:Curr=USD,Mag=Standard,ConvMethod=R,FilingVer=Current/Restated") -> Primary Industry | J2: =_xll.SNL.Clients.Office.Excel.Functions.SPGLabel(266637,"NAICS_CODE","Primary","","Options:Curr=USD,Mag=Standard,ConvMethod=R,FilingVer=Current/Restated") -> NAICS Code | K2: =_xll.SNL.Clients.Office.Excel.Functions.SPGLabel(266637,"SP_TOTAL_REV","LTM","","Options:Curr=USD,Mag=Standard,ConvMethod=R,FilingVer=Current/Restated") -> Total Revenue ($000) | L2: =_xll.SNL.Clients.Office.Excel.Functions.SPGLabel(266637,"SP_TOTAL_REV","LTM-1","","Options:Curr=USD,Mag=Standard,ConvMethod=R,FilingVer=Current/Restated") -> Total Revenue ($000) | M2: =_xll.SNL.Clients.Office.Excel.Functions.SPGLabel(266637,"SP_EBITDA","LTM","","Options:Curr=USD,Mag=Standard,ConvMethod=R,FilingVer=Current/Restated") -> EBITDA ($000) | N2: =_xll.SNL.Clients.Office.Excel.Functions.SPGLabel(266637,"SP_EBITDA","LTM-1","","Options:Curr=USD,Mag=Standard,ConvMethod=R,FilingVer=Current/Restated") -> EBITDA ($000) | O2: =_xll.SNL.Clients.Office.Excel.Functions.SPGLabel(266637,"SP_EBIT","LTM","","Options:Curr=USD,Mag=Standard,ConvMethod=R,FilingVer=Current/Restated") -> EBIT ($000) | P2: =_xll.SNL.Clients.Office.Excel.Functions.SPGLabel(266637,"SP_EBIT","LTM-1","","Options:Curr=USD,Mag=Standard,ConvMethod=R,FilingVer=Current/Restated") -> EBIT ($000) | Q2: =_xll.SNL.Clients.Office.Excel.Functions.SPGLabel(266637,"SP_NET_INC","LTM","","Options:Curr=USD,Mag=Standard,ConvMethod=R,FilingVer=Current/Restated") -> Net Income ($000) | R2: =_xll.SNL.Clients.Office.Excel.Functions.SPGLabel(266637,"SP_NET_INC","LTM-1","","Options:Curr=USD,Mag=Standard,ConvMethod=R,FilingVer=Current/Restated") -> Net Income ($000) | S2: =_xll.SNL.Clients.Office.Excel.Functions.SPGLabel(266637,"IQ_CASH_OPER","LTM","","Options:Curr=USD,Mag=Standard,ConvMethod=R,FilingVer=Current/Restated") -> Cash from Ops. ($000) | T2: =_xll.SNL.Clients.Office.Excel.Functions.SPGLabel(266637,"IQ_CASH_OPER","LTM-1","","Options:Curr=USD,Mag=Standard,ConvMethod=R,FilingVer=Current/Restated") -> Cash from Ops. ($000) | U2: =_xll.SNL.Clients.Office.Excel.Functions.SPGLabel(266637,"IQ_LT_DEBT_BNK","LTM","","Options:Curr=USD,Mag=Standard,ConvMethod=R,FilingVer=Current/Restated") -> Long-Term Debt ($000) | V2: =_xll.SNL.Clients.Office.Excel.Functions.SPGLabel(266637,"IQ_LT_DEBT_BNK","LTM-1","","Options:Curr=USD,Mag=Standard,ConvMethod=R,FilingVer=Current/Restated") -> Long-Term Debt ($000) | W2: =_xll.SNL.Clients.Office.Excel.Functions.SPGLabel(266637,"SP_TOTAL_ASSETS","LTM","","Options:Curr=USD,Mag=Standard,ConvMethod=R,FilingVer=Current/Restated") -> Total Assets ($000) | X2: =_xll.SNL.Clients.Office.Excel.Functions.SPGLabel(266637,"SP_TOTAL_ASSETS","LTM-1","","Options:Curr=USD,Mag=Standard,ConvMethod=R,FilingVer=Current/Restated") -> Total Assets ($000) | Y2: =_xll.SNL.Clients.Office.Excel.Functions.SPGLabel(266637,"SP_CURRENT_ASSETS","LTM","","Options:Curr=USD,Mag=Standard,ConvMethod=R,FilingVer=Current/Restated") -> Total Current Assets ($000) | Z2: =_xll.SNL.Clients.Office.Excel.Functions.SPGLabel(266637,"SP_CURRENT_ASSETS","LTM-1","","Options:Curr=USD,Mag=Standard,ConvMethod=R,FilingVer=Current/Restated") -> Total Current Assets ($000) | AA2: =_xll.SNL.Clients.Office.Excel.Functions.SPGLabel(266637,"SP_CURRENT_LIAB","LTM","","Options:Curr=USD,Mag=Standard,ConvMethod=R,FilingVer=Current/Restated") -> Total Current Liabilities ($000) | AB2: =_xll.SNL.Clients.Office.Excel.Functions.SPGLabel(266637,"SP_CURRENT_LIAB","LTM-1","","Options:Curr=USD,Mag=Standard,ConvMethod=R,FilingVer=Current/Restated") -> Total Current Liabilities ($000) | AC2: =_xll.SNL.Clients.Office.Excel.Functions.SPGLabel(266637,"SP_SHARES_OUT_PERIOD_END","LTM","","Options:Curr=USD,Mag=Standard,ConvMethod=R,FilingVer=Current/Restated") -> Common Shares Outstanding (actual) | AD2: =_xll.SNL.Clients.Office.Excel.Functions.SPGLabel(266637,"SP_SHARES_OUT_PERIOD_END","LTM-1","","Options:Curr=USD,Mag=Standard,ConvMethod=R,FilingVer=Current/Restated") -> Common Shares Outstanding (actual)
A3: SP_ENTITY_NAME | B3: SP_ENTITY_ID | C3: SP_EXCHANGE | D3: SP_PRICE_CLOSE | E3: SP_MARKETCAP | F3: IQ_SECTOR | G3: IQ_INDUSTRY_GROUP | H3: IQ_INDUSTRY | I3: IQ_PRIMARY_INDUSTRY | J3: NAICS_CODE | K3: SP_TOTAL_REV | L3: SP_TOTAL_REV | M3: SP_EBITDA | N3: SP_EBITDA | O3: SP_EBIT | P3: SP_EBIT | Q3: SP_NET_INC | R3: SP_NET_INC | S3: IQ_CASH_OPER | T3: IQ_CASH_OPER | U3: IQ_LT_DEBT_BNK | V3: IQ_LT_DEBT_BNK | W3: SP_TOTAL_ASSETS | X3: SP_TOTAL_ASSETS | Y3: SP_CURRENT_ASSETS | Z3: SP_CURRENT_ASSETS | AA3: SP_CURRENT_LIAB | AB3: SP_CURRENT_LIAB | AC3: SP_SHARES_OUT_PERIOD_END | AD3: SP_SHARES_OUT_PERIOD_END | AF3: RoA | AG3: RoA | AH3: Debt / Asset | AI3: Debt / Asset | AJ3: Current Asset / Liability | AK3: Current Asset / Liability | AL3: EBIT Margin | AM3: EBIT Margin | AN3: Rev / Asset | AO3: Rev / Asset
D4: =_xll.SNL.Clients.Office.Excel.Functions.SPGLabel(266637,"SP_PRICE_CLOSE","<>Current") -> Current | J4: =_xll.SNL.Clients.Office.Excel.Functions.SPGLabel(266637,"NAICS_CODE","<>Primary") -> Primary | K4: LTM | L4: LTM-1 | M4: LTM | N4: LTM-1 | O4: LTM | P4: LTM-1 | Q4: LTM | R4: LTM-1 | S4: LTM | T4: LTM-1 | U4: LTM | V4: LTM-1 | W4: LTM | X4: LTM-1 | Y4: LTM | Z4: LTM-1 | AA4: LTM | AB4: LTM-1 | AC4: LTM | AD4: LTM-1 | AF4: LTM | AG4: LTM-1 | AH4: LTM | AI4: LTM-1 | AJ4: LTM | AK4: LTM-1 | AL4: LTM | AM4: LTM-1 | AN4: LTM | AO4: LTM-1
A6: 10x Genomics, Inc. (NASDAQGS:TXG) | B6: 5248867 | C6: NASDAQGS | D6: 15.71 | E6: 1901.7654 | F6: Health Care | G6: Pharmaceuticals, Biotechnology and Life Sciences | H6: Life Sciences Tools and Services | I6: Life Sciences Tools and Services | J6: 33911 - Medical Equipment and Supplies Manufacturing | K6: 629743 | L6: 631733 | M6: -134769 | N6: -146284 | O6: -171615 | P6: -183538 | Q6: -182551 | R6: -239784 | S6: 39170 | T6: -7775 | U6: NA | V6: NA | W6: 937794 | X6: 929668 | Y6: 593893 | Z6: 579155 | AA6: 121235 | AB6: 111019 | AC6: 121039868 | AD6: 120474167 | AF6: =Q6/W6 -> -0.19466002 | AG6: =R6/X6 -> -0.25792433 | AH6: =U6/W6 -> #VALUE! | AI6: =V6/X6 -> #VALUE! | AJ6: =Y6/AA6 -> 4.8986926 | AK6: =Z6/AB6 -> 5.2167197 | AL6: =O6/K6 -> -0.27251593 | AM6: =P6/L6 -> -0.29053097 | AN6: =K6/W6 -> 0.67151528 | AO6: =L6/X6 -> 0.67952538 | AP6: =IF(OR(Q6<0, Q6="NA"), 0, 1) -> 0 | AQ6: =IF(OR(S6<0, S6="NA"), 0, 1) -> 1 | AR6: =IFERROR(IF((AF6-AG6)>0,1,0),0) -> 1 | AS6: =IFERROR(IF((S6-Q6)>0,1,0),0) -> 1 | AT6: =IFERROR(IF((AH6-AI6)<0,1,0),0) -> 0 | AU6: =IFERROR(IF((AJ6-AK6)>0,1,0),0) -> 0 | AV6: =IFERROR(IF((AL6-AM6)>0,1,0),0) -> 1 | AW6: =IFERROR(IF((AN6-AO6)>0,1,0),0) -> 0 | AX6: =IFERROR(IF((AC6-AD6)<0,1,0),0) -> 0 | AY6: =SUM(AP6:AX6) -> 4
A7: 1-800-FLOWERS.COM, Inc. (NASDAQGS:FLWS) | B7: 4122591 | C7: NASDAQGS | D7: 7.39 | E7: 471.85851 | F7: Consumer Discretionary | G7: Consumer Discretionary Distribution and Retail | H7: Specialty Retail | I7: Other Specialty Retail | J7: 459999 - All Other Miscellaneous Retailers | K7: 1804461 | L7: 1831421 | M7: 58693 | N7: 66011 | O7: 5097 | P7: 12259 | Q7: -9053 | R7: -6105 | S7: 61642 | T7: 94999 | U7: 172293 | V7: 177113 | W7: 1034624 | X7: 1032648 | Y7: 385714 | Z7: 385732 | AA7: 266994 | AB7: 227819 | AC7: 64060948 | AD7: 64215626 | AF7: =Q7/W7 -> -0.0087500387 | AG7: =R7/X7 -> -0.0059119855 | AH7: =U7/W7 -> 0.16652716 | AI7: =V7/X7 -> 0.17151343 | AJ7: =Y7/AA7 -> 1.4446542 | AK7: =Z7/AB7 -> 1.6931511 | AL7: =O7/K7 -> 0.0028246662 | AM7: =P7/L7 -> 0.0066937094 | AN7: =K7/W7 -> 1.7440742 | AO7: =L7/X7 -> 1.7735191 | AP7: =IF(OR(Q7<0, Q7="NA"), 0, 1) -> 0 | AQ7: =IF(OR(S7<0, S7="NA"), 0, 1) -> 1 | AR7: =IFERROR(IF((AF7-AG7)>0,1,0),0) -> 0 | AS7: =IFERROR(IF((S7-Q7)>0,1,0),0) -> 1 | AT7: =IFERROR(IF((AH7-AI7)<0,1,0),0) -> 1 | AU7: =IFERROR(IF((AJ7-AK7)>0,1,0),0) -> 0 | AV7: =IFERROR(IF((AL7-AM7)>0,1,0),0) -> 0 | AW7: =IFERROR(IF((AN7-AO7)>0,1,0),0) -> 0 | AX7: =IFERROR(IF((AC7-AD7)<0,1,0),0) -> 1 | AY7: =SUM(AP7:AX7) -> 4
A8: 1895 Bancorp of Wisconsin, Inc. (NASDAQCM:BCOW) | B8: 11123920 | C8: NASDAQCM | D8: 9.94 | E8: 55.057362 | F8: Financials | G8: Banks | H8: Banks | I8: Regional Banks | J8: 522180 - Savings Institutions and Other Depository Credit Intermediation | K8: 12126 | L8: 10086 | M8: NA | N8: NA | O8: 7291 | P8: 4937 | Q8: -3263 | R8: -6745 | S8: -43 | T8: -1067 | U8: NA | V8: NA | W8: 564540 | X8: 561454 | Y8: NA | Z8: NA | AA8: NA | AB8: NA | AC8: 5965459 | AD8: 5969174 | AF8: =Q8/W8 -> -0.005779927 | AG8: =R8/X8 -> -0.012013451 | AH8: =U8/W8 -> #VALUE! | AI8: =V8/X8 -> #VALUE! | AJ8: =Y8/AA8 -> #VALUE! | AK8: =Z8/AB8 -> #VALUE! | AL8: =O8/K8 -> 0.60127 | AM8: =P8/L8 -> 0.48949038 | AN8: =K8/W8 -> 0.021479435 | AO8: =L8/X8 -> 0.017964072 | AP8: =IF(OR(Q8<0, Q8="NA"), 0, 1) -> 0 | AQ8: =IF(OR(S8<0, S8="NA"), 0, 1) -> 0 | AR8: =IFERROR(IF((AF8-AG8)>0,1,0),0) -> 1 | AS8: =IFERROR(IF((S8-Q8)>0,1,0),0) -> 1 | AT8: =IFERROR(IF((AH8-AI8)<0,1,0),0) -> 0 | AU8: =IFERROR(IF((AJ8-AK8)>0,1,0),0) -> 0 | AV8: =IFERROR(IF((AL8-AM8)>0,1,0),0) -> 1 | AW8: =IFERROR(IF((AN8-AO8)>0,1,0),0) -> 1 | AX8: =IFERROR(IF((AC8-AD8)<0,1,0),0) -> 1 | AY8: =SUM(AP8:AX8) -> 5
A9: 1st Source Corporation (NASDAQGS:SRCE) | B9: 100444 | C9: NASDAQGS | D9: 55.84 | E9: 1368.9898 | F9: Financials | G9: Banks | H9: Banks | I9: Regional Banks | J9: 522110 - Commercial Banking | K9: 380682 | L9: 376439 | M9: NA | N9: NA | O9: 350177 | P9: 337806 | Q9: 129598 | R9: 127623 | S9: 204458 | T9: 188255 | U9: 39220 | V9: 39136 | W9: 8763946 | X9: 8878003 | Y9: NA | Z9: NA | AA9: NA | AB9: NA | AC9: 24514383 | AD9: 24507023 | AF9: =Q9/W9 -> 0.014787631 | AG9: =R9/X9 -> 0.014375192 | AH9: =U9/W9 -> 0.0044751531 | AI9: =V9/X9 -> 0.0044081986 | AJ9: =Y9/AA9 -> #VALUE! | AK9: =Z9/AB9 -> #VALUE! | AL9: =O9/K9 -> 0.9198675 | AM9: =P9/L9 -> 0.89737248 | AN9: =K9/W9 -> 0.043437283 | AO9: =L9/X9 -> 0.042401315 | AP9: =IF(OR(Q9<0, Q9="NA"), 0, 1) -> 1 | AQ9: =IF(OR(S9<0, S9="NA"), 0, 1) -> 1 | AR9: =IFERROR(IF((AF9-AG9)>0,1,0),0) -> 1 | AS9: =IFERROR(IF((S9-Q9)>0,1,0),0) -> 1 | AT9: =IFERROR(IF((AH9-AI9)<0,1,0),0) -> 0 | AU9: =IFERROR(IF((AJ9-AK9)>0,1,0),0) -> 0 | AV9: =IFERROR(IF((AL9-AM9)>0,1,0),0) -> 1 | AW9: =IFERROR(IF((AN9-AO9)>0,1,0),0) -> 1 | AX9: =IFERROR(IF((AC9-AD9)<0,1,0),0) -> 0 | AY9: =SUM(AP9:AX9) -> 6
A10: 3M Company (NYSE:MMM) | B10: 105135 | C10: NYSE | D10: 134.6 | E10: 73297.589 | F10: Industrials | G10: Capital Goods | H10: Industrial Conglomerates | I10: Industrial Conglomerates | J10: 3251 - Basic Chemical Manufacturing | K10: 32638000 | L10: 32614000 | M10: 8117000 | N10: 7350000 | O10: 6539000 | P10: 5547000 | Q10: 4407000 | R10: 960000 | S10: 1987000 | T10: 5684000 | U10: 11387000 | V10: 11877000 | W10: 40875000 | X10: 43377000 | Y10: 16299000 | Z10: 19515000 | AA10: 11391000 | AB10: 14345000 | AC10: 544558607 | AD10: 549353621 | AF10: =Q10/W10 -> 0.10781651 | AG10: =R10/X10 -> 0.022131544 | AH10: =U10/W10 -> 0.27858104 | AI10: =V10/X10 -> 0.2738087 | AJ10: =Y10/AA10 -> 1.4308665 | AK10: =Z10/AB10 -> 1.3604043 | AL10: =O10/K10 -> 0.20034929 | AM10: =P10/L10 -> 0.17008033 | AN10: =K10/W10 -> 0.79848318 | AO10: =L10/X10 -> 0.75187311 | AP10: =IF(OR(Q10<0, Q10="NA"), 0, 1) -> 1 | AQ10: =IF(OR(S10<0, S10="NA"), 0, 1) -> 1 | AR10: =IFERROR(IF((AF10-AG10)>0,1,0),0) -> 1 | AS10: =IFERROR(IF((S10-Q10)>0,1,0),0) -> 0 | AT10: =IFERROR(IF((AH10-AI10)<0,1,0),0) -> 0 | AU10: =IFERROR(IF((AJ10-AK10)>0,1,0),0) -> 1 | AV10: =IFERROR(IF((AL10-AM10)>0,1,0),0) -> 1 | AW10: =IFERROR(IF((AN10-AO10)>0,1,0),0) -> 1 | AX10: =IFERROR(IF((AC10-AD10)<0,1,0),0) -> 1 | AY10: =SUM(AP10:AX10) -> 7
A11: 4D Molecular Therapeutics, Inc. (NASDAQGS:FDMT) | B11: 5284798 | C11: NASDAQGS | D11: 4.76 | E11: 220.04389 | F11: Health Care | G11: Pharmaceuticals, Biotechnology and Life Sciences | H11: Biotechnology | I11: Biotechnology | J11: 541714 - Research and Development in Biotechnology (except Nanobiotechnology) | K11: 17 | L11: 20218 | M11: -163717 | N11: -126755 | O11: -168376 | P11: -131218 | Q11: -143480 | R11: -109893 | S11: -113372 | T11: -85152 | U11: NA | V11: NA | W11: 604028 | X11: 620117 | Y11: 510757 | Z11: 552633 | AA11: 29465 | AB11: 19403 | AC11: 51996639 | AD11: 51914275 | AF11: =Q11/W11 -> -0.23753866 | AG11: =R11/X11 -> -0.17721333 | AH11: =U11/W11 -> #VALUE! | AI11: =V11/X11 -> #VALUE! | AJ11: =Y11/AA11 -> 17.334363 | AK11: =Z11/AB11 -> 28.481833 | AL11: =O11/K11 -> -9904.4706 | AM11: =P11/L11 -> -6.4901573 | AN11: =K11/W11 -> 2.8144391e-05 | AO11: =L11/X11 -> 0.032603525 | AP11: =IF(OR(Q11<0, Q11="NA"), 0, 1) -> 0 | AQ11: =IF(OR(S11<0, S11="NA"), 0, 1) -> 0 | AR11: =IFERROR(IF((AF11-AG11)>0,1,0),0) -> 0 | AS11: =IFERROR(IF((S11-Q11)>0,1,0),0) -> 1 | AT11: =IFERROR(IF((AH11-AI11)<0,1,0),0) -> 0 | AU11: =IFERROR(IF((AJ11-AK11)>0,1,0),0) -> 0 | AV11: =IFERROR(IF((AL11-AM11)>0,1,0),0) -> 0 | AW11: =IFERROR(IF((AN11-AO11)>0,1,0),0) -> 0 | AX11: =IFERROR(IF((AC11-AD11)<0,1,0),0) -> 0 | AY11: =SUM(AP11:AX11) -> 1
A12: 5:01 Acquisition Corp. (NASDAQCM:FVAM) | B12: 25688942 | C12: NASDAQCM | D12: 10 | E12: 106.56717 | F12: Financials | G12: Financial Services | H12: Capital Markets | I12: Asset Management and Custody Banks | J12: 525990 - Other Financial Vehicles | K12: NA | L12: NA | M12: NA | N12: NA | O12: -1317.983 | P12: -1200.069 | Q12: -1187.185 | R12: -1186.415 | S12: -1111.117 | T12: -986.685 | U12: 1000 | V12: 1000 | W12: 83430.064 | X12: 83681.82 | Y12: 739.002 | Z12: 1100.207 | AA12: 275 | AB12: 315 | AC12: 10656717 | AD12: 10685467 | AF12: =Q12/W12 -> -0.014229703 | AG12: =R12/X12 -> -0.014177691 | AH12: =U12/W12 -> 0.011986087 | AI12: =V12/X12 -> 0.011950027 | AJ12: =Y12/AA12 -> 2.68728 | AK12: =Z12/AB12 -> 3.4927206 | AL12: =O12/K12 -> #VALUE! | AM12: =P12/L12 -> #VALUE! | AN12: =K12/W12 -> #VALUE! | AO12: =L12/X12 -> #VALUE! | AP12: =IF(OR(Q12<0, Q12="NA"), 0, 1) -> 0 | AQ12: =IF(OR(S12<0, S12="NA"), 0, 1) -> 0 | AR12: =IFERROR(IF((AF12-AG12)>0,1,0),0) -> 0 | AS12: =IFERROR(IF((S12-Q12)>0,1,0),0) -> 1 | AT12: =IFERROR(IF((AH12-AI12)<0,1,0),0) -> 0 | AU12: =IFERROR(IF((AJ12-AK12)>0,1,0),0) -> 0 | AV12: =IFERROR(IF((AL12-AM12)>0,1,0),0) -> 0 | AW12: =IFERROR(IF((AN12-AO12)>0,1,0),0) -> 0 | AX12: =IFERROR(IF((AC12-AD12)<0,1,0),0) -> 1 | AY12: =SUM(AP12:AX12) -> 2
A13: 89bio, Inc. (NASDAQGM:ETNB) | B13: 19357914 | C13: NASDAQGM | D13: 6.31 | E13: 741.94381 | F13: Health Care | G13: Pharmaceuticals, Biotechnology and Life Sciences | H13: Biotechnology | I13: Biotechnology | J13: 325414 - Biological Product (except Diagnostic) Manufacturing | K13: NA | L13: NA | M13: -303812 | N13: -191217 | O13: -303857 | P13: -191264 | Q13: -288960 | R13: -174612 | S13: -280536 | T13: -165538 | U13: 35544 | V13: 20355 | W13: 458297 | X13: 582138 | Y13: 456206 | Z13: 579854 | AA13: 39131 | AB13: 41653 | AC13: 106126338 | AD13: 104915176 | AF13: =Q13/W13 -> -0.63050816 | AG13: =R13/X13 -> -0.2999495 | AH13: =U13/W13 -> 0.077556694 | AI13: =V13/X13 -> 0.034965936 | AJ13: =Y13/AA13 -> 11.658429 | AK13: =Z13/AB13 -> 13.921062 | AL13: =O13/K13 -> #VALUE! | AM13: =P13/L13 -> #VALUE! | AN13: =K13/W13 -> #VALUE! | AO13: =L13/X13 -> #VALUE! | AP13: =IF(OR(Q13<0, Q13="NA"), 0, 1) -> 0 | AQ13: =IF(OR(S13<0, S13="NA"), 0, 1) -> 0 | AR13: =IFERROR(IF((AF13-AG13)>0,1,0),0) -> 0 | AS13: =IFERROR(IF((S13-Q13)>0,1,0),0) -> 1 | AT13: =IFERROR(IF((AH13-AI13)<0,1,0),0) -> 0 | AU13: =IFERROR(IF((AJ13-AK13)>0,1,0),0) -> 0 | AV13: =IFERROR(IF((AL13-AM13)>0,1,0),0) -> 0 | AW13: =IFERROR(IF((AN13-AO13)>0,1,0),0) -> 0 | AX13: =IFERROR(IF((AC13-AD13)<0,1,0),0) -> 0 | AY13: =SUM(AP13:AX13) -> 1
A14: A SPAC III Acquisition Corp. (NASDAQCM:ASPC.U) | B14: 100630552 | C14: NASDAQCM | D14: 9.98 | E14: 80.3889 | F14: Financials | G14: Financial Services | H14: Capital Markets | I14: Asset Management and Custody Banks | J14: 525990 - Other Financial Vehicles | K14: NA | L14: NA | M14: NA | N14: NA | O14: -49.428 | P14: -2.65 | Q14: -49.428 | R14: -2.65 | S14: NA | T14: 0 | U14: NA | V14: NA | W14: 82.25 | X14: NA | Y14: NA | Z14: NA | AA14: 270 | AB14: 141 | AC14: 1581250 | AD14: 1581250 | AF14: =Q14/W14 -> -0.60094833 | AG14: =R14/X14 -> #VALUE! | AH14: =U14/W14 -> #VALUE! | AI14: =V14/X14 -> #VALUE! | AJ14: =Y14/AA14 -> #VALUE! | AK14: =Z14/AB14 -> #VALUE! | AL14: =O14/K14 -> #VALUE! | AM14: =P14/L14 -> #VALUE! | AN14: =K14/W14 -> #VALUE! | AO14: =L14/X14 -> #VALUE! | AP14: =IF(OR(Q14<0, Q14="NA"), 0, 1) -> 0 | AQ14: =IF(OR(S14<0, S14="NA"), 0, 1) -> 0 | AR14: =IFERROR(IF((AF14-AG14)>0,1,0),0) -> 0 | AS14: =IFERROR(IF((S14-Q14)>0,1,0),0) -> 0 | AT14: =IFERROR(IF((AH14-AI14)<0,1,0),0) -> 0 | AU14: =IFERROR(IF((AJ14-AK14)>0,1,0),0) -> 0 | AV14: =IFERROR(IF((AL14-AM14)>0,1,0),0) -> 0 | AW14: =IFERROR(IF((AN14-AO14)>0,1,0),0) -> 0 | AX14: =IFERROR(IF((AC14-AD14)<0,1,0),0) -> 0 | AY14: =SUM(AP14:AX14) -> 0
A15: A. O. Smith Corporation (NYSE:AOS) | B15: 4020605 | C15: NYSE | D15: 68.63 | E15: 9951.0386 | F15: Industrials | G15: Capital Goods | H15: Building Products | I15: Building Products | J15: 3352 - Household Appliance Manufacturing | K15: 3893800 | L15: 3928700 | M15: 809100 | N15: 828900 | O15: 728800 | P15: 749500 | Q15: 561200 | R15: 576500 | S15: 591200 | T15: 574100 | U15: 109700 | V15: 130400 | W15: 3154200 | X15: 3197600 | Y15: 1412500 | Z15: 1481300 | AA15: 844200 | AB15: 872400 | AC15: 144995463 | AD15: 145845344 | AF15: =Q15/W15 -> 0.1779215 | AG15: =R15/X15 -> 0.18029147 | AH15: =U15/W15 -> 0.034779025 | AI15: =V15/X15 -> 0.040780585 | AJ15: =Y15/AA15 -> 1.6731817 | AK15: =Z15/AB15 -> 1.6979597 | AL15: =O15/K15 -> 0.18716935 | AM15: =P15/L15 -> 0.19077557 | AN15: =K15/W15 -> 1.234481 | AO15: =L15/X15 -> 1.2286402 | AP15: =IF(OR(Q15<0, Q15="NA"), 0, 1) -> 1 | AQ15: =IF(OR(S15<0, S15="NA"), 0, 1) -> 1 | AR15: =IFERROR(IF((AF15-AG15)>0,1,0),0) -> 0 | AS15: =IFERROR(IF((S15-Q15)>0,1,0),0) -> 1 | AT15: =IFERROR(IF((AH15-AI15)<0,1,0),0) -> 1 | AU15: =IFERROR(IF((AJ15-AK15)>0,1,0),0) -> 0 | AV15: =IFERROR(IF((AL15-AM15)>0,1,0),0) -> 0 | AW15: =IFERROR(IF((AN15-AO15)>0,1,0),0) -> 1 | AX15: =IFERROR(IF((AC15-AD15)<0,1,0),0) -> 1 | AY15: =SUM(AP15:AX15) -> 6
A16: a.k.a. Brands Holding Corp. (NYSE:AKA) | B16: 29663785 | C16: NYSE | D16: 19.57 | E16: 208.23249 | F16: Consumer Discretionary | G16: Consumer Discretionary Distribution and Retail | H16: Specialty Retail | I16: Apparel Retail | J16: 459 - Sporting Goods, Hobby, Musical Instrument, Book, and Miscellaneous Retailers | K16: 564586 | L16: 555516 | M16: 6553 | N16: 4878 | O16: -10917 | P16: -12670 | Q16: -30516 | R16: -95487 | S16: 9046 | T16: 21938 | U16: 105610 | V16: 100607 | W16: 404101 | X16: 388804 | Y16: 156277 | Z16: 155067 | AA16: 98830 | AB16: 99843 | AC16: 10631326 | AD16: 10529419 | AF16: =Q16/W16 -> -0.075515775 | AG16: =R16/X16 -> -0.24559161 | AH16: =U16/W16 -> 0.26134555 | AI16: =V16/X16 -> 0.2587602 | AJ16: =Y16/AA16 -> 1.5812709 | AK16: =Z16/AB16 -> 1.5531084 | AL16: =O16/K16 -> -0.019336292 | AM16: =P16/L16 -> -0.022807624 | AN16: =K16/W16 -> 1.3971408 | AO16: =L16/X16 -> 1.4287816 | AP16: =IF(OR(Q16<0, Q16="NA"), 0, 1) -> 0 | AQ16: =IF(OR(S16<0, S16="NA"), 0, 1) -> 1 | AR16: =IFERROR(IF((AF16-AG16)>0,1,0),0) -> 1 | AS16: =IFERROR(IF((S16-Q16)>0,1,0),0) -> 1 | AT16: =IFERROR(IF((AH16-AI16)<0,1,0),0) -> 0 | AU16: =IFERROR(IF((AJ16-AK16)>0,1,0),0) -> 1 | AV16: =IFERROR(IF((AL16-AM16)>0,1,0),0) -> 1 | AW16: =IFERROR(IF((AN16-AO16)>0,1,0),0) -> 0 | AX16: =IFERROR(IF((AC16-AD16)<0,1,0),0) -> 0 | AY16: =SUM(AP16:AX16) -> 5
A17: A10 Networks, Inc. (NYSE:ATEN) | B17: 4433033 | C17: NYSE | D17: 17.99 | E17: 1327.6422 | F17: Information Technology | G17: Software and Services | H17: Software | I17: Systems Software | J17: 513210 - Software Publishers | K17: 257909 | L17: 248963 | M17: 53927 | N17: 45490 | O17: 43578 | P17: 35344 | Q17: 49756 | R17: 43588 | S17: 67513 | T17: 70442 | U17: NA | V17: NA | W17: 407747 | X17: 397170 | Y17: 283837 | Z17: 275047 | AA17: 127038 | AB17: 115033 | AC17: 73783000 | AD17: 73860000 | AF17: =Q17/W17 -> 0.12202665 | AG17: =R17/X17 -> 0.10974646 | AH17: =U17/W17 -> #VALUE! | AI17: =V17/X17 -> #VALUE! | AJ17: =Y17/AA17 -> 2.2342685 | AK17: =Z17/AB17 -> 2.3910269 | AL17: =O17/K17 -> 0.16896657 | AM17: =P17/L17 -> 0.14196487 | AN17: =K17/W17 -> 0.63252213 | AO17: =L17/X17 -> 0.62684241 | AP17: =IF(OR(Q17<0, Q17="NA"), 0, 1) -> 1 | AQ17: =IF(OR(S17<0, S17="NA"), 0, 1) -> 1 | AR17: =IFERROR(IF((AF17-AG17)>0,1,0),0) -> 1 | AS17: =IFERROR(IF((S17-Q17)>0,1,0),0) -> 1 | AT17: =IFERROR(IF((AH17-AI17)<0,1,0),0) -> 0 | AU17: =IFERROR(IF((AJ17-AK17)>0,1,0),0) -> 0 | AV17: =IFERROR(IF((AL17-AM17)>0,1,0),0) -> 1 | AW17: =IFERROR(IF((AN17-AO17)>0,1,0),0) -> 1 | AX17: =IFERROR(IF((AC17-AD17)<0,1,0),0) -> 1 | AY17: =SUM(AP17:AX17) -> 7
A18: A2Z Cust2Mate Solutions Corp. (NASDAQCM:AZ) | B18: 19068495 | C18: NASDAQCM | D18: 6.66 | E18: 173.59994 | F18: Industrials | G18: Capital Goods | H18: Aerospace and Defense | I18: Aerospace and Defense | J18: 336992 - Military Armored Vehicle, Tank, and Tank Component Manufacturing | K18: 6628 | L18: 7142 | M18: -13874 | N18: -15876 | O18: -14501 | P18: -16541 | Q18: -11307 | R18: -10362 | S18: -10472 | T18: -13179 | U18: 136 | V18: 133 | W18: 10152 | X18: 7219 | Y18: 6627 | Z18: 3561 | AA18: 9356 | AB18: 6768 | AC18: 22732495 | AD18: 20892941 | AF18: =Q18/W18 -> -1.1137707 | AG18: =R18/X18 -> -1.4353789 | AH18: =U18/W18 -> 0.013396375 | AI18: =V18/X18 -> 0.018423604 | AJ18: =Y18/AA18 -> 0.70831552 | AK18: =Z18/AB18 -> 0.52615248 | AL18: =O18/K18 -> -2.1878395 | AM18: =P18/L18 -> -2.3160179 | AN18: =K18/W18 -> 0.65287628 | AO18: =L18/X18 -> 0.9893337 | AP18: =IF(OR(Q18<0, Q18="NA"), 0, 1) -> 0 | AQ18: =IF(OR(S18<0, S18="NA"), 0, 1) -> 0 | AR18: =IFERROR(IF((AF18-AG18)>0,1,0),0) -> 1 | AS18: =IFERROR(IF((S18-Q18)>0,1,0),0) -> 1 | AT18: =IFERROR(IF((AH18-AI18)<0,1,0),0) -> 1 | AU18: =IFERROR(IF((AJ18-AK18)>0,1,0),0) -> 1 | AV18: =IFERROR(IF((AL18-AM18)>0,1,0),0) -> 1 | AW18: =IFERROR(IF((AN18-AO18)>0,1,0),0) -> 0 | AX18: =IFERROR(IF((AC18-AD18)<0,1,0),0) -> 0 | AY18: =SUM(AP18:AX18) -> 5
A19: AA Mission Acquisition Corp. (NYSE:AAM) | B19: 118460002 | C19: NYSE | D19: 10.12 | E19: 445.01688 | F19: Financials | G19: Financial Services | H19: Capital Markets | I19: Asset Management and Custody Banks | J19: 525990 - Other Financial Vehicles | K19: NA | L19: NA | M19: NA | N19: NA | O19: NA | P19: NA | Q19: NA | R19: NA | S19: NA | T19: NA | U19: NA | V19: NA | W19: NA | X19: NA | Y19: NA | Z19: NA | AA19: NA | AB19: NA | AC19: NA | AD19: NA | AF19: =Q19/W19 -> #VALUE! | AG19: =R19/X19 -> #VALUE! | AH19: =U19/W19 -> #VALUE! | AI19: =V19/X19 -> #VALUE! | AJ19: =Y19/AA19 -> #VALUE! | AK19: =Z19/AB19 -> #VALUE! | AL19: =O19/K19 -> #VALUE! | AM19: =P19/L19 -> #VALUE! | AN19: =K19/W19 -> #VALUE! | AO19: =L19/X19 -> #VALUE! | AP19: =IF(OR(Q19<0, Q19="NA"), 0, 1) -> 0 | AQ19: =IF(OR(S19<0, S19="NA"), 0, 1) -> 0 | AR19: =IFERROR(IF((AF19-AG19)>0,1,0),0) -> 0 | AS19: =IFERROR(IF((S19-Q19)>0,1,0),0) -> 0 | AT19: =IFERROR(IF((AH19-AI19)<0,1,0),0) -> 0 | AU19: =IFERROR(IF((AJ19-AK19)>0,1,0),0) -> 0 | AV19: =IFERROR(IF((AL19-AM19)>0,1,0),0) -> 0 | AW19: =IFERROR(IF((AN19-AO19)>0,1,0),0) -> 0 | AX19: =IFERROR(IF((AC19-AD19)<0,1,0),0) -> 0 | AY19: =SUM(AP19:AX19) -> 0
A20: AAON, Inc. (NASDAQGS:AAON) | B20: 4987250 | C20: NASDAQGS | D20: 123.4 | E20: 10029.906 | F20: Industrials | G20: Capital Goods | H20: Building Products | I20: Building Products | J20: 333415 - Air-Conditioning and Warm Air Heating Equipment and Commercial and Industrial Refrigeration Equipment Manufacturing | K20: 1209555 | L20: 1194273 | M20: 310718 | N20: 304944 | O20: 252504 | P20: 251789 | Q20: 190918 | R20: 186371 | S20: 243437 | T20: 226867 | U20: 55677 | V20: 85884 | W20: 1030625 | X20: 1010716 | Y20: 427836 | Z20: 423095 | AA20: 139833 | AB20: 141319 | AC20: 81246902 | AD20: 80950856 | AF20: =Q20/W20 -> 0.18524488 | AG20: =R20/X20 -> 0.18439502 | AH20: =U20/W20 -> 0.054022559 | AI20: =V20/X20 -> 0.084973425 | AJ20: =Y20/AA20 -> 3.0596211 | AK20: =Z20/AB20 -> 2.9939003 | AL20: =O20/K20 -> 0.20875777 | AM20: =P20/L20 -> 0.21083035 | AN20: =K20/W20 -> 1.1736131 | AO20: =L20/X20 -> 1.1816109 | AP20: =IF(OR(Q20<0, Q20="NA"), 0, 1) -> 1 | AQ20: =IF(OR(S20<0, S20="NA"), 0, 1) -> 1 | AR20: =IFERROR(IF((AF20-AG20)>0,1,0),0) -> 1 | AS20: =IFERROR(IF((S20-Q20)>0,1,0),0) -> 1 | AT20: =IFERROR(IF((AH20-AI20)<0,1,0),0) -> 1 | AU20: =IFERROR(IF((AJ20-AK20)>0,1,0),0) -> 1 | AV20: =IFERROR(IF((AL20-AM20)>0,1,0),0) -> 0 | AW20: =IFERROR(IF((AN20-AO20)>0,1,0),0) -> 0 | AX20: =IFERROR(IF((AC20-AD20)<0,1,0),0) -> 0 | AY20: =SUM(AP20:AX20) -> 6
A21: AAR Corp. (NYSE:AIR) | B21: 4157610 | C21: NYSE | D21: 69.45 | E21: 2450.1022 | F21: Industrials | G21: Capital Goods | H21: Aerospace and Defense | I21: Aerospace and Defense | J21: 488190 - Other Support Activities for Air Transportation | K21: 2571600 | L21: 2430900 | M21: 197800 | N21: 212800 | O21: 144900 | P21: 165800 | Q21: 10500 | R21: 64900 | S21: 48300 | T21: 43700 | U21: 986700 | V21: 981000 | W21: 2849300 | X21: 2783300 | Y21: 1498000 | Z21: 1426900 | AA21: 558300 | AB21: 466900 | AC21: 35278649 | AD21: 35271686 | AF21: =Q21/W21 -> 0.0036851156 | AG21: =R21/X21 -> 0.023317645 | AH21: =U21/W21 -> 0.34629558 | AI21: =V21/X21 -> 0.35245931 | AJ21: =Y21/AA21 -> 2.6831453 | AK21: =Z21/AB21 -> 3.0561148 | AL21: =O21/K21 -> 0.056346244 | AM21: =P21/L21 -> 0.068205191 | AN21: =K21/W21 -> 0.90253747 | AO21: =L21/X21 -> 0.87338771 | AP21: =IF(OR(Q21<0, Q21="NA"), 0, 1) -> 1 | AQ21: =IF(OR(S21<0, S21="NA"), 0, 1) -> 1 | AR21: =IFERROR(IF((AF21-AG21)>0,1,0),0) -> 0 | AS21: =IFERROR(IF((S21-Q21)>0,1,0),0) -> 1 | AT21: =IFERROR(IF((AH21-AI21)<0,1,0),0) -> 1 | AU21: =IFERROR(IF((AJ21-AK21)>0,1,0),0) -> 0 | AV21: =IFERROR(IF((AL21-AM21)>0,1,0),0) -> 0 | AW21: =IFERROR(IF((AN21-AO21)>0,1,0),0) -> 1 | AX21: =IFERROR(IF((AC21-AD21)<0,1,0),0) -> 0 | AY21: =SUM(AP21:AX21) -> 5
A22: AB Active ETFs, Inc. - AB Conservative Buffer ETF (NASDAQGM:BUFC) | B22: 112904984 | C22: NASDAQGM | D22: 39.04 | E22: 712.48 | F22: Financials | G22: Financial Services | H22: Capital Markets | I22: Asset Management and Custody Banks | K22: NA | L22: NA | M22: NA | N22: NA | O22: NA | P22: NA | Q22: NA | R22: NA | S22: NA | T22: NA | U22: NA | V22: NA | W22: NA | X22: NA | Y22: NA | Z22: NA | AA22: NA | AB22: NA | AC22: NA | AD22: NA | AF22: =Q22/W22 -> #VALUE! | AG22: =R22/X22 -> #VALUE! | AH22: =U22/W22 -> #VALUE! | AI22: =V22/X22 -> #VALUE! | AJ22: =Y22/AA22 -> #VALUE! | AK22: =Z22/AB22 -> #VALUE! | AL22: =O22/K22 -> #VALUE! | AM22: =P22/L22 -> #VALUE! | AN22: =K22/W22 -> #VALUE! | AO22: =L22/X22 -> #VALUE! | AP22: =IF(OR(Q22<0, Q22="NA"), 0, 1) -> 0 | AQ22: =IF(OR(S22<0, S22="NA"), 0, 1) -> 0 | AR22: =IFERROR(IF((AF22-AG22)>0,1,0),0) -> 0 | AS22: =IFERROR(IF((S22-Q22)>0,1,0),0) -> 0 | AT22: =IFERROR(IF((AH22-AI22)<0,1,0),0) -> 0 | AU22: =IFERROR(IF((AJ22-AK22)>0,1,0),0) -> 0 | AV22: =IFERROR(IF((AL22-AM22)>0,1,0),0) -> 0 | AW22: =IFERROR(IF((AN22-AO22)>0,1,0),0) -> 0 | AX22: =IFERROR(IF((AC22-AD22)<0,1,0),0) -> 0 | AY22: =SUM(AP22:AX22) -> 0
A23: AB Active ETFs, Inc. - AB Core Plus Bond ETF (NASDAQGM:CPLS) | B23: 113622077 | C23: NASDAQGM | D23: 34.47 | E23: 58.599 | F23: Financials | G23: Financial Services | H23: Capital Markets | I23: Asset Management and Custody Banks | K23: NA | L23: NA | M23: NA | N23: NA | O23: NA | P23: NA | Q23: NA | R23: NA | S23: NA | T23: NA | U23: NA | V23: NA | W23: NA | X23: NA | Y23: NA | Z23: NA | AA23: NA | AB23: NA | AC23: NA | AD23: NA | AF23: =Q23/W23 -> #VALUE! | AG23: =R23/X23 -> #VALUE! | AH23: =U23/W23 -> #VALUE! | AI23: =V23/X23 -> #VALUE! | AJ23: =Y23/AA23 -> #VALUE! | AK23: =Z23/AB23 -> #VALUE! | AL23: =O23/K23 -> #VALUE! | AM23: =P23/L23 -> #VALUE! | AN23: =K23/W23 -> #VALUE! | AO23: =L23/X23 -> #VALUE! | AP23: =IF(OR(Q23<0, Q23="NA"), 0, 1) -> 0 | AQ23: =IF(OR(S23<0, S23="NA"), 0, 1) -> 0 | AR23: =IFERROR(IF((AF23-AG23)>0,1,0),0) -> 0 | AS23: =IFERROR(IF((S23-Q23)>0,1,0),0) -> 0 | AT23: =IFERROR(IF((AH23-AI23)<0,1,0),0) -> 0 | AU23: =IFERROR(IF((AJ23-AK23)>0,1,0),0) -> 0 | AV23: =IFERROR(IF((AL23-AM23)>0,1,0),0) -> 0 | AW23: =IFERROR(IF((AN23-AO23)>0,1,0),0) -> 0 | AX23: =IFERROR(IF((AC23-AD23)<0,1,0),0) -> 0 | AY23: =SUM(AP23:AX23) -> 0
A24: AB Active ETFs, Inc. - AB Corporate Bond ETF (NASDAQGM:EYEG) | B24: 114183165 | C24: NASDAQGM | D24: 34.555 | E24: 25.91625 | F24: Financials | G24: Financial Services | H24: Capital Markets | I24: Asset Management and Custody Banks | K24: NA | L24: NA | M24: NA | N24: NA | O24: NA | P24: NA | Q24: NA | R24: NA | S24: NA | T24: NA | U24: NA | V24: NA | W24: NA | X24: NA | Y24: NA | Z24: NA | AA24: NA | AB24: NA | AC24: NA | AD24: NA | AF24: =Q24/W24 -> #VALUE! | AG24: =R24/X24 -> #VALUE! | AH24: =U24/W24 -> #VALUE! | AI24: =V24/X24 -> #VALUE! | AJ24: =Y24/AA24 -> #VALUE! | AK24: =Z24/AB24 -> #VALUE! | AL24: =O24/K24 -> #VALUE! | AM24: =P24/L24 -> #VALUE! | AN24: =K24/W24 -> #VALUE! | AO24: =L24/X24 -> #VALUE! | AP24: =IF(OR(Q24<0, Q24="NA"), 0, 1) -> 0 | AQ24: =IF(OR(S24<0, S24="NA"), 0, 1) -> 0 | AR24: =IFERROR(IF((AF24-AG24)>0,1,0),0) -> 0 | AS24: =IFERROR(IF((S24-Q24)>0,1,0),0) -> 0 | AT24: =IFERROR(IF((AH24-AI24)<0,1,0),0) -> 0 | AU24: =IFERROR(IF((AJ24-AK24)>0,1,0),0) -> 0 | AV24: =IFERROR(IF((AL24-AM24)>0,1,0),0) -> 0 | AW24: =IFERROR(IF((AN24-AO24)>0,1,0),0) -> 0 | AX24: =IFERROR(IF((AC24-AD24)<0,1,0),0) -> 0 | AY24: =SUM(AP24:AX24) -> 0
A25: Abacus Life, Inc. (NASDAQCM:ABL) | B25: 107089758 | C25: NASDAQCM | D25: 7.11 | E25: 667.5757 | F25: Financials | G25: Insurance | H25: Insurance | I25: Insurance Brokers | J25: 5242 - Agencies, Brokerages, and Other Insurance Related Activities | K25: 102407.32 | L25: 95379.763 | M25: 27886.217 | N25: 25797.275 | O25: 20995.498 | P25: 18956.982 | Q25: -12273.363 | R25: -5937.58 | S25: -131117.95 | T25: -90701.488 | U25: 166512.99 | V25: 151311.3 | W25: 477309.17 | X25: 483854.91 | Y25: 30796.677 | Z25: 101637.37 | AA25: 23862 | AB25: 55383 | AC25: 74708213 | AD25: 74436341 | AF25: =Q25/W25 -> -0.025713654 | AG25: =R25/X25 -> -0.012271406 | AH25: =U25/W25 -> 0.34885773 | AI25: =V25/X25 -> 0.31272039 | AJ25: =Y25/AA25 -> 1.2906159 | AK25: =Z25/AB25 -> 1.8351727 | AL25: =O25/K25 -> 0.2050195 | AM25: =P25/L25 -> 0.19875266 | AN25: =K25/W25 -> 0.21455135 | AO25: =L25/X25 -> 0.19712472 | AP25: =IF(OR(Q25<0, Q25="NA"), 0, 1) -> 0 | AQ25: =IF(OR(S25<0, S25="NA"), 0, 1) -> 0 | AR25: =IFERROR(IF((AF25-AG25)>0,1,0),0) -> 0 | AS25: =IFERROR(IF((S25-Q25)>0,1,0),0) -> 0 | AT25: =IFERROR(IF((AH25-AI25)<0,1,0),0) -> 0 | AU25: =IFERROR(IF((AJ25-AK25)>0,1,0),0) -> 0 | AV25: =IFERROR(IF((AL25-AM25)>0,1,0),0) -> 1 | AW25: =IFERROR(IF((AN25-AO25)>0,1,0),0) -> 1 | AX25: =IFERROR(IF((AC25-AD25)<0,1,0),0) -> 0 | AY25: =SUM(AP25:AX25) -> 2
A26: Abbott Laboratories (NYSE:ABT) | B26: 4004092 | C26: NYSE | D26: 113.19 | E26: 196322.99 | F26: Health Care | G26: Health Care Equipment and Services | H26: Health Care Equipment and Supplies | I26: Health Care Equipment | J26: 339112 - Surgical and Medical Instrument Manufacturing | K26: 41217000 | L26: 40725000 | M26: 10825000 | N26: 10623000 | O26: 7601000 | P26: 7376000 | Q26: 5767000 | R26: 5557000 | S26: 8728000 | T26: 7900000 | U26: 12879000 | V26: 13213000 | W26: 74356000 | X26: 73017000 | Y26: 23802000 | Z26: 23119000 | AA26: 14902000 | AB26: 13760000 | AC26: 1734455938 | AD26: 1739897729 | AF26: =Q26/W26 -> 0.077559309 | AG26: =R26/X26 -> 0.076105564 | AH26: =U26/W26 -> 0.17320727 | AI26: =V26/X26 -> 0.18095786 | AJ26: =Y26/AA26 -> 1.5972353 | AK26: =Z26/AB26 -> 1.6801599 | AL26: =O26/K26 -> 0.1844142 | AM26: =P26/L26 -> 0.18111725 | AN26: =K26/W26 -> 0.55431976 | AO26: =L26/X26 -> 0.55774683 | AP26: =IF(OR(Q26<0, Q26="NA"), 0, 1) -> 1 | AQ26: =IF(OR(S26<0, S26="NA"), 0, 1) -> 1 | AR26: =IFERROR(IF((AF26-AG26)>0,1,0),0) -> 1 | AS26: =IFERROR(IF((S26-Q26)>0,1,0),0) -> 1 | AT26: =IFERROR(IF((AH26-AI26)<0,1,0),0) -> 1 | AU26: =IFERROR(IF((AJ26-AK26)>0,1,0),0) -> 0 | AV26: =IFERROR(IF((AL26-AM26)>0,1,0),0) -> 1 | AW26: =IFERROR(IF((AN26-AO26)>0,1,0),0) -> 0 | AX26: =IFERROR(IF((AC26-AD26)<0,1,0),0) -> 1 | AY26: =SUM(AP26:AX26) -> 7
A27: AbbVie Inc. (NYSE:ABBV) | B27: 4558282 | C27: NYSE | D27: 176.74 | E27: 312324.38 | F27: Health Care | G27: Pharmaceuticals, Biotechnology and Life Sciences | H27: Biotechnology | I27: Biotechnology | J27: 325414 - Biological Product (except Diagnostic) Manufacturing | K27: 55533000 | L27: 55000000 | M27: 25630000 | N27: 26121000 | O27: 17270000 | P27: 17605000 | Q27: 5133000 | R27: 5350000 | S27: 16511000 | T27: 18638000 | U27: 58753000 | V27: 58352000 | W27: 143422000 | X27: 141937000 | Y27: 27785000 | Z27: 33816000 | AA27: 43062000 | AB27: 41915000 | AC27: 1767104613 | AD27: 1765942851 | AF27: =Q27/W27 -> 0.035789488 | AG27: =R27/X27 -> 0.037692779 | AH27: =U27/W27 -> 0.40965124 | AI27: =V27/X27 -> 0.41111197 | AJ27: =Y27/AA27 -> 0.64523246 | AK27: =Z27/AB27 -> 0.80677562 | AL27: =O27/K27 -> 0.31098626 | AM27: =P27/L27 -> 0.32009091 | AN27: =K27/W27 -> 0.38720001 | AO27: =L27/X27 -> 0.38749586 | AP27: =IF(OR(Q27<0, Q27="NA"), 0, 1) -> 1 | AQ27: =IF(OR(S27<0, S27="NA"), 0, 1) -> 1 | AR27: =IFERROR(IF((AF27-AG27)>0,1,0),0) -> 0 | AS27: =IFERROR(IF((S27-Q27)>0,1,0),0) -> 1 | AT27: =IFERROR(IF((AH27-AI27)<0,1,0),0) -> 1 | AU27: =IFERROR(IF((AJ27-AK27)>0,1,0),0) -> 0 | AV27: =IFERROR(IF((AL27-AM27)>0,1,0),0) -> 0 | AW27: =IFERROR(IF((AN27-AO27)>0,1,0),0) -> 0 | AX27: =IFERROR(IF((AC27-AD27)<0,1,0),0) -> 0 | AY27: =SUM(AP27:AX27) -> 4
A28: Abeona Therapeutics Inc. (NASDAQCM:ABEO) | B28: 4812619 | C28: NASDAQCM | D28: 5.61 | E28: 243.87248 | F28: Health Care | G28: Pharmaceuticals, Biotechnology and Life Sciences | H28: Biotechnology | I28: Biotechnology | J28: 325414 - Biological Product (except Diagnostic) Manufacturing | K28: 0 | L28: 0 | M28: -58792 | N28: -54747 | O28: -60748 | P28: -56737 | Q28: -71032 | R28: -52599 | S28: -48691 | T28: -42203 | U28: 14206 | V28: 16133 | W28: 120592 | X28: 134003 | Y28: 112657 | Z28: 125904 | AA28: 18422 | AB28: 16843 | AC28: 43404706 | AD28: 41661993 | AF28: =Q28/W28 -> -0.58902746 | AG28: =R28/X28 -> -0.39252106 | AH28: =U28/W28 -> 0.11780218 | AI28: =V28/X28 -> 0.12039283 | AJ28: =Y28/AA28 -> 6.1153512 | AK28: =Z28/AB28 -> 7.4751529 | AL28: =O28/K28 -> #DIV/0! | AM28: =P28/L28 -> #DIV/0! | AN28: =K28/W28 -> 0 | AO28: =L28/X28 -> 0 | AP28: =IF(OR(Q28<0, Q28="NA"), 0, 1) -> 0 | AQ28: =IF(OR(S28<0, S28="NA"), 0, 1) -> 0 | AR28: =IFERROR(IF((AF28-AG28)>0,1,0),0) -> 0 | AS28: =IFERROR(IF((S28-Q28)>0,1,0),0) -> 1 | AT28: =IFERROR(IF((AH28-AI28)<0,1,0),0) -> 1 | AU28: =IFERROR(IF((AJ28-AK28)>0,1,0),0) -> 0 | AV28: =IFERROR(IF((AL28-AM28)>0,1,0),0) -> 0 | AW28: =IFERROR(IF((AN28-AO28)>0,1,0),0) -> 0 | AX28: =IFERROR(IF((AC28-AD28)<0,1,0),0) -> 0 | AY28: =SUM(AP28:AX28) -> 2
A29: Abercrombie & Fitch Co. (NYSE:ANF) | B29: 4066681 | C29: NYSE | D29: 135.72 | E29: 6836.5814 | F29: Consumer Discretionary | G29: Consumer Discretionary Distribution and Retail | H29: Specialty Retail | I29: Apparel Retail | J29: 458110 - Clothing and Clothing Accessories Retailers | K29: 4816577 | L29: 4664042 | M29: 866770 | N29: 816855 | O29: 714603 | P29: 671118 | Q29: 545424 | R29: 509292 | S29: 706036 | T29: 697213 | U29: NA | V29: NA | W29: 3269872 | X29: 3049558 | Y29: 1655767 | Z29: 1516653 | AA29: 1182089 | AB29: 1051656 | AC29: 50371000 | AD29: 51069000 | AF29: =Q29/W29 -> 0.16680286 | AG29: =R29/X29 -> 0.16700519 | AH29: =U29/W29 -> #VALUE! | AI29: =V29/X29 -> #VALUE! | AJ29: =Y29/AA29 -> 1.4007126 | AK29: =Z29/AB29 -> 1.4421569 | AL29: =O29/K29 -> 0.14836325 | AM29: =P29/L29 -> 0.14389193 | AN29: =K29/W29 -> 1.473017 | AO29: =L29/X29 -> 1.5294157 | AP29: =IF(OR(Q29<0, Q29="NA"), 0, 1) -> 1 | AQ29: =IF(OR(S29<0, S29="NA"), 0, 1) -> 1 | AR29: =IFERROR(IF((AF29-AG29)>0,1,0),0) -> 0 | AS29: =IFERROR(IF((S29-Q29)>0,1,0),0) -> 1 | AT29: =IFERROR(IF((AH29-AI29)<0,1,0),0) -> 0 | AU29: =IFERROR(IF((AJ29-AK29)>0,1,0),0) -> 0 | AV29: =IFERROR(IF((AL29-AM29)>0,1,0),0) -> 1 | AW29: =IFERROR(IF((AN29-AO29)>0,1,0),0) -> 0 | AX29: =IFERROR(IF((AC29-AD29)<0,1,0),0) -> 1 | AY29: =SUM(AP29:AX29) -> 5
A30: ABM Industries Incorporated (NYSE:ABM) | B30: 4066692 | C30: NYSE | D30: 51.68 | E30: 3214.6702 | F30: Industrials | G30: Commercial and Professional Services | H30: Commercial Services and Supplies | I30: Environmental and Facilities Services | J30: 5617 - Services to Buildings and Dwellings | K30: 8359400 | L30: 8274900 | M30: 414400 | N30: 370400 | O30: 307800 | P30: 261500 | Q30: 81400 | R30: 155900 | S30: 226700 | T30: 335500 | U30: 1302200 | V30: 1305100 | W30: 5097200 | X30: 5040400 | Y30: 1788700 | Z30: 1723400 | AA30: 1348400 | AB30: 1246100 | AC30: 62196665 | AD30: 62785283 | AF30: =Q30/W30 -> 0.015969552 | AG30: =R30/X30 -> 0.030930085 | AH30: =U30/W30 -> 0.25547359 | AI30: =V30/X30 -> 0.25892786 | AJ30: =Y30/AA30 -> 1.3265352 | AK30: =Z30/AB30 -> 1.3830351 | AL30: =O30/K30 -> 0.036820824 | AM30: =P30/L30 -> 0.03160159 | AN30: =K30/W30 -> 1.6399984 | AO30: =L30/X30 -> 1.6417149 | AP30: =IF(OR(Q30<0, Q30="NA"), 0, 1) -> 1 | AQ30: =IF(OR(S30<0, S30="NA"), 0, 1) -> 1 | AR30: =IFERROR(IF((AF30-AG30)>0,1,0),0) -> 0 | AS30: =IFERROR(IF((S30-Q30)>0,1,0),0) -> 1 | AT30: =IFERROR(IF((AH30-AI30)<0,1,0),0) -> 1 | AU30: =IFERROR(IF((AJ30-AK30)>0,1,0),0) -> 0 | AV30: =IFERROR(IF((AL30-AM30)>0,1,0),0) -> 1 | AW30: =IFERROR(IF((AN30-AO30)>0,1,0),0) -> 0 | AX30: =IFERROR(IF((AC30-AD30)<0,1,0),0) -> 1 | AY30: =SUM(AP30:AX30) -> 6
A31: Abrdn Global Dynamic Dividend Fund (NYSE:AGD) | B31: 5724762 | C31: NYSE | D31: 9.87 | E31: 123.86437 | F31: Financials | G31: Financial Services | H31: Capital Markets | I31: Asset Management and Custody Banks | K31: 21673.448 | L31: 19980.42 | M31: NA | N31: NA | O31: 18463.656 | P31: 16789.708 | Q31: 54117.787 | R31: 34440.128 | S31: NA | T31: NA | U31: NA | V31: NA | W31: 285985.84 | X31: 285985.84 | Y31: 4031.509 | Z31: 4031.509 | AA31: 8650 | AB31: 8650 | AC31: 24865081 | AD31: 24865081 | AF31: =Q31/W31 -> 0.1892324 | AG31: =R31/X31 -> 0.12042599 | AH31: =U31/W31 -> #VALUE! | AI31: =V31/X31 -> #VALUE! | AJ31: =Y31/AA31 -> 0.4660704 | AK31: =Z31/AB31 -> 0.4660704 | AL31: =O31/K31 -> 0.85190211 | AM31: =P31/L31 -> 0.84030806 | AN31: =K31/W31 -> 0.07578504 | AO31: =L31/X31 -> 0.069865068 | AP31: =IF(OR(Q31<0, Q31="NA"), 0, 1) -> 1 | AQ31: =IF(OR(S31<0, S31="NA"), 0, 1) -> 0 | AR31: =IFERROR(IF((AF31-AG31)>0,1,0),0) -> 1 | AS31: =IFERROR(IF((S31-Q31)>0,1,0),0) -> 0 | AT31: =IFERROR(IF((AH31-AI31)<0,1,0),0) -> 0 | AU31: =IFERROR(IF((AJ31-AK31)>0,1,0),0) -> 0 | AV31: =IFERROR(IF((AL31-AM31)>0,1,0),0) -> 1 | AW31: =IFERROR(IF((AN31-AO31)>0,1,0),0) -> 1 | AX31: =IFERROR(IF((AC31-AD31)<0,1,0),0) -> 0 | AY31: =SUM(AP31:AX31) -> 4
A32: Abrdn Global Infrastructure Income Fund (NYSE:ASGI) | B32: 19477916 | C32: NYSE | D32: 17.33 | E32: 501.60351 | F32: Financials | G32: Financial Services | H32: Capital Markets | I32: Asset Management and Custody Banks | J32: 525990 - Other Financial Vehicles | K32: NA | L32: NA | M32: NA | N32: NA | O32: NA | P32: NA | Q32: NA | R32: NA | S32: NA | T32: NA | U32: NA | V32: NA | W32: NA | X32: NA | Y32: NA | Z32: NA | AA32: NA | AB32: NA | AC32: NA | AD32: NA | AF32: =Q32/W32 -> #VALUE! | AG32: =R32/X32 -> #VALUE! | AH32: =U32/W32 -> #VALUE! | AI32: =V32/X32 -> #VALUE! | AJ32: =Y32/AA32 -> #VALUE! | AK32: =Z32/AB32 -> #VALUE! | AL32: =O32/K32 -> #VALUE! | AM32: =P32/L32 -> #VALUE! | AN32: =K32/W32 -> #VALUE! | AO32: =L32/X32 -> #VALUE! | AP32: =IF(OR(Q32<0, Q32="NA"), 0, 1) -> 0 | AQ32: =IF(OR(S32<0, S32="NA"), 0, 1) -> 0 | AR32: =IFERROR(IF((AF32-AG32)>0,1,0),0) -> 0 | AS32: =IFERROR(IF((S32-Q32)>0,1,0),0) -> 0 | AT32: =IFERROR(IF((AH32-AI32)<0,1,0),0) -> 0 | AU32: =IFERROR(IF((AJ32-AK32)>0,1,0),0) -> 0 | AV32: =IFERROR(IF((AL32-AM32)>0,1,0),0) -> 0 | AW32: =IFERROR(IF((AN32-AO32)>0,1,0),0) -> 0 | AX32: =IFERROR(IF((AC32-AD32)<0,1,0),0) -> 0 | AY32: =SUM(AP32:AX32) -> 0
A33: Abrdn Healthcare Investors (NYSE:HQH) | B33: 5720683 | C33: NYSE | D33: 16.79 | E33: 875.26089 | F33: Financials | G33: Financial Services | H33: Capital Markets | I33: Asset Management and Custody Banks | K33: 10769.258 | L33: 10369.271 | M33: NA | N33: NA | O33: -220.271 | P33: -636.865 | Q33: 184946.63 | R33: 128907.86 | S33: NA | T33: NA | U33: NA | V33: NA | W33: 1060991.1 | X33: 1060991.1 | Y33: 603.882 | Z33: 603.882 | AA33: 1395 | AB33: 1395 | AC33: 52129892 | AD33: 52129892 | AF33: =Q33/W33 -> 0.17431498 | AG33: =R33/X33 -> 0.12149759 | AH33: =U33/W33 -> #VALUE! | AI33: =V33/X33 -> #VALUE! | AJ33: =Y33/AA33 -> 0.43289032 | AK33: =Z33/AB33 -> 0.43289032 | AL33: =O33/K33 -> -0.020453684 | AM33: =P33/L33 -> -0.061418493 | AN33: =K33/W33 -> 0.010150187 | AO33: =L33/X33 -> 0.0097731936 | AP33: =IF(OR(Q33<0, Q33="NA"), 0, 1) -> 1 | AQ33: =IF(OR(S33<0, S33="NA"), 0, 1) -> 0 | AR33: =IFERROR(IF((AF33-AG33)>0,1,0),0) -> 1 | AS33: =IFERROR(IF((S33-Q33)>0,1,0),0) -> 0 | AT33: =IFERROR(IF((AH33-AI33)<0,1,0),0) -> 0 | AU33: =IFERROR(IF((AJ33-AK33)>0,1,0),0) -> 0 | AV33: =IFERROR(IF((AL33-AM33)>0,1,0),0) -> 1 | AW33: =IFERROR(IF((AN33-AO33)>0,1,0),0) -> 1 | AX33: =IFERROR(IF((AC33-AD33)<0,1,0),0) -> 0 | AY33: =SUM(AP33:AX33) -> 4
A34: Abrdn Healthcare Opportunities Fund (NYSE:THQ) | B34: 5735674 | C34: NYSE | D34: 19.41 | E34: 802.41806 | F34: Financials | G34: Financial Services | H34: Capital Markets | I34: Asset Management and Custody Banks | K34: NA | L34: NA | M34: NA | N34: NA | O34: NA | P34: NA | Q34: NA | R34: NA | S34: NA | T34: NA | U34: NA | V34: NA | W34: NA | X34: NA | Y34: NA | Z34: NA | AA34: NA | AB34: NA | AC34: NA | AD34: NA | AF34: =Q34/W34 -> #VALUE! | AG34: =R34/X34 -> #VALUE! | AH34: =U34/W34 -> #VALUE! | AI34: =V34/X34 -> #VALUE! | AJ34: =Y34/AA34 -> #VALUE! | AK34: =Z34/AB34 -> #VALUE! | AL34: =O34/K34 -> #VALUE! | AM34: =P34/L34 -> #VALUE! | AN34: =K34/W34 -> #VALUE! | AO34: =L34/X34 -> #VALUE! | AP34: =IF(OR(Q34<0, Q34="NA"), 0, 1) -> 0 | AQ34: =IF(OR(S34<0, S34="NA"), 0, 1) -> 0 | AR34: =IFERROR(IF((AF34-AG34)>0,1,0),0) -> 0 | AS34: =IFERROR(IF((S34-Q34)>0,1,0),0) -> 0 | AT34: =IFERROR(IF((AH34-AI34)<0,1,0),0) -> 0 | AU34: =IFERROR(IF((AJ34-AK34)>0,1,0),0) -> 0 | AV34: =IFERROR(IF((AL34-AM34)>0,1,0),0) -> 0 | AW34: =IFERROR(IF((AN34-AO34)>0,1,0),0) -> 0 | AX34: =IFERROR(IF((AC34-AD34)<0,1,0),0) -> 0 | AY34: =SUM(AP34:AX34) -> 0
A35: Abrdn Income Credit Strategies Fund (NYSE:ACP) | B35: 5731540 | C35: NYSE | D35: 5.97 | E35: 749.05995 | F35: Financials | G35: Financial Services | H35: Capital Markets | I35: Asset Management and Custody Banks | K35: 60226.187 | L35: 51849.593 | M35: NA | N35: NA | O35: 50541.106 | P35: 43213.704 | Q35: 77913.516 | R35: 62703.47 | S35: -81305.552 | T35: 66029.759 | U35: 240000 | V35: 240000 | W35: 1137288.6 | X35: 1137288.6 | Y35: 32865.466 | Z35: 32865.466 | AA35: 37486 | AB35: 37486 | AC35: 125470678 | AD35: 125470678 | AF35: =Q35/W35 -> 0.068508131 | AG35: =R35/X35 -> 0.055134176 | AH35: =U35/W35 -> 0.21102823 | AI35: =V35/X35 -> 0.21102823 | AJ35: =Y35/AA35 -> 0.87673974 | AK35: =Z35/AB35 -> 0.87673974 | AL35: =O35/K35 -> 0.83918821 | AM35: =P35/L35 -> 0.83344346 | AN35: =K35/W35 -> 0.05295594 | AO35: =L35/X35 -> 0.045590533 | AP35: =IF(OR(Q35<0, Q35="NA"), 0, 1) -> 1 | AQ35: =IF(OR(S35<0, S35="NA"), 0, 1) -> 0 | AR35: =IFERROR(IF((AF35-AG35)>0,1,0),0) -> 1 | AS35: =IFERROR(IF((S35-Q35)>0,1,0),0) -> 0 | AT35: =IFERROR(IF((AH35-AI35)<0,1,0),0) -> 0 | AU35: =IFERROR(IF((AJ35-AK35)>0,1,0),0) -> 0 | AV35: =IFERROR(IF((AL35-AM35)>0,1,0),0) -> 1 | AW35: =IFERROR(IF((AN35-AO35)>0,1,0),0) -> 1 | AX35: =IFERROR(IF((AC35-AD35)<0,1,0),0) -> 0 | AY35: =SUM(AP35:AX35) -> 4
A36: Abrdn Japan Equity Fund Inc (NYSE:JEQ) | B36: 5721558 | C36: NYSE | D36: 5.64 | E36: 78.104576 | F36: Financials | G36: Financial Services | H36: Capital Markets | I36: Asset Management and Custody Banks | K36: 1919.471 | L36: 1845.097 | M36: NA | N36: NA | O36: 937.958 | P36: 808.77 | Q36: 18925.896 | R36: 15678.377 | S36: 4913.065 | T36: 4480.073 | U36: NA | V36: NA | W36: 108172.06 | X36: 108172.06 | Y36: 2146.824 | Z36: 2146.824 | AA36: 10773 | AB36: 10773 | AC36: 13999038 | AD36: 13999038 | AF36: =Q36/W36 -> 0.17496104 | AG36: =R36/X36 -> 0.14493925 | AH36: =U36/W36 -> #VALUE! | AI36: =V36/X36 -> #VALUE! | AJ36: =Y36/AA36 -> 0.1992782 | AK36: =Z36/AB36 -> 0.1992782 | AL36: =O36/K36 -> 0.48865443 | AM36: =P36/L36 -> 0.43833468 | AN36: =K36/W36 -> 0.01774461 | AO36: =L36/X36 -> 0.017057057 | AP36: =IF(OR(Q36<0, Q36="NA"), 0, 1) -> 1 | AQ36: =IF(OR(S36<0, S36="NA"), 0, 1) -> 1 | AR36: =IFERROR(IF((AF36-AG36)>0,1,0),0) -> 1 | AS36: =IFERROR(IF((S36-Q36)>0,1,0),0) -> 0 | AT36: =IFERROR(IF((AH36-AI36)<0,1,0),0) -> 0 | AU36: =IFERROR(IF((AJ36-AK36)>0,1,0),0) -> 0 | AV36: =IFERROR(IF((AL36-AM36)>0,1,0),0) -> 1 | AW36: =IFERROR(IF((AN36-AO36)>0,1,0),0) -> 1 | AX36: =IFERROR(IF((AC36-AD36)<0,1,0),0) -> 0 | AY36: =SUM(AP36:AX36) -> 5
A37: Abrdn Life Sciences Investors (NYSE:HQL) | B37: 5720684 | C37: NYSE | D37: 13.43 | E37: 376.86459 | F37: Financials | G37: Financial Services | H37: Capital Markets | I37: Asset Management and Custody Banks | K37: 3979.986 | L37: 3512.919 | M37: NA | N37: NA | O37: -1920.347 | P37: -2243.029 | Q37: 85296.459 | R37: 5496.099 | S37: NA | T37: NA | U37: NA | V37: NA | W37: 460583.22 | X37: 432689.12 | Y37: 281.797 | Z37: 2693.02 | AA37: 889 | AB37: 10044 | AC37: 28061399 | AD37: 26212047 | AF37: =Q37/W37 -> 0.18519229 | AG37: =R37/X37 -> 0.012702189 | AH37: =U37/W37 -> #VALUE! | AI37: =V37/X37 -> #VALUE! | AJ37: =Y37/AA37 -> 0.316982 | AK37: =Z37/AB37 -> 0.26812226 | AL37: =O37/K37 -> -0.48250094 | AM37: =P37/L37 -> -0.6385086 | AN37: =K37/W37 -> 0.0086411877 | AO37: =L37/X37 -> 0.008118806 | AP37: =IF(OR(Q37<0, Q37="NA"), 0, 1) -> 1 | AQ37: =IF(OR(S37<0, S37="NA"), 0, 1) -> 0 | AR37: =IFERROR(IF((AF37-AG37)>0,1,0),0) -> 1 | AS37: =IFERROR(IF((S37-Q37)>0,1,0),0) -> 0 | AT37: =IFERROR(IF((AH37-AI37)<0,1,0),0) -> 0 | AU37: =IFERROR(IF((AJ37-AK37)>0,1,0),0) -> 1 | AV37: =IFERROR(IF((AL37-AM37)>0,1,0),0) -> 1 | AW37: =IFERROR(IF((AN37-AO37)>0,1,0),0) -> 1 | AX37: =IFERROR(IF((AC37-AD37)<0,1,0),0) -> 0 | AY37: =SUM(AP37:AX37) -> 5
A38: Abrdn Total Dynamic Dividend Fund (NYSE:AOD) | B38: 5726755 | C38: NYSE | D38: 8.51 | E38: 897.21779 | F38: Financials | G38: Financial Services | H38: Capital Markets | I38: Asset Management and Custody Banks | K38: 72962.082 | L38: NA | M38: NA | N38: NA | O38: 61388.086 | P38: NA | Q38: 203771.4 | R38: 128320.15 | S38: NA | T38: NA | U38: NA | V38: NA | W38: 1029323.2 | X38: NA | Y38: 8653.219 | Z38: NA | AA38: 11477 | AB38: NA | AC38: 105430999 | AD38: 105430999 | AF38: =Q38/W38 -> 0.19796639 | AG38: =R38/X38 -> #VALUE! | AH38: =U38/W38 -> #VALUE! | AI38: =V38/X38 -> #VALUE! | AJ38: =Y38/AA38 -> 0.75396175 | AK38: =Z38/AB38 -> #VALUE! | AL38: =O38/K38 -> 0.84136971 | AM38: =P38/L38 -> #VALUE! | AN38: =K38/W38 -> 0.070883549 | AO38: =L38/X38 -> #VALUE! | AP38: =IF(OR(Q38<0, Q38="NA"), 0, 1) -> 1 | AQ38: =IF(OR(S38<0, S38="NA"), 0, 1) -> 0 | AR38: =IFERROR(IF((AF38-AG38)>0,1,0),0) -> 0 | AS38: =IFERROR(IF((S38-Q38)>0,1,0),0) -> 0 | AT38: =IFERROR(IF((AH38-AI38)<0,1,0),0) -> 0 | AU38: =IFERROR(IF((AJ38-AK38)>0,1,0),0) -> 0 | AV38: =IFERROR(IF((AL38-AM38)>0,1,0),0) -> 0 | AW38: =IFERROR(IF((AN38-AO38)>0,1,0),0) -> 0 | AX38: =IFERROR(IF((AC38-AD38)<0,1,0),0) -> 0 | AY38: =SUM(AP38:AX38) -> 1
A39: Abrdn World Healthcare Fund (NYSE:THW) | B39: 5736914 | C39: NYSE | D39: 11.45 | E39: 435.08185 | F39: Financials | G39: Financial Services | H39: Capital Markets | I39: Asset Management and Custody Banks | J39: 525990 - Other Financial Vehicles | K39: NA | L39: NA | M39: NA | N39: NA | O39: NA | P39: NA | Q39: NA | R39: NA | S39: NA | T39: NA | U39: NA | V39: NA | W39: NA | X39: NA | Y39: NA | Z39: NA | AA39: NA | AB39: NA | AC39: NA | AD39: NA | AF39: =Q39/W39 -> #VALUE! | AG39: =R39/X39 -> #VALUE! | AH39: =U39/W39 -> #VALUE! | AI39: =V39/X39 -> #VALUE! | AJ39: =Y39/AA39 -> #VALUE! | AK39: =Z39/AB39 -> #VALUE! | AL39: =O39/K39 -> #VALUE! | AM39: =P39/L39 -> #VALUE! | AN39: =K39/W39 -> #VALUE! | AO39: =L39/X39 -> #VALUE! | AP39: =IF(OR(Q39<0, Q39="NA"), 0, 1) -> 0 | AQ39: =IF(OR(S39<0, S39="NA"), 0, 1) -> 0 | AR39: =IFERROR(IF((AF39-AG39)>0,1,0),0) -> 0 | AS39: =IFERROR(IF((S39-Q39)>0,1,0),0) -> 0 | AT39: =IFERROR(IF((AH39-AI39)<0,1,0),0) -> 0 | AU39: =IFERROR(IF((AJ39-AK39)>0,1,0),0) -> 0 | AV39: =IFERROR(IF((AL39-AM39)>0,1,0),0) -> 0 | AW39: =IFERROR(IF((AN39-AO39)>0,1,0),0) -> 0 | AX39: =IFERROR(IF((AC39-AD39)<0,1,0),0) -> 0 | AY39: =SUM(AP39:AX39) -> 0
A40: Academy Sports and Outdoors, Inc. (NASDAQGS:ASO) | B40: 5223225 | C40: NASDAQGS | D40: 55.48 | E40: 3850.1509 | F40: Consumer Discretionary | G40: Consumer Discretionary Distribution and Retail | H40: Specialty Retail | I40: Other Specialty Retail | J40: 459110 - Sporting Goods Retailers | K40: 6051358 | L40: 6105805 | M40: 706559 | N40: 749851 | O40: 587909 | P40: 633165 | Q40: 452983 | R40: 487198 | S40: 622649 | T40: 583236 | U40: 483148 | V40: 483617 | W40: 5091778 | X40: 4874358 | Y40: 1907982 | Z40: 1812388 | AA40: 1212014 | AB40: 1091275 | AC40: 69932128 | AD40: 70915916 | AF40: =Q40/W40 -> 0.088963619 | AG40: =R40/X40 -> 0.099951214 | AH40: =U40/W40 -> 0.094887876 | AI40: =V40/X40 -> 0.099216553 | AJ40: =Y40/AA40 -> 1.5742244 | AK40: =Z40/AB40 -> 1.6607986 | AL40: =O40/K40 -> 0.097153234 | AM40: =P40/L40 -> 0.10369886 | AN40: =K40/W40 -> 1.1884568 | AO40: =L40/X40 -> 1.2526378 | AP40: =IF(OR(Q40<0, Q40="NA"), 0, 1) -> 1 | AQ40: =IF(OR(S40<0, S40="NA"), 0, 1) -> 1 | AR40: =IFERROR(IF((AF40-AG40)>0,1,0),0) -> 0 | AS40: =IFERROR(IF((S40-Q40)>0,1,0),0) -> 1 | AT40: =IFERROR(IF((AH40-AI40)<0,1,0),0) -> 1 | AU40: =IFERROR(IF((AJ40-AK40)>0,1,0),0) -> 0 | AV40: =IFERROR(IF((AL40-AM40)>0,1,0),0) -> 0 | AW40: =IFERROR(IF((AN40-AO40)>0,1,0),0) -> 0 | AX40: =IFERROR(IF((AC40-AD40)<0,1,0),0) -> 1 | AY40: =SUM(AP40:AX40) -> 5
A41: Acadia Healthcare Company, Inc. (NASDAQGS:ACHC) | B41: 4811530 | C41: NASDAQGS | D41: 45.41 | E41: 4217.9238 | F41: Health Care | G41: Health Care Equipment and Services | H41: Health Care Providers and Services | I41: Health Care Facilities | J41: 622 - Hospitals | K41: 3122525 | L41: 3057225 | M41: 689293 | N41: 672171 | O41: 543859 | P41: 530990 | Q41: 290712 | R41: 3819 | S41: 129296 | T41: 104025 | U41: 1804825 | V41: 1774556 | W41: 5870457 | X41: 5678052 | Y41: 652062 | Z41: 645214 | AA41: 609500 | AB41: 546522 | AC41: 91757352 | AD41: 91680774 | AF41: =Q41/W41 -> 0.049521187 | AG41: =R41/X41 -> 0.00067258982 | AH41: =U41/W41 -> 0.30744199 | AI41: =V41/X41 -> 0.31252902 | AJ41: =Y41/AA41 -> 1.069831 | AK41: =Z41/AB41 -> 1.1805819 | AL41: =O41/K41 -> 0.17417282 | AM41: =P41/L41 -> 0.17368365 | AN41: =K41/W41 -> 0.53190493 | AO41: =L41/X41 -> 0.5384285 | AP41: =IF(OR(Q41<0, Q41="NA"), 0, 1) -> 1 | AQ41: =IF(OR(S41<0, S41="NA"), 0, 1) -> 1 | AR41: =IFERROR(IF((AF41-AG41)>0,1,0),0) -> 1 | AS41: =IFERROR(IF((S41-Q41)>0,1,0),0) -> 0 | AT41: =IFERROR(IF((AH41-AI41)<0,1,0),0) -> 1 | AU41: =IFERROR(IF((AJ41-AK41)>0,1,0),0) -> 0 | AV41: =IFERROR(IF((AL41-AM41)>0,1,0),0) -> 1 | AW41: =IFERROR(IF((AN41-AO41)>0,1,0),0) -> 0 | AX41: =IFERROR(IF((AC41-AD41)<0,1,0),0) -> 0 | AY41: =SUM(AP41:AX41) -> 5
A42: ACADIA Pharmaceuticals Inc. (NASDAQGS:ACAD) | B42: 4811060 | C42: NASDAQGS | D42: 17.9 | E42: 2978.4148 | F42: Health Care | G42: Pharmaceuticals, Biotechnology and Life Sciences | H42: Biotechnology | I42: Biotechnology | J42: 325414 - Biological Product (except Diagnostic) Manufacturing | K42: 929236 | L42: 890534 | M42: 124541 | N42: 34274 | O42: 112235 | P42: 22815 | Q42: 128506 | R42: 30565 | S42: 202727 | T42: 80526 | U42: NA | V42: NA | W42: 976868 | X42: 914099 | Y42: 788284 | Z42: 728916 | AA42: 343945 | AB42: 337851 | AC42: 166351715 | AD42: 165853301 | AF42: =Q42/W42 -> 0.13154899 | AG42: =R42/X42 -> 0.033437297 | AH42: =U42/W42 -> #VALUE! | AI42: =V42/X42 -> #VALUE! | AJ42: =Y42/AA42 -> 2.2918897 | AK42: =Z42/AB42 -> 2.1575073 | AL42: =O42/K42 -> 0.12078202 | AM42: =P42/L42 -> 0.02561946 | AN42: =K42/W42 -> 0.95124009 | AO42: =L42/X42 -> 0.97422052 | AP42: =IF(OR(Q42<0, Q42="NA"), 0, 1) -> 1 | AQ42: =IF(OR(S42<0, S42="NA"), 0, 1) -> 1 | AR42: =IFERROR(IF((AF42-AG42)>0,1,0),0) -> 1 | AS42: =IFERROR(IF((S42-Q42)>0,1,0),0) -> 1 | AT42: =IFERROR(IF((AH42-AI42)<0,1,0),0) -> 0 | AU42: =IFERROR(IF((AJ42-AK42)>0,1,0),0) -> 1 | AV42: =IFERROR(IF((AL42-AM42)>0,1,0),0) -> 1 | AW42: =IFERROR(IF((AN42-AO42)>0,1,0),0) -> 0 | AX42: =IFERROR(IF((AC42-AD42)<0,1,0),0) -> 0 | AY42: =SUM(AP42:AX42) -> 6
A43: Acadia Realty Trust (NYSE:AKR) | B43: 103085 | C43: NYSE | D43: 22.45 | E43: 2686.2526 | F43: Real Estate | G43: Equity Real Estate Investment Trusts (REITs) | H43: Retail REITs | I43: Retail REITs | J43: 531110 - Lessors of Residential Buildings and Dwellings | K43: 373594 | L43: 358417 | M43: 231093 | N43: 203264 | O43: 92343 | P43: 65288 | Q43: -3256 | R43: -31778 | S43: 143167 | T43: 124282 | U43: 1452974 | V43: 1699588 | W43: 4276323 | X43: 4251038 | Y43: NA | Z43: NA | AA43: NA | AB43: NA | AC43: 113902348 | AD43: 105266580 | AF43: =Q43/W43 -> -0.00076140179 | AG43: =R43/X43 -> -0.0074753507 | AH43: =U43/W43 -> 0.33977181 | AI43: =V43/X43 -> 0.39980541 | AJ43: =Y43/AA43 -> #VALUE! | AK43: =Z43/AB43 -> #VALUE! | AL43: =O43/K43 -> 0.24717474 | AM43: =P43/L43 -> 0.18215654 | AN43: =K43/W43 -> 0.087363373 | AO43: =L43/X43 -> 0.08431282 | AP43: =IF(OR(Q43<0, Q43="NA"), 0, 1) -> 0 | AQ43: =IF(OR(S43<0, S43="NA"), 0, 1) -> 1 | AR43: =IFERROR(IF((AF43-AG43)>0,1,0),0) -> 1 | AS43: =IFERROR(IF((S43-Q43)>0,1,0),0) -> 1 | AT43: =IFERROR(IF((AH43-AI43)<0,1,0),0) -> 1 | AU43: =IFERROR(IF((AJ43-AK43)>0,1,0),0) -> 0 | AV43: =IFERROR(IF((AL43-AM43)>0,1,0),0) -> 1 | AW43: =IFERROR(IF((AN43-AO43)>0,1,0),0) -> 1 | AX43: =IFERROR(IF((AC43-AD43)<0,1,0),0) -> 0 | AY43: =SUM(AP43:AX43) -> 6
A44: Accel Entertainment, Inc. (NYSE:ACEL) | B44: 7689847 | C44: NYSE | D44: 10.36 | E44: 853.07821 | F44: Consumer Discretionary | G44: Consumer Services | H44: Hotels, Restaurants and Leisure | I44: Casinos and Gaming | J44: 7132 - Gambling Industries | K44: 1210525 | L44: 1195795 | M44: 162997 | N44: 167664 | O44: 100682 | P44: 107227 | Q44: 42885 | R44: 48440 | S44: 148188 | T44: 126299 | U44: 525572 | V44: 537252 | W44: 950206 | X44: 950348 | Y44: 323323 | Z44: 322201 | AA44: 119372 | AB44: 105755 | AC44: 82430205 | AD44: 82958153 | AF44: =Q44/W44 -> 0.045132319 | AG44: =R44/X44 -> 0.050970802 | AH44: =U44/W44 -> 0.55311375 | AI44: =V44/X44 -> 0.56532133 | AJ44: =Y44/AA44 -> 2.708533 | AK44: =Z44/AB44 -> 3.0466739 | AL44: =O44/K44 -> 0.083172177 | AM44: =P44/L44 -> 0.089670052 | AN44: =K44/W44 -> 1.2739606 | AO44: =L44/X44 -> 1.2582707 | AP44: =IF(OR(Q44<0, Q44="NA"), 0, 1) -> 1 | AQ44: =IF(OR(S44<0, S44="NA"), 0, 1) -> 1 | AR44: =IFERROR(IF((AF44-AG44)>0,1,0),0) -> 0 | AS44: =IFERROR(IF((S44-Q44)>0,1,0),0) -> 1 | AT44: =IFERROR(IF((AH44-AI44)<0,1,0),0) -> 1 | AU44: =IFERROR(IF((AJ44-AK44)>0,1,0),0) -> 0 | AV44: =IFERROR(IF((AL44-AM44)>0,1,0),0) -> 0 | AW44: =IFERROR(IF((AN44-AO44)>0,1,0),0) -> 1 | AX44: =IFERROR(IF((AC44-AD44)<0,1,0),0) -> 1 | AY44: =SUM(AP44:AX44) -> 6
A45: Accenture plc (NYSE:ACN) | B45: 4142760 | C45: NYSE | D45: 349.14 | E45: 218380.07 | F45: Information Technology | G45: Software and Services | H45: IT Services | I45: IT Consulting and Other Services | J45: 541511 - Custom Computer Programming Services | K45: 66361706 | L45: 64896464 | M45: 11358275 | N45: 11065912 | O45: 10213279 | P45: 9969353 | Q45: 7725406 | R45: 7419197 | S45: 9654962 | T45: 9131027 | U45: 5039460 | V45: 78628 | W45: 59868070 | X45: 55932363 | Y45: 25198337 | Z45: 20857781 | AA45: 17186968 | AB45: 18976127 | AC45: 625030128 | AD45: 625280287 | AF45: =Q45/W45 -> 0.12904051 | AG45: =R45/X45 -> 0.13264587 | AH45: =U45/W45 -> 0.084176089 | AI45: =V45/X45 -> 0.0014057693 | AJ45: =Y45/AA45 -> 1.4661304 | AK45: =Z45/AB45 -> 1.099159 | AL45: =O45/K45 -> 0.1539032 | AM45: =P45/L45 -> 0.15361936 | AN45: =K45/W45 -> 1.1084658 | AO45: =L45/X45 -> 1.1602668 | AP45: =IF(OR(Q45<0, Q45="NA"), 0, 1) -> 1 | AQ45: =IF(OR(S45<0, S45="NA"), 0, 1) -> 1 | AR45: =IFERROR(IF((AF45-AG45)>0,1,0),0) -> 0 | AS45: =IFERROR(IF((S45-Q45)>0,1,0),0) -> 1 | AT45: =IFERROR(IF((AH45-AI45)<0,1,0),0) -> 0 | AU45: =IFERROR(IF((AJ45-AK45)>0,1,0),0) -> 1 | AV45: =IFERROR(IF((AL45-AM45)>0,1,0),0) -> 1 | AW45: =IFERROR(IF((AN45-AO45)>0,1,0),0) -> 0 | AX45: =IFERROR(IF((AC45-AD45)<0,1,0),0) -> 1 | AY45: =SUM(AP45:AX45) -> 6
A46: ACCO Brands Corporation (NYSE:ACCO) | B46: 4828634 | C46: NYSE | D46: 4.99 | E46: 463.47623 | F46: Industrials | G46: Commercial and Professional Services | H46: Commercial Services and Supplies | I46: Office Services and Supplies | J46: 322230 - Stationery Product Manufacturing | K46: 1706700 | L46: 1733800 | M46: 201500 | N46: 203800 | O46: 143000 | P46: 145400 | Q46: -181600 | R46: -176000 | S46: 153500 | T46: 170600 | U46: 849800 | V46: 917500 | W46: 2357500 | X46: 2413400 | Y46: 794000 | Z46: 858400 | AA46: 497700 | AB46: 484300 | AC46: 93400000 | AD46: 95800000 | AF46: =Q46/W46 -> -0.077030753 | AG46: =R46/X46 -> -0.072926162 | AH46: =U46/W46 -> 0.3604666 | AI46: =V46/X46 -> 0.38016906 | AJ46: =Y46/AA46 -> 1.5953386 | AK46: =Z46/AB46 -> 1.7724551 | AL46: =O46/K46 -> 0.083787426 | AM46: =P46/L46 -> 0.083862037 | AN46: =K46/W46 -> 0.72394486 | AO46: =L46/X46 -> 0.71840557 | AP46: =IF(OR(Q46<0, Q46="NA"), 0, 1) -> 0 | AQ46: =IF(OR(S46<0, S46="NA"), 0, 1) -> 1 | AR46: =IFERROR(IF((AF46-AG46)>0,1,0),0) -> 0 | AS46: =IFERROR(IF((S46-Q46)>0,1,0),0) -> 1 | AT46: =IFERROR(IF((AH46-AI46)<0,1,0),0) -> 1 | AU46: =IFERROR(IF((AJ46-AK46)>0,1,0),0) -> 0 | AV46: =IFERROR(IF((AL46-AM46)>0,1,0),0) -> 0 | AW46: =IFERROR(IF((AN46-AO46)>0,1,0),0) -> 1 | AX46: =IFERROR(IF((AC46-AD46)<0,1,0),0) -> 1 | AY46: =SUM(AP46:AX46) -> 5
A47: ACI Worldwide, Inc. (NASDAQGS:ACIW) | B47: 4097321 | C47: NASDAQGS | D47: 51.62 | E47: 5414.3517 | F47: Information Technology | G47: Software and Services | H47: Software | I47: Application Software | J47: 513210 - Software Publishers | K47: 1617813 | L47: 1529076 | M47: 421408 | N47: 362494 | O47: 373563 | P47: 311001 | Q47: 227179 | R47: 183663 | S47: 318009 | T47: 289267 | U47: 959387 | V47: 973121 | W47: 3092985 | X47: 3364672 | Y47: 1085600 | Z47: 1381210 | AA47: 697294 | AB47: 1044121 | AC47: 104870815 | AD47: 104860637 | AF47: =Q47/W47 -> 0.073449758 | AG47: =R47/X47 -> 0.054585707 | AH47: =U47/W47 -> 0.31018159 | AI47: =V47/X47 -> 0.2892172 | AJ47: =Y47/AA47 -> 1.5568756 | AK47: =Z47/AB47 -> 1.3228448 | AL47: =O47/K47 -> 0.23090617 | AM47: =P47/L47 -> 0.20339146 | AN47: =K47/W47 -> 0.52305879 | AO47: =L47/X47 -> 0.45445024 | AP47: =IF(OR(Q47<0, Q47="NA"), 0, 1) -> 1 | AQ47: =IF(OR(S47<0, S47="NA"), 0, 1) -> 1 | AR47: =IFERROR(IF((AF47-AG47)>0,1,0),0) -> 1 | AS47: =IFERROR(IF((S47-Q47)>0,1,0),0) -> 1 | AT47: =IFERROR(IF((AH47-AI47)<0,1,0),0) -> 0 | AU47: =IFERROR(IF((AJ47-AK47)>0,1,0),0) -> 1 | AV47: =IFERROR(IF((AL47-AM47)>0,1,0),0) -> 1 | AW47: =IFERROR(IF((AN47-AO47)>0,1,0),0) -> 1 | AX47: =IFERROR(IF((AC47-AD47)<0,1,0),0) -> 0 | AY47: =SUM(AP47:AX47) -> 7
A48: ACM Research, Inc. (NASDAQGM:ACMR) | B48: 5328081 | C48: NASDAQGM | D48: 15.49 | E48: 970.10535 | F48: Information Technology | G48: Semiconductors and Semiconductor Equipment | H48: Semiconductors and Semiconductor Equipment | I48: Semiconductor Materials and Equipment | J48: 333242 - Semiconductor Machinery Manufacturing | K48: 728968 | L48: 693561 | M48: 139670 | N48: 128190 | O48: 130383 | P48: 119372 | Q48: 115461 | R48: 107783 | S48: 25502 | T48: -4236 | U48: 106069 | V48: 70833 | W48: 1794175 | X48: 1667575 | Y48: 1445314 | Z48: 1343162 | AA48: 610035 | AB48: 586170 | AC48: 62546330 | AD48: 62424064 | AF48: =Q48/W48 -> 0.064353254 | AG48: =R48/X48 -> 0.064634574 | AH48: =U48/W48 -> 0.059118536 | AI48: =V48/X48 -> 0.04247665 | AJ48: =Y48/AA48 -> 2.3692313 | AK48: =Z48/AB48 -> 2.2914206 | AL48: =O48/K48 -> 0.1788597 | AM48: =P48/L48 -> 0.17211464 | AN48: =K48/W48 -> 0.40629704 | AO48: =L48/X48 -> 0.41590993 | AP48: =IF(OR(Q48<0, Q48="NA"), 0, 1) -> 1 | AQ48: =IF(OR(S48<0, S48="NA"), 0, 1) -> 1 | AR48: =IFERROR(IF((AF48-AG48)>0,1,0),0) -> 0 | AS48: =IFERROR(IF((S48-Q48)>0,1,0),0) -> 0 | AT48: =IFERROR(IF((AH48-AI48)<0,1,0),0) -> 0 | AU48: =IFERROR(IF((AJ48-AK48)>0,1,0),0) -> 1 | AV48: =IFERROR(IF((AL48-AM48)>0,1,0),0) -> 1 | AW48: =IFERROR(IF((AN48-AO48)>0,1,0),0) -> 0 | AX48: =IFERROR(IF((AC48-AD48)<0,1,0),0) -> 0 | AY48: =SUM(AP48:AX48) -> 4
A49: ACNB Corporation (NASDAQCM:ACNB) | B49: 100603 | C49: NASDAQCM | D49: 37.18 | E49: 317.83788 | F49: Financials | G49: Banks | H49: Banks | I49: Regional Banks | J49: 522110 - Commercial Banking | K49: 108389 | L49: 108642 | M49: NA | N49: NA | O49: 58307 | P49: 56714 | Q49: 29348 | R49: 31188 | S49: 42687 | T49: 36653 | U49: 15000 | V49: 15000 | W49: 2420914 | X49: 2457753 | Y49: NA | Z49: NA | AA49: NA | AB49: NA | AC49: 8548625 | AD49: 8545629 | AF49: =Q49/W49 -> 0.012122694 | AG49: =R49/X49 -> 0.01268964 | AH49: =U49/W49 -> 0.006196007 | AI49: =V49/X49 -> 0.0061031357 | AJ49: =Y49/AA49 -> #VALUE! | AK49: =Z49/AB49 -> #VALUE! | AL49: =O49/K49 -> 0.53794204 | AM49: =P49/L49 -> 0.52202647 | AN49: =K49/W49 -> 0.044771933 | AO49: =L49/X49 -> 0.044203791 | AP49: =IF(OR(Q49<0, Q49="NA"), 0, 1) -> 1 | AQ49: =IF(OR(S49<0, S49="NA"), 0, 1) -> 1 | AR49: =IFERROR(IF((AF49-AG49)>0,1,0),0) -> 0 | AS49: =IFERROR(IF((S49-Q49)>0,1,0),0) -> 1 | AT49: =IFERROR(IF((AH49-AI49)<0,1,0),0) -> 0 | AU49: =IFERROR(IF((AJ49-AK49)>0,1,0),0) -> 0 | AV49: =IFERROR(IF((AL49-AM49)>0,1,0),0) -> 1 | AW49: =IFERROR(IF((AN49-AO49)>0,1,0),0) -> 1 | AX49: =IFERROR(IF((AC49-AD49)<0,1,0),0) -> 0 | AY49: =SUM(AP49:AX49) -> 5
A50: ACRES Commercial Realty Corp. (NYSE:ACR) | B50: 4103630 | C50: NYSE | D50: 17.24 | E50: 123.47924 | F50: Financials | G50: Financial Services | H50: Mortgage Real Estate Investment Trusts (REITs) | I50: Mortgage REITs | J50: 525990 - Other Financial Vehicles | K50: 94827 | L50: 93674 | M50: NA | N50: NA | O50: 149732 | P50: 153876 | Q50: 25805 | R50: 25318 | S50: 28013 | T50: 31352 | U50: 1437681 | V50: 1530483 | W50: 2010336 | X50: 2095242 | Y50: NA | Z50: NA | AA50: NA | AB50: NA | AC50: 7789217 | AD50: 7903175 | AF50: =Q50/W50 -> 0.012836163 | AG50: =R50/X50 -> 0.012083568 | AH50: =U50/W50 -> 0.71514463 | AI50: =V50/X50 -> 0.73045643 | AJ50: =Y50/AA50 -> #VALUE! | AK50: =Z50/AB50 -> #VALUE! | AL50: =O50/K50 -> 1.5790018 | AM50: =P50/L50 -> 1.6426757 | AN50: =K50/W50 -> 0.047169727 | AO50: =L50/X50 -> 0.044707962 | AP50: =IF(OR(Q50<0, Q50="NA"), 0, 1) -> 1 | AQ50: =IF(OR(S50<0, S50="NA"), 0, 1) -> 1 | AR50: =IFERROR(IF((AF50-AG50)>0,1,0),0) -> 1 | AS50: =IFERROR(IF((S50-Q50)>0,1,0),0) -> 1 | AT50: =IFERROR(IF((AH50-AI50)<0,1,0),0) -> 1 | AU50: =IFERROR(IF((AJ50-AK50)>0,1,0),0) -> 0 | AV50: =IFERROR(IF((AL50-AM50)>0,1,0),0) -> 0 | AW50: =IFERROR(IF((AN50-AO50)>0,1,0),0) -> 1 | AX50: =IFERROR(IF((AC50-AD50)<0,1,0),0) -> 1 | AY50: =SUM(AP50:AX50) -> 7
A51: Acrivon Therapeutics, Inc. (NASDAQGM:ACRV) | B51: 19814853 | C51: NASDAQGM | D51: 5.51 | E51: 171.56099 | F51: Health Care | G51: Pharmaceuticals, Biotechnology and Life Sciences | H51: Biotechnology | I51: Biotechnology | J51: 325412 - Pharmaceutical Preparation Manufacturing | K51: NA | L51: NA | M51: -84446 | N51: -75561 | O51: -85298 | P51: -76295 | Q51: -76977 | R51: -69002 | S51: -60675 | T51: -53158 | U51: NA | V51: NA | W51: 214684 | X51: 230585 | Y51: 188984 | Z51: 182358 | AA51: 14819 | AB51: 11284 | AC51: 31130892 | AD51: 30966255 | AF51: =Q51/W51 -> -0.35855956 | AG51: =R51/X51 -> -0.29924757 | AH51: =U51/W51 -> #VALUE! | AI51: =V51/X51 -> #VALUE! | AJ51: =Y51/AA51 -> 12.752817 | AK51: =Z51/AB51 -> 16.160759 | AL51: =O51/K51 -> #VALUE! | AM51: =P51/L51 -> #VALUE! | AN51: =K51/W51 -> #VALUE! | AO51: =L51/X51 -> #VALUE! | AP51: =IF(OR(Q51<0, Q51="NA"), 0, 1) -> 0 | AQ51: =IF(OR(S51<0, S51="NA"), 0, 1) -> 0 | AR51: =IFERROR(IF((AF51-AG51)>0,1,0),0) -> 0 | AS51: =IFERROR(IF((S51-Q51)>0,1,0),0) -> 1 | AT51: =IFERROR(IF((AH51-AI51)<0,1,0),0) -> 0 | AU51: =IFERROR(IF((AJ51-AK51)>0,1,0),0) -> 0 | AV51: =IFERROR(IF((AL51-AM51)>0,1,0),0) -> 0 | AW51: =IFERROR(IF((AN51-AO51)>0,1,0),0) -> 0 | AX51: =IFERROR(IF((AC51-AD51)<0,1,0),0) -> 0 | AY51: =SUM(AP51:AX51) -> 1
A52: Actuate Therapeutics, Inc. (NASDAQGM:ACTU) | B52: 5306830 | C52: NASDAQGM | D52: 8.08 | E52: 157.81562 | F52: Health Care | G52: Pharmaceuticals, Biotechnology and Life Sciences | H52: Biotechnology | I52: Biotechnology | J52: 325414 - Biological Product (except Diagnostic) Manufacturing | K52: NA | L52: NA | M52: NA | N52: NA | O52: -26216.787 | P52: -27299.557 | Q52: -28451.393 | R52: -28818.357 | S52: -22582.077 | T52: -19071.315 | U52: NA | V52: NA | W52: 14262.781 | X52: 1730.826 | Y52: 14262.781 | Z52: 549.687 | AA52: 8497 | AB52: 20073 | AC52: 19531636 | AD52: 1690760 | AF52: =Q52/W52 -> -1.9947998 | AG52: =R52/X52 -> -16.65006 | AH52: =U52/W52 -> #VALUE! | AI52: =V52/X52 -> #VALUE! | AJ52: =Y52/AA52 -> 1.6785667 | AK52: =Z52/AB52 -> 0.027384397 | AL52: =O52/K52 -> #VALUE! | AM52: =P52/L52 -> #VALUE! | AN52: =K52/W52 -> #VALUE! | AO52: =L52/X52 -> #VALUE! | AP52: =IF(OR(Q52<0, Q52="NA"), 0, 1) -> 0 | AQ52: =IF(OR(S52<0, S52="NA"), 0, 1) -> 0 | AR52: =IFERROR(IF((AF52-AG52)>0,1,0),0) -> 1 | AS52: =IFERROR(IF((S52-Q52)>0,1,0),0) -> 1 | AT52: =IFERROR(IF((AH52-AI52)<0,1,0),0) -> 0 | AU52: =IFERROR(IF((AJ52-AK52)>0,1,0),0) -> 1 | AV52: =IFERROR(IF((AL52-AM52)>0,1,0),0) -> 0 | AW52: =IFERROR(IF((AN52-AO52)>0,1,0),0) -> 0 | AX52: =IFERROR(IF((AC52-AD52)<0,1,0),0) -> 0 | AY52: =SUM(AP52:AX52) -> 3
A53: Acuity Brands, Inc. (NYSE:AYI) | B53: 4991217 | C53: NYSE | D53: 306.36 | E53: 9392.7825 | F53: Industrials | G53: Capital Goods | H53: Electrical Equipment | I53: Electrical Components and Equipment | J53: 33513 - Electric Lighting Equipment Manufacturing | K53: 3857900 | L53: 3841000 | M53: 646900 | N53: 642900 | O53: 556900 | P53: 551800 | Q53: 428700 | R53: 422600 | S53: 561400 | T53: 619200 | U53: 496300 | V53: 496200 | W53: 3864300 | X53: 3814600 | Y53: 1937300 | Z53: 1871500 | AA53: 650600 | AB53: 687900 | AC53: 30700000 | AD53: 30500000 | AF53: =Q53/W53 -> 0.11093859 | AG53: =R53/X53 -> 0.11078488 | AH53: =U53/W53 -> 0.12843206 | AI53: =V53/X53 -> 0.13007917 | AJ53: =Y53/AA53 -> 2.9777129 | AK53: =Z53/AB53 -> 2.7205989 | AL53: =O53/K53 -> 0.14435315 | AM53: =P53/L53 -> 0.14366051 | AN53: =K53/W53 -> 0.99834381 | AO53: =L53/X53 -> 1.0069208 | AP53: =IF(OR(Q53<0, Q53="NA"), 0, 1) -> 1 | AQ53: =IF(OR(S53<0, S53="NA"), 0, 1) -> 1 | AR53: =IFERROR(IF((AF53-AG53)>0,1,0),0) -> 1 | AS53: =IFERROR(IF((S53-Q53)>0,1,0),0) -> 1 | AT53: =IFERROR(IF((AH53-AI53)<0,1,0),0) -> 1 | AU53: =IFERROR(IF((AJ53-AK53)>0,1,0),0) -> 1 | AV53: =IFERROR(IF((AL53-AM53)>0,1,0),0) -> 1 | AW53: =IFERROR(IF((AN53-AO53)>0,1,0),0) -> 0 | AX53: =IFERROR(IF((AC53-AD53)<0,1,0),0) -> 0 | AY53: =SUM(AP53:AX53) -> 7
A54: Acushnet Holdings Corp. (NYSE:GOLF) | B54: 4912136 | C54: NYSE | D54: 71.72 | E54: 4360.7875 | F54: Consumer Discretionary | G54: Consumer Durables and Apparel | H54: Leisure Products | I54: Leisure Products | J54: 339920 - Sporting and Athletic Goods Manufacturing | K54: 2424883 | L54: 2397763 | M54: 333804 | N54: 329182 | O54: 288513 | P54: 285049 | Q54: 183576 | R54: 185347 | S54: 321125 | T54: 354327 | U54: 708043 | V54: 728129 | W54: 2280748 | X54: 2274158 | Y54: 1085449 | Z54: 1093524 | AA54: 515712 | AB54: 479187 | AC54: 61162949 | AD54: 62141383 | AF54: =Q54/W54 -> 0.080489383 | AG54: =R54/X54 -> 0.081501373 | AH54: =U54/W54 -> 0.31044333 | AI54: =V54/X54 -> 0.3201752 | AJ54: =Y54/AA54 -> 2.1047581 | AK54: =Z54/AB54 -> 2.2820402 | AL54: =O54/K54 -> 0.11898017 | AM54: =P54/L54 -> 0.11888122 | AN54: =K54/W54 -> 1.0631964 | AO54: =L54/X54 -> 1.054352 | AP54: =IF(OR(Q54<0, Q54="NA"), 0, 1) -> 1 | AQ54: =IF(OR(S54<0, S54="NA"), 0, 1) -> 1 | AR54: =IFERROR(IF((AF54-AG54)>0,1,0),0) -> 0 | AS54: =IFERROR(IF((S54-Q54)>0,1,0),0) -> 1 | AT54: =IFERROR(IF((AH54-AI54)<0,1,0),0) -> 1 | AU54: =IFERROR(IF((AJ54-AK54)>0,1,0),0) -> 0 | AV54: =IFERROR(IF((AL54-AM54)>0,1,0),0) -> 1 | AW54: =IFERROR(IF((AN54-AO54)>0,1,0),0) -> 1 | AX54: =IFERROR(IF((AC54-AD54)<0,1,0),0) -> 1 | AY54: =SUM(AP54:AX54) -> 7
A55: ACV Auctions Inc. (NASDAQGS:ACVA) | B55: 5294845 | C55: NASDAQGS | D55: 20.78 | E55: 3483.5584 | F55: Industrials | G55: Commercial and Professional Services | H55: Commercial Services and Supplies | I55: Diversified Support Services | J55: 561499 - All Other Business Support Services | K55: 596019 | L55: 543704 | M55: -56145 | N55: -66101 | O55: -79374 | P55: -84648 | Q55: -76804 | R55: -79013 | S55: 42120 | T55: 6250 | U55: 115000 | V55: 110000 | W55: 1034353 | X55: 1010847 | Y55: 639232 | Z55: 614084 | AA55: 422242 | AB55: 412143 | AC55: 167046067 | AD55: 166029699 | AF55: =Q55/W55 -> -0.07425318 | AG55: =R55/X55 -> -0.078165143 | AH55: =U55/W55 -> 0.11118061 | AI55: =V55/X55 -> 0.10881963 | AJ55: =Y55/AA55 -> 1.5138996 | AK55: =Z55/AB55 -> 1.489978 | AL55: =O55/K55 -> -0.13317361 | AM55: =P55/L55 -> -0.15568765 | AN55: =K55/W55 -> 0.57622398 | AO55: =L55/X55 -> 0.53786973 | AP55: =IF(OR(Q55<0, Q55="NA"), 0, 1) -> 0 | AQ55: =IF(OR(S55<0, S55="NA"), 0, 1) -> 1 | AR55: =IFERROR(IF((AF55-AG55)>0,1,0),0) -> 1 | AS55: =IFERROR(IF((S55-Q55)>0,1,0),0) -> 1 | AT55: =IFERROR(IF((AH55-AI55)<0,1,0),0) -> 0 | AU55: =IFERROR(IF((AJ55-AK55)>0,1,0),0) -> 1 | AV55: =IFERROR(IF((AL55-AM55)>0,1,0),0) -> 1 | AW55: =IFERROR(IF((AN55-AO55)>0,1,0),0) -> 1 | AX55: =IFERROR(IF((AC55-AD55)<0,1,0),0) -> 0 | AY55: =SUM(AP55:AX55) -> 6
A56: Adams Diversified Equity Fund, Inc. (NYSE:ADX) | B56: 4047880 | C56: NYSE | D56: 20.39 | E56: 2276.4734 | F56: Financials | G56: Financial Services | H56: Capital Markets | I56: Asset Management and Custody Banks | J56: 525910 - Open-End Investment Funds | K56: 34758.821 | L56: 34949.589 | M56: NA | N56: NA | O56: 19512.632 | P56: 20264.469 | Q56: 625495.99 | R56: 589208.86 | S56: NA | T56: NA | U56: NA | V56: NA | W56: 2945556.6 | X56: 2945556.6 | Y56: 5510.562 | Z56: 5510.562 | AA56: 7212 | AB56: 7212 | AC56: 124027617 | AD56: 124027617 | AF56: =Q56/W56 -> 0.21235239 | AG56: =R56/X56 -> 0.20003312 | AH56: =U56/W56 -> #VALUE! | AI56: =V56/X56 -> #VALUE! | AJ56: =Y56/AA56 -> 0.76408236 | AK56: =Z56/AB56 -> 0.76408236 | AL56: =O56/K56 -> 0.56137209 | AM56: =P56/L56 -> 0.57981995 | AN56: =K56/W56 -> 0.011800426 | AO56: =L56/X56 -> 0.01186519 | AP56: =IF(OR(Q56<0, Q56="NA"), 0, 1) -> 1 | AQ56: =IF(OR(S56<0, S56="NA"), 0, 1) -> 0 | AR56: =IFERROR(IF((AF56-AG56)>0,1,0),0) -> 1 | AS56: =IFERROR(IF((S56-Q56)>0,1,0),0) -> 0 | AT56: =IFERROR(IF((AH56-AI56)<0,1,0),0) -> 0 | AU56: =IFERROR(IF((AJ56-AK56)>0,1,0),0) -> 0 | AV56: =IFERROR(IF((AL56-AM56)>0,1,0),0) -> 0 | AW56: =IFERROR(IF((AN56-AO56)>0,1,0),0) -> 0 | AX56: =IFERROR(IF((AC56-AD56)<0,1,0),0) -> 0 | AY56: =SUM(AP56:AX56) -> 2
A57: Adams Natural Resources Fund, Inc. (NYSE:PEO) | B57: 4783704 | C57: NYSE | D57: 23.09 | E57: 587.72457 | F57: Financials | G57: Financial Services | H57: Capital Markets | I57: Asset Management and Custody Banks | J57: 525990 - Other Financial Vehicles | K57: 20665.906 | L57: 20938.51 | M57: NA | N57: NA | O57: 16580.77 | P57: 16836.301 | Q57: 94740.384 | R57: 52217.131 | S57: NA | T57: NA | U57: NA | V57: NA | W57: 692272.57 | X57: 692272.57 | Y57: 2417.211 | Z57: 2417.211 | AA57: 1778 | AB57: 1778 | AC57: 25453641 | AD57: 25453641 | AF57: =Q57/W57 -> 0.13685417 | AG57: =R57/X57 -> 0.075428572 | AH57: =U57/W57 -> #VALUE! | AI57: =V57/X57 -> #VALUE! | AJ57: =Y57/AA57 -> 1.3595112 | AK57: =Z57/AB57 -> 1.3595112 | AL57: =O57/K57 -> 0.80232485 | AM57: =P57/L57 -> 0.80408305 | AN57: =K57/W57 -> 0.029852268 | AO57: =L57/X57 -> 0.030246049 | AP57: =IF(OR(Q57<0, Q57="NA"), 0, 1) -> 1 | AQ57: =IF(OR(S57<0, S57="NA"), 0, 1) -> 0 | AR57: =IFERROR(IF((AF57-AG57)>0,1,0),0) -> 1 | AS57: =IFERROR(IF((S57-Q57)>0,1,0),0) -> 0 | AT57: =IFERROR(IF((AH57-AI57)<0,1,0),0) -> 0 | AU57: =IFERROR(IF((AJ57-AK57)>0,1,0),0) -> 0 | AV57: =IFERROR(IF((AL57-AM57)>0,1,0),0) -> 0 | AW57: =IFERROR(IF((AN57-AO57)>0,1,0),0) -> 0 | AX57: =IFERROR(IF((AC57-AD57)<0,1,0),0) -> 0 | AY57: =SUM(AP57:AX57) -> 2
A58: AdaptHealth Corp. (NASDAQCM:AHCO) | B58: 15907646 | C58: NASDAQCM | D58: 10.33 | E58: 1359.6331 | F58: Health Care | G58: Health Care Equipment and Services | H58: Health Care Providers and Services | I58: Health Care Distributors | J58: 423450 - Medical, Dental, and Hospital Equipment and Supplies Merchant Wholesalers | K58: 3262564 | L58: 3260737 | M58: 669381 | N58: 662075 | O58: 302220 | P58: 288363 | Q58: -210198 | R58: -687074 | S58: 546690 | T58: 501118 | U58: 2013644 | V58: 2040451 | W58: 4469936 | X58: 4510912 | Y58: 683791 | Z58: 686428 | AA58: 553025 | AB58: 596024 | AC58: 131603695 | AD58: 129441488 | AF58: =Q58/W58 -> -0.047024834 | AG58: =R58/X58 -> -0.15231377 | AH58: =U58/W58 -> 0.45048609 | AI58: =V58/X58 -> 0.45233669 | AJ58: =Y58/AA58 -> 1.2364559 | AK58: =Z58/AB58 -> 1.1516785 | AL58: =O58/K58 -> 0.092632666 | AM58: =P58/L58 -> 0.088434915 | AN58: =K58/W58 -> 0.72989054 | AO58: =L58/X58 -> 0.72285538 | AP58: =IF(OR(Q58<0, Q58="NA"), 0, 1) -> 0 | AQ58: =IF(OR(S58<0, S58="NA"), 0, 1) -> 1 | AR58: =IFERROR(IF((AF58-AG58)>0,1,0),0) -> 1 | AS58: =IFERROR(IF((S58-Q58)>0,1,0),0) -> 1 | AT58: =IFERROR(IF((AH58-AI58)<0,1,0),0) -> 1 | AU58: =IFERROR(IF((AJ58-AK58)>0,1,0),0) -> 1 | AV58: =IFERROR(IF((AL58-AM58)>0,1,0),0) -> 1 | AW58: =IFERROR(IF((AN58-AO58)>0,1,0),0) -> 1 | AX58: =IFERROR(IF((AC58-AD58)<0,1,0),0) -> 0 | AY58: =SUM(AP58:AX58) -> 7
A59: Adaptive Biotechnologies Corporation (NASDAQGS:ADPT) | B59: 4578703 | C59: NASDAQGS | D59: 6.46 | E59: 953.36348 | F59: Health Care | G59: Pharmaceuticals, Biotechnology and Life Sciences | H59: Life Sciences Tools and Services | I59: Life Sciences Tools and Services | J59: 541715 - Research and Development in the Physical, Engineering, and Life Sciences (except Nanotechnology and Biotechnology) | K59: 177282 | L59: 168766 | M59: -146946 | N59: -164098 | O59: -167146 | P59: -185470 | Q59: -195345 | R59: -213574 | S59: -109653 | T59: -129272 | U59: 132700 | V59: 132082 | W59: 558506 | X59: 584872 | Y59: 308345 | Z59: 351552 | AA59: 87627 | AB59: 88126 | AC59: 147561586 | AD59: 147462201 | AF59: =Q59/W59 -> -0.34976348 | AG59: =R59/X59 -> -0.36516366 | AH59: =U59/W59 -> 0.23759816 | AI59: =V59/X59 -> 0.22583061 | AJ59: =Y59/AA59 -> 3.5188355 | AK59: =Z59/AB59 -> 3.9891973 | AL59: =O59/K59 -> -0.94282555 | AM59: =P59/L59 -> -1.0989773 | AN59: =K59/W59 -> 0.31742184 | AO59: =L59/X59 -> 0.28855203 | AP59: =IF(OR(Q59<0, Q59="NA"), 0, 1) -> 0 | AQ59: =IF(OR(S59<0, S59="NA"), 0, 1) -> 0 | AR59: =IFERROR(IF((AF59-AG59)>0,1,0),0) -> 1 | AS59: =IFERROR(IF((S59-Q59)>0,1,0),0) -> 1 | AT59: =IFERROR(IF((AH59-AI59)<0,1,0),0) -> 0 | AU59: =IFERROR(IF((AJ59-AK59)>0,1,0),0) -> 0 | AV59: =IFERROR(IF((AL59-AM59)>0,1,0),0) -> 1 | AW59: =IFERROR(IF((AN59-AO59)>0,1,0),0) -> 1 | AX59: =IFERROR(IF((AC59-AD59)<0,1,0),0) -> 0 | AY59: =SUM(AP59:AX59) -> 4
A60: Addus HomeCare Corporation (NASDAQGS:ADUS) | B60: 4810366 | C60: NASDAQGS | D60: 126.34 | E60: 2265.5434 | F60: Health Care | G60: Health Care Equipment and Services | H60: Health Care Providers and Services | I60: Health Care Services | J60: 621610 - Home Health Care Services | K60: 1133806 | L60: 1114740 | M60: 123755 | N60: 120815 | O60: 109762 | P60: 106648 | Q60: 73650 | R60: 68898 | S60: 136065 | T60: 109325 | U60: NA | V60: NA | W60: 1152901 | X60: 1116554 | Y60: 332814 | Z60: 294988 | AA60: 157818 | AB60: 147532 | AC60: 17932000 | AD60: 17899000 | AF60: =Q60/W60 -> 0.063882328 | AG60: =R60/X60 -> 0.061705927 | AH60: =U60/W60 -> #VALUE! | AI60: =V60/X60 -> #VALUE! | AJ60: =Y60/AA60 -> 2.1088469 | AK60: =Z60/AB60 -> 1.9994849 | AL60: =O60/K60 -> 0.096808449 | AM60: =P60/L60 -> 0.095670739 | AN60: =K60/W60 -> 0.98343743 | AO60: =L60/X60 -> 0.99837536 | AP60: =IF(OR(Q60<0, Q60="NA"), 0, 1) -> 1 | AQ60: =IF(OR(S60<0, S60="NA"), 0, 1) -> 1 | AR60: =IFERROR(IF((AF60-AG60)>0,1,0),0) -> 1 | AS60: =IFERROR(IF((S60-Q60)>0,1,0),0) -> 1 | AT60: =IFERROR(IF((AH60-AI60)<0,1,0),0) -> 0 | AU60: =IFERROR(IF((AJ60-AK60)>0,1,0),0) -> 1 | AV60: =IFERROR(IF((AL60-AM60)>0,1,0),0) -> 1 | AW60: =IFERROR(IF((AN60-AO60)>0,1,0),0) -> 0 | AX60: =IFERROR(IF((AC60-AD60)<0,1,0),0) -> 0 | AY60: =SUM(AP60:AX60) -> 6
A61: Adecoagro S.A. (NYSE:AGRO) | B61: 4910946 | C61: NYSE | D61: 9.91 | E61: 999.2927 | F61: Consumer Staples | G61: Food, Beverage and Tobacco | H61: Food Products | I61: Packaged Foods and Meats | J61: 31131 - Sugar Manufacturing | K61: 1408633 | L61: 1322932 | M61: 392061 | N61: 409959 | O61: 178102 | P61: 193405 | Q61: 158132 | R61: 214808 | S61: 342575 | T61: 511024 | U61: 688628 | V61: 678805 | W61: 3227710 | X61: 3148372 | Y61: 1066665 | Z61: 1023975 | AA61: 444786 | AB61: 422522 | AC61: 100836801 | AD61: 102461382 | AF61: =Q61/W61 -> 0.04899201 | AG61: =R61/X61 -> 0.068228278 | AH61: =U61/W61 -> 0.21334878 | AI61: =V61/X61 -> 0.21560508 | AJ61: =Y61/AA61 -> 2.3981533 | AK61: =Z61/AB61 -> 2.4234833 | AL61: =O61/K61 -> 0.12643606 | AM61: =P61/L61 -> 0.14619421 | AN61: =K61/W61 -> 0.4364187 | AO61: =L61/X61 -> 0.42019558 | AP61: =IF(OR(Q61<0, Q61="NA"), 0, 1) -> 1 | AQ61: =IF(OR(S61<0, S61="NA"), 0, 1) -> 1 | AR61: =IFERROR(IF((AF61-AG61)>0,1,0),0) -> 0 | AS61: =IFERROR(IF((S61-Q61)>0,1,0),0) -> 1 | AT61: =IFERROR(IF((AH61-AI61)<0,1,0),0) -> 1 | AU61: =IFERROR(IF((AJ61-AK61)>0,1,0),0) -> 0 | AV61: =IFERROR(IF((AL61-AM61)>0,1,0),0) -> 0 | AW61: =IFERROR(IF((AN61-AO61)>0,1,0),0) -> 1 | AX61: =IFERROR(IF((AC61-AD61)<0,1,0),0) -> 1 | AY61: =SUM(AP61:AX61) -> 6
A62: Adeia Inc. (NASDAQGS:ADEA) | B62: 4968288 | C62: NASDAQGS | D62: 12.69 | E62: 1386.5721 | F62: Information Technology | G62: Software and Services | H62: Software | I62: Systems Software | J62: 513210 - Software Publishers | K62: 343723 | L62: 359019 | M62: 188131 | N62: 209322 | O62: 106410 | P62: 117959 | Q62: 41295 | R62: 46213 | S62: 144441 | T62: 151377 | U62: 499692 | V62: 510857 | W62: 1083165 | X62: 1068674 | Y62: 244710 | Z62: 219383 | AA62: 71498 | AB62: 73223 | AC62: 109193000 | AD62: 108854000 | AF62: =Q62/W62 -> 0.038124385 | AG62: =R62/X62 -> 0.043243309 | AH62: =U62/W62 -> 0.46132584 | AI62: =V62/X62 -> 0.47802885 | AJ62: =Y62/AA62 -> 3.4226132 | AK62: =Z62/AB62 -> 2.9960941 | AL62: =O62/K62 -> 0.30958068 | AM62: =P62/L62 -> 0.32855921 | AN62: =K62/W62 -> 0.31733208 | AO62: =L62/X62 -> 0.3359481 | AP62: =IF(OR(Q62<0, Q62="NA"), 0, 1) -> 1 | AQ62: =IF(OR(S62<0, S62="NA"), 0, 1) -> 1 | AR62: =IFERROR(IF((AF62-AG62)>0,1,0),0) -> 0 | AS62: =IFERROR(IF((S62-Q62)>0,1,0),0) -> 1 | AT62: =IFERROR(IF((AH62-AI62)<0,1,0),0) -> 1 | AU62: =IFERROR(IF((AJ62-AK62)>0,1,0),0) -> 1 | AV62: =IFERROR(IF((AL62-AM62)>0,1,0),0) -> 0 | AW62: =IFERROR(IF((AN62-AO62)>0,1,0),0) -> 0 | AX62: =IFERROR(IF((AC62-AD62)<0,1,0),0) -> 0 | AY62: =SUM(AP62:AX62) -> 5
A63: Adient plc (NYSE:ADNT) | B63: 4915451 | C63: NYSE | D63: 17.1 | E63: 1451.2216 | F63: Consumer Discretionary | G63: Automobiles and Components | H63: Automobile Components | I63: Automotive Parts and Equipment | J63: 3363 - Motor Vehicle Parts Manufacturing | K63: 14688000 | L63: 14855000 | M63: 733000 | N63: 723000 | O63: 401000 | P63: 387000 | Q63: 101000 | R63: 158000 | S63: 543000 | T63: 574000 | U63: 2396000 | V63: 2395000 | W63: 9351000 | X63: 9095000 | Y63: 4086000 | Z63: 3999000 | AA63: 3678000 | AB63: 3686000 | AC63: 84866763 | AD63: 87189933 | AF63: =Q63/W63 -> 0.010800984 | AG63: =R63/X63 -> 0.017372183 | AH63: =U63/W63 -> 0.25622928 | AI63: =V63/X63 -> 0.2633315 | AJ63: =Y63/AA63 -> 1.1109299 | AK63: =Z63/AB63 -> 1.0849159 | AL63: =O63/K63 -> 0.027301198 | AM63: =P63/L63 -> 0.026051834 | AN63: =K63/W63 -> 1.5707411 | AO63: =L63/X63 -> 1.633315 | AP63: =IF(OR(Q63<0, Q63="NA"), 0, 1) -> 1 | AQ63: =IF(OR(S63<0, S63="NA"), 0, 1) -> 1 | AR63: =IFERROR(IF((AF63-AG63)>0,1,0),0) -> 0 | AS63: =IFERROR(IF((S63-Q63)>0,1,0),0) -> 1 | AT63: =IFERROR(IF((AH63-AI63)<0,1,0),0) -> 1 | AU63: =IFERROR(IF((AJ63-AK63)>0,1,0),0) -> 1 | AV63: =IFERROR(IF((AL63-AM63)>0,1,0),0) -> 1 | AW63: =IFERROR(IF((AN63-AO63)>0,1,0),0) -> 0 | AX63: =IFERROR(IF((AC63-AD63)<0,1,0),0) -> 1 | AY63: =SUM(AP63:AX63) -> 7
A64: ADMA Biologics, Inc. (NASDAQGM:ADMA) | B64: 4812756 | C64: NASDAQGM | D64: 16.49 | E64: 3898.0753 | F64: Health Care | G64: Pharmaceuticals, Biotechnology and Life Sciences | H64: Biotechnology | I64: Biotechnology | J64: 325414 - Biological Product (except Diagnostic) Manufacturing | K64: 382809 | L64: 330244 | M64: 125894 | N64: 95093 | O64: 117693 | P64: 86740 | Q64: 68132 | R64: 34789 | S64: 86053 | T64: 73010 | U64: 101326 | V64: 131074 | W64: 390618 | X64: 376399 | Y64: 318193 | Z64: 303691 | AA64: 44891 | AB64: 44177 | AC64: 236378607 | AD64: 233026736 | AF64: =Q64/W64 -> 0.17442105 | AG64: =R64/X64 -> 0.092425857 | AH64: =U64/W64 -> 0.25939921 | AI64: =V64/X64 -> 0.34823153 | AJ64: =Y64/AA64 -> 7.0881246 | AK64: =Z64/AB64 -> 6.8744143 | AL64: =O64/K64 -> 0.30744575 | AM64: =P64/L64 -> 0.26265428 | AN64: =K64/W64 -> 0.9800086 | AO64: =L64/X64 -> 0.87737746 | AP64: =IF(OR(Q64<0, Q64="NA"), 0, 1) -> 1 | AQ64: =IF(OR(S64<0, S64="NA"), 0, 1) -> 1 | AR64: =IFERROR(IF((AF64-AG64)>0,1,0),0) -> 1 | AS64: =IFERROR(IF((S64-Q64)>0,1,0),0) -> 1 | AT64: =IFERROR(IF((AH64-AI64)<0,1,0),0) -> 1 | AU64: =IFERROR(IF((AJ64-AK64)>0,1,0),0) -> 1 | AV64: =IFERROR(IF((AL64-AM64)>0,1,0),0) -> 1 | AW64: =IFERROR(IF((AN64-AO64)>0,1,0),0) -> 1 | AX64: =IFERROR(IF((AC64-AD64)<0,1,0),0) -> 0 | AY64: =SUM(AP64:AX64) -> 8
A65: Adobe Inc. (NASDAQGS:ADBE) | B65: 4047847 | C65: NASDAQGS | D65: 408.5 | E65: 179821.7 | F65: Information Technology | G65: Software and Services | H65: Software | I65: Application Software | J65: 513210 - Software Publishers | K65: 21505000 | L65: 20947000 | M65: 8592999.8 | N65: 8134000 | O65: 7741000 | P65: 7527000 | Q65: 5560000 | R65: 5360000 | S65: NA | T65: 6732000 | U65: 4129000 | V65: 4128000 | W65: 30230000 | X65: 29830000 | Y65: 11232000 | Z65: 10716000 | AA65: 10521000 | AB65: 9644000 | AC65: 441000000 | AD65: 445000000 | AF65: =Q65/W65 -> 0.18392326 | AG65: =R65/X65 -> 0.17968488 | AH65: =U65/W65 -> 0.13658617 | AI65: =V65/X65 -> 0.13838418 | AJ65: =Y65/AA65 -> 1.0675791 | AK65: =Z65/AB65 -> 1.1111572 | AL65: =O65/K65 -> 0.3599628 | AM65: =P65/L65 -> 0.35933547 | AN65: =K65/W65 -> 0.71137942 | AO65: =L65/X65 -> 0.70221254 | AP65: =IF(OR(Q65<0, Q65="NA"), 0, 1) -> 1 | AQ65: =IF(OR(S65<0, S65="NA"), 0, 1) -> 0 | AR65: =IFERROR(IF((AF65-AG65)>0,1,0),0) -> 1 | AS65: =IFERROR(IF((S65-Q65)>0,1,0),0) -> 0 | AT65: =IFERROR(IF((AH65-AI65)<0,1,0),0) -> 1 | AU65: =IFERROR(IF((AJ65-AK65)>0,1,0),0) -> 0 | AV65: =IFERROR(IF((AL65-AM65)>0,1,0),0) -> 1 | AW65: =IFERROR(IF((AN65-AO65)>0,1,0),0) -> 1 | AX65: =IFERROR(IF((AC65-AD65)<0,1,0),0) -> 1 | AY65: =SUM(AP65:AX65) -> 6
A66: ADS-TEC Energy PLC (NASDAQCM:ADSE) | B66: 9995793 | C66: NASDAQCM | D66: 15.1 | E66: 776.71409 | F66: Industrials | G66: Capital Goods | H66: Electrical Equipment | I66: Electrical Components and Equipment | J66: 335910 - Battery Manufacturing | K66: 160488.23 | L66: 138704.13 | M66: -25586.867 | N66: -34430.491 | O66: -30883.798 | P66: -39121.663 | Q66: -77281.967 | R66: -68620.186 | S66: 2783.133 | T66: -9808.617 | U66: NA | V66: NA | W66: 138421.73 | X66: 139377.49 | Y66: 101843.99 | Z66: 102547.2 | AA66: 69101.039 | AB66: 69578.164 | AC66: 50740449 | AD66: 50740449 | AF66: =Q66/W66 -> -0.55830806 | AG66: =R66/X66 -> -0.49233333 | AH66: =U66/W66 -> #VALUE! | AI66: =V66/X66 -> #VALUE! | AJ66: =Y66/AA66 -> 1.4738417 | AK66: =Z66/AB66 -> 1.4738417 | AL66: =O66/K66 -> -0.19243653 | AM66: =P66/L66 -> -0.28205118 | AN66: =K66/W66 -> 1.159415 | AO66: =L66/X66 -> 0.99516874 | AP66: =IF(OR(Q66<0, Q66="NA"), 0, 1) -> 0 | AQ66: =IF(OR(S66<0, S66="NA"), 0, 1) -> 1 | AR66: =IFERROR(IF((AF66-AG66)>0,1,0),0) -> 0 | AS66: =IFERROR(IF((S66-Q66)>0,1,0),0) -> 1 | AT66: =IFERROR(IF((AH66-AI66)<0,1,0),0) -> 0 | AU66: =IFERROR(IF((AJ66-AK66)>0,1,0),0) -> 0 | AV66: =IFERROR(IF((AL66-AM66)>0,1,0),0) -> 1 | AW66: =IFERROR(IF((AN66-AO66)>0,1,0),0) -> 1 | AX66: =IFERROR(IF((AC66-AD66)<0,1,0),0) -> 0 | AY66: =SUM(AP66:AX66) -> 4
A67: ADT Inc. (NYSE:ADT) | B67: 4589651 | C67: NYSE | D67: 6.92 | E67: 6212.908 | F67: Consumer Discretionary | G67: Consumer Services | H67: Diversified Consumer Services | I67: Specialized Consumer Services | J67: 56162 - Security Systems Services | K67: 5140300 | L67: 5076337 | M67: 2431220 | N67: 2414236 | O67: 1097340 | P67: 1085780 | Q67: 886968 | R67: 673580 | S67: 1837255 | T67: 1785296 | U67: 7479567 | V67: 7482955 | W67: 16084561 | X67: 15985822 | Y67: 1002893 | Z67: 985541 | AA67: 1245357 | AB67: 1315346 | AC67: 902800434 | AD67: 902602830 | AF67: =Q67/W67 -> 0.05514406 | AG67: =R67/X67 -> 0.042136088 | AH67: =U67/W67 -> 0.4650153 | AI67: =V67/X67 -> 0.46809948 | AJ67: =Y67/AA67 -> 0.80530563 | AK67: =Z67/AB67 -> 0.74926369 | AL67: =O67/K67 -> 0.21347781 | AM67: =P67/L67 -> 0.21389045 | AN67: =K67/W67 -> 0.31957975 | AO67: =L67/X67 -> 0.31755245 | AP67: =IF(OR(Q67<0, Q67="NA"), 0, 1) -> 1 | AQ67: =IF(OR(S67<0, S67="NA"), 0, 1) -> 1 | AR67: =IFERROR(IF((AF67-AG67)>0,1,0),0) -> 1 | AS67: =IFERROR(IF((S67-Q67)>0,1,0),0) -> 1 | AT67: =IFERROR(IF((AH67-AI67)<0,1,0),0) -> 1 | AU67: =IFERROR(IF((AJ67-AK67)>0,1,0),0) -> 1 | AV67: =IFERROR(IF((AL67-AM67)>0,1,0),0) -> 0 | AW67: =IFERROR(IF((AN67-AO67)>0,1,0),0) -> 1 | AX67: =IFERROR(IF((AC67-AD67)<0,1,0),0) -> 0 | AY67: =SUM(AP67:AX67) -> 7
A68: Adtalem Global Education Inc. (NYSE:ATGE) | B68: 4183694 | C68: NYSE | D68: 94.3 | E68: 3535.3832 | F68: Consumer Discretionary | G68: Consumer Services | H68: Diversified Consumer Services | I68: Education Services | J68: 611 - Educational Services | K68: 1633207 | L68: 1584652 | M68: 359252 | N68: 346959 | O68: 291339 | P68: 271639 | Q68: 172296 | R68: 136777 | S68: 290018 | T68: 295775 | U68: 649318 | V68: 648712 | W68: 2817707 | X68: 2741417 | Y68: 516914 | Z68: 418085 | AA68: 551309 | AB68: 487657 | AC68: 37716000 | AD68: 37681000 | AF68: =Q68/W68 -> 0.061147593 | AG68: =R68/X68 -> 0.049892811 | AH68: =U68/W68 -> 0.23044199 | AI68: =V68/X68 -> 0.23663383 | AJ68: =Y68/AA68 -> 0.93761212 | AK68: =Z68/AB68 -> 0.85733415 | AL68: =O68/K68 -> 0.17838461 | AM68: =P68/L68 -> 0.17141871 | AN68: =K68/W68 -> 0.57962272 | AO68: =L68/X68 -> 0.57804121 | AP68: =IF(OR(Q68<0, Q68="NA"), 0, 1) -> 1 | AQ68: =IF(OR(S68<0, S68="NA"), 0, 1) -> 1 | AR68: =IFERROR(IF((AF68-AG68)>0,1,0),0) -> 1 | AS68: =IFERROR(IF((S68-Q68)>0,1,0),0) -> 1 | AT68: =IFERROR(IF((AH68-AI68)<0,1,0),0) -> 1 | AU68: =IFERROR(IF((AJ68-AK68)>0,1,0),0) -> 1 | AV68: =IFERROR(IF((AL68-AM68)>0,1,0),0) -> 1 | AW68: =IFERROR(IF((AN68-AO68)>0,1,0),0) -> 1 | AX68: =IFERROR(IF((AC68-AD68)<0,1,0),0) -> 0 | AY68: =SUM(AP68:AX68) -> 8
A69: ADTRAN Holdings, Inc. (NASDAQGS:ADTN) | B69: 4189232 | C69: NASDAQGS | D69: 10.01 | E69: 790.61925 | F69: Information Technology | G69: Technology Hardware and Equipment | H69: Communications Equipment | I69: Communications Equipment | J69: 334210 - Telephone Apparatus Manufacturing | K69: 905347 | L69: 949974 | M69: -22228 | N69: -39070 | O69: -112176 | P69: -129708 | Q69: -504564 | R69: -551356 | S69: 82236 | T69: 47052 | U69: 189849 | V69: 190273 | W69: 1273146 | X69: 1290782 | Y69: 638856 | Z69: 668319 | AA69: 304824 | AB69: 289712 | AC69: 78967000 | AD69: 78855000 | AF69: =Q69/W69 -> -0.39631276 | AG69: =R69/X69 -> -0.42714881 | AH69: =U69/W69 -> 0.14911801 | AI69: =V69/X69 -> 0.14740909 | AJ69: =Y69/AA69 -> 2.0958192 | AK69: =Z69/AB69 -> 2.3068392 | AL69: =O69/K69 -> -0.12390387 | AM69: =P69/L69 -> -0.13653847 | AN69: =K69/W69 -> 0.71111012 | AO69: =L69/X69 -> 0.73596781 | AP69: =IF(OR(Q69<0, Q69="NA"), 0, 1) -> 0 | AQ69: =IF(OR(S69<0, S69="NA"), 0, 1) -> 1 | AR69: =IFERROR(IF((AF69-AG69)>0,1,0),0) -> 1 | AS69: =IFERROR(IF((S69-Q69)>0,1,0),0) -> 1 | AT69: =IFERROR(IF((AH69-AI69)<0,1,0),0) -> 0 | AU69: =IFERROR(IF((AJ69-AK69)>0,1,0),0) -> 0 | AV69: =IFERROR(IF((AL69-AM69)>0,1,0),0) -> 1 | AW69: =IFERROR(IF((AN69-AO69)>0,1,0),0) -> 0 | AX69: =IFERROR(IF((AC69-AD69)<0,1,0),0) -> 0 | AY69: =SUM(AP69:AX69) -> 4
A70: Advance Auto Parts, Inc. (NYSE:AAP) | B70: 4226924 | C70: NYSE | D70: 44.85 | E70: 2661.422 | F70: Consumer Discretionary | G70: Consumer Discretionary Distribution and Retail | H70: Specialty Retail | I70: Automotive Retail | J70: 441330 - Automotive Parts and Accessories Retailers | K70: 11191239 | L70: 11261453 | M70: 456825 | N70: 371774 | O70: 139832 | P70: 60851 | Q70: 43862 | R70: -12161 | S70: 416477 | T70: 542320 | U70: 1788513 | V70: 1787867 | W70: 12468184 | X70: 12289806 | Y70: 7493767 | Z70: 6460140 | AA70: 5593541 | AB70: 5256774 | AC70: 59337000 | AD70: 59281000 | AF70: =Q70/W70 -> 0.0035179141 | AG70: =R70/X70 -> -0.00098951928 | AH70: =U70/W70 -> 0.14344615 | AI70: =V70/X70 -> 0.14547561 | AJ70: =Y70/AA70 -> 1.3397179 | AK70: =Z70/AB70 -> 1.2289172 | AL70: =O70/K70 -> 0.012494774 | AM70: =P70/L70 -> 0.0054034768 | AN70: =K70/W70 -> 0.89758372 | AO70: =L70/X70 -> 0.91632472 | AP70: =IF(OR(Q70<0, Q70="NA"), 0, 1) -> 1 | AQ70: =IF(OR(S70<0, S70="NA"), 0, 1) -> 1 | AR70: =IFERROR(IF((AF70-AG70)>0,1,0),0) -> 1 | AS70: =IFERROR(IF((S70-Q70)>0,1,0),0) -> 1 | AT70: =IFERROR(IF((AH70-AI70)<0,1,0),0) -> 1 | AU70: =IFERROR(IF((AJ70-AK70)>0,1,0),0) -> 1 | AV70: =IFERROR(IF((AL70-AM70)>0,1,0),0) -> 1 | AW70: =IFERROR(IF((AN70-AO70)>0,1,0),0) -> 0 | AX70: =IFERROR(IF((AC70-AD70)<0,1,0),0) -> 0 | AY70: =SUM(AP70:AX70) -> 7
A71: Advanced Drainage Systems, Inc. (NYSE:WMS) | B71: 4987603 | C71: NYSE | D71: 114.98 | E71: 8915.1063 | F71: Industrials | G71: Capital Goods | H71: Building Products | I71: Building Products | J71: 326122 - Plastics Pipe and Pipe Fitting Manufacturing | K71: 2914153 | L71: 2911763 | M71: 858326 | N71: 860407 | O71: 707959 | P71: 718126 | Q71: 495855 | R71: 501708 | S71: 609390 | T71: 657387 | U71: 1250983 | V71: 1252266 | W71: 3535750 | X71: 3447538 | Y71: 1491920 | Z71: 1424300 | AA71: 467337 | AB71: 492927 | AC71: 71463000 | AD71: 71198000 | AF71: =Q71/W71 -> 0.1402404 | AG71: =R71/X71 -> 0.14552646 | AH71: =U71/W71 -> 0.3538098 | AI71: =V71/X71 -> 0.36323486 | AJ71: =Y71/AA71 -> 3.1923858 | AK71: =Z71/AB71 -> 2.8894745 | AL71: =O71/K71 -> 0.24293817 | AM71: =P71/L71 -> 0.24662928 | AN71: =K71/W71 -> 0.82419656 | AO71: =L71/X71 -> 0.844592 | AP71: =IF(OR(Q71<0, Q71="NA"), 0, 1) -> 1 | AQ71: =IF(OR(S71<0, S71="NA"), 0, 1) -> 1 | AR71: =IFERROR(IF((AF71-AG71)>0,1,0),0) -> 0 | AS71: =IFERROR(IF((S71-Q71)>0,1,0),0) -> 1 | AT71: =IFERROR(IF((AH71-AI71)<0,1,0),0) -> 1 | AU71: =IFERROR(IF((AJ71-AK71)>0,1,0),0) -> 1 | AV71: =IFERROR(IF((AL71-AM71)>0,1,0),0) -> 0 | AW71: =IFERROR(IF((AN71-AO71)>0,1,0),0) -> 0 | AX71: =IFERROR(IF((AC71-AD71)<0,1,0),0) -> 0 | AY71: =SUM(AP71:AX71) -> 5
A72: Advanced Energy Industries, Inc. (NASDAQGS:AEIS) | B72: 4306705 | C72: NASDAQGS | D72: 117.35 | E72: 4420.9344 | F72: Information Technology | G72: Technology Hardware and Equipment | H72: Electronic Equipment, Instruments and Components | I72: Electronic Equipment and Instruments | J72: 333242 - Semiconductor Machinery Manufacturing | K72: 1471910 | L72: 1507684 | M72: 135878 | N72: 150671 | O72: 67285 | P72: 83186 | Q72: 42842 | R72: 90468 | S72: 132063 | T72: 170520 | U72: 564000 | V72: 887309 | W72: 2192860 | X72: 2541859 | Y72: 1345708 | Z72: 1677839 | AA72: 291508 | AB72: 306837 | AC72: 37671000 | AD72: 37671000 | AF72: =Q72/W72 -> 0.019537043 | AG72: =R72/X72 -> 0.035591274 | AH72: =U72/W72 -> 0.25719836 | AI72: =V72/X72 -> 0.34907876 | AJ72: =Y72/AA72 -> 4.6163673 | AK72: =Z72/AB72 -> 5.4681769 | AL72: =O72/K72 -> 0.045712713 | AM72: =P72/L72 -> 0.055174692 | AN72: =K72/W72 -> 0.67122844 | AO72: =L72/X72 -> 0.59314226 | AP72: =IF(OR(Q72<0, Q72="NA"), 0, 1) -> 1 | AQ72: =IF(OR(S72<0, S72="NA"), 0, 1) -> 1 | AR72: =IFERROR(IF((AF72-AG72)>0,1,0),0) -> 0 | AS72: =IFERROR(IF((S72-Q72)>0,1,0),0) -> 1 | AT72: =IFERROR(IF((AH72-AI72)<0,1,0),0) -> 1 | AU72: =IFERROR(IF((AJ72-AK72)>0,1,0),0) -> 0 | AV72: =IFERROR(IF((AL72-AM72)>0,1,0),0) -> 0 | AW72: =IFERROR(IF((AN72-AO72)>0,1,0),0) -> 1 | AX72: =IFERROR(IF((AC72-AD72)<0,1,0),0) -> 0 | AY72: =SUM(AP72:AX72) -> 5
A73: Advanced Flower Capital Inc. (NASDAQGM:AFCG) | B73: 24801985 | C73: NASDAQGM | D73: 8.33 | E73: 182.8658 | F73: Financials | G73: Financial Services | H73: Mortgage Real Estate Investment Trusts (REITs) | I73: Mortgage REITs | J73: 525990 - Other Financial Vehicles | K73: 40787 | L73: 51374 | M73: 16235 | N73: 23234 | O73: 16235 | P73: 23234 | Q73: 8588 | R73: 15184 | S73: 25574.227 | T73: 28392.569 | U73: 88461.936 | V73: 88311.721 | W73: 366618 | X73: 457992 | Y73: NA | Z73: NA | AA73: NA | AB73: NA | AC73: 21882047 | AD73: 20667094 | AF73: =Q73/W73 -> 0.023424927 | AG73: =R73/X73 -> 0.033153418 | AH73: =U73/W73 -> 0.24129185 | AI73: =V73/X73 -> 0.19282372 | AJ73: =Y73/AA73 -> #VALUE! | AK73: =Z73/AB73 -> #VALUE! | AL73: =O73/K73 -> 0.39804349 | AM73: =P73/L73 -> 0.45225211 | AN73: =K73/W73 -> 0.11125204 | AO73: =L73/X73 -> 0.11217227 | AP73: =IF(OR(Q73<0, Q73="NA"), 0, 1) -> 1 | AQ73: =IF(OR(S73<0, S73="NA"), 0, 1) -> 1 | AR73: =IFERROR(IF((AF73-AG73)>0,1,0),0) -> 0 | AS73: =IFERROR(IF((S73-Q73)>0,1,0),0) -> 1 | AT73: =IFERROR(IF((AH73-AI73)<0,1,0),0) -> 0 | AU73: =IFERROR(IF((AJ73-AK73)>0,1,0),0) -> 0 | AV73: =IFERROR(IF((AL73-AM73)>0,1,0),0) -> 0 | AW73: =IFERROR(IF((AN73-AO73)>0,1,0),0) -> 0 | AX73: =IFERROR(IF((AC73-AD73)<0,1,0),0) -> 0 | AY73: =SUM(AP73:AX73) -> 3
A74: Advanced Micro Devices, Inc. (NASDAQGS:AMD) | B74: 4066743 | C74: NASDAQGS | D74: 117.32 | E74: 190387.76 | F74: Information Technology | G74: Semiconductors and Semiconductor Equipment | H74: Semiconductors and Semiconductor Equipment | I74: Semiconductors | J74: 334413 - Semiconductor and Related Device Manufacturing | K74: 24295000 | L74: 23276000 | M74: 4479000 | N74: 4046000 | O74: 1371000 | P74: 871000 | Q74: 1826000 | R74: 1354000 | S74: 2123000 | T74: 1916000 | U74: 1720000 | V74: 1719000 | W74: 69636000 | X74: 67886000 | Y74: 18735000 | Z74: 17465000 | AA74: 7500000 | AB74: 6195000 | AC74: 1623000000 | AD74: 1618000000 | AF74: =Q74/W74 -> 0.026222069 | AG74: =R74/X74 -> 0.019945202 | AH74: =U74/W74 -> 0.024699868 | AI74: =V74/X74 -> 0.025321863 | AJ74: =Y74/AA74 -> 2.498 | AK74: =Z74/AB74 -> 2.819209 | AL74: =O74/K74 -> 0.056431364 | AM74: =P74/L74 -> 0.037420519 | AN74: =K74/W74 -> 0.34888563 | AO74: =L74/X74 -> 0.34286893 | AP74: =IF(OR(Q74<0, Q74="NA"), 0, 1) -> 1 | AQ74: =IF(OR(S74<0, S74="NA"), 0, 1) -> 1 | AR74: =IFERROR(IF((AF74-AG74)>0,1,0),0) -> 1 | AS74: =IFERROR(IF((S74-Q74)>0,1,0),0) -> 1 | AT74: =IFERROR(IF((AH74-AI74)<0,1,0),0) -> 1 | AU74: =IFERROR(IF((AJ74-AK74)>0,1,0),0) -> 0 | AV74: =IFERROR(IF((AL74-AM74)>0,1,0),0) -> 1 | AW74: =IFERROR(IF((AN74-AO74)>0,1,0),0) -> 1 | AX74: =IFERROR(IF((AC74-AD74)<0,1,0),0) -> 0 | AY74: =SUM(AP74:AX74) -> 7
A75: AdvanSix Inc. (NYSE:ASIX) | B75: 4698704 | C75: NYSE | D75: 28.98 | E75: 774.66464 | F75: Materials | G75: Materials | H75: Chemicals | I75: Commodity Chemicals | J75: 325211 - Plastics Material and Resin Manufacturing | K75: 1570703 | L75: 1495423 | M75: 138929 | N75: 91876 | O75: 63059 | P75: 16560 | Q75: 38715 | R75: 8472 | S75: 131417 | T75: 94969 | U75: 215000 | V75: 230000 | W75: 1510235 | X75: 1477950 | Y75: 395773 | Z75: 378592 | AA75: 295142 | AB75: 272954 | AC75: 26730739 | AD75: 26709407 | AF75: =Q75/W75 -> 0.025635083 | AG75: =R75/X75 -> 0.0057322643 | AH75: =U75/W75 -> 0.14236195 | AI75: =V75/X75 -> 0.15562096 | AJ75: =Y75/AA75 -> 1.3409579 | AK75: =Z75/AB75 -> 1.3870176 | AL75: =O75/K75 -> 0.040146992 | AM75: =P75/L75 -> 0.01107379 | AN75: =K75/W75 -> 1.0400388 | AO75: =L75/X75 -> 1.0118225 | AP75: =IF(OR(Q75<0, Q75="NA"), 0, 1) -> 1 | AQ75: =IF(OR(S75<0, S75="NA"), 0, 1) -> 1 | AR75: =IFERROR(IF((AF75-AG75)>0,1,0),0) -> 1 | AS75: =IFERROR(IF((S75-Q75)>0,1,0),0) -> 1 | AT75: =IFERROR(IF((AH75-AI75)<0,1,0),0) -> 1 | AU75: =IFERROR(IF((AJ75-AK75)>0,1,0),0) -> 0 | AV75: =IFERROR(IF((AL75-AM75)>0,1,0),0) -> 1 | AW75: =IFERROR(IF((AN75-AO75)>0,1,0),0) -> 1 | AX75: =IFERROR(IF((AC75-AD75)<0,1,0),0) -> 0 | AY75: =SUM(AP75:AX75) -> 7
A76: Advent Convertible and Income Fund (NYSE:AVK) | B76: 5721375 | C76: NYSE | D76: 11.85 | E76: 409.93616 | F76: Financials | G76: Financial Services | H76: Capital Markets | I76: Asset Management and Custody Banks | J76: 525990 - Other Financial Vehicles | K76: 37910.628 | L76: 32267.671 | M76: NA | N76: NA | O76: 30309.895 | P76: 24542.843 | Q76: 106501.27 | R76: -38747.013 | S76: -18023.245 | T76: 48505.738 | U76: 132000 | V76: 173000 | W76: 863675.35 | X76: 787917.65 | Y76: 17193.304 | Z76: 16483.795 | AA76: 197019 | AB76: 188090 | AC76: 44148745 | AD76: 34593769 | AF76: =Q76/W76 -> 0.1233117 | AG76: =R76/X76 -> -0.049176475 | AH76: =U76/W76 -> 0.15283521 | AI76: =V76/X76 -> 0.21956609 | AJ76: =Y76/AA76 -> 0.087267238 | AK76: =Z76/AB76 -> 0.087637806 | AL76: =O76/K76 -> 0.79950918 | AM76: =P76/L76 -> 0.76060163 | AN76: =K76/W76 -> 0.043894535 | AO76: =L76/X76 -> 0.040953101 | AP76: =IF(OR(Q76<0, Q76="NA"), 0, 1) -> 1 | AQ76: =IF(OR(S76<0, S76="NA"), 0, 1) -> 0 | AR76: =IFERROR(IF((AF76-AG76)>0,1,0),0) -> 1 | AS76: =IFERROR(IF((S76-Q76)>0,1,0),0) -> 0 | AT76: =IFERROR(IF((AH76-AI76)<0,1,0),0) -> 1 | AU76: =IFERROR(IF((AJ76-AK76)>0,1,0),0) -> 0 | AV76: =IFERROR(IF((AL76-AM76)>0,1,0),0) -> 1 | AW76: =IFERROR(IF((AN76-AO76)>0,1,0),0) -> 1 | AX76: =IFERROR(IF((AC76-AD76)<0,1,0),0) -> 0 | AY76: =SUM(AP76:AX76) -> 5
A77: Advent Technologies Holdings, Inc. (NASDAQCM:ADN) | B77: 6300107 | C77: NASDAQCM | D77: 6.3 | E77: 16.61 | F77: Industrials | G77: Capital Goods | H77: Electrical Equipment | I77: Electrical Components and Equipment | J77: 335 - Electrical Equipment, Appliance, and Component Manufacturing | K77: 8157 | L77: 7026 | M77: -47765 | N77: -43444 | O77: -50450 | P77: -46590 | Q77: -64883 | R77: -58207 | S77: 7213 | T77: -18026 | U77: NA | V77: 537 | W77: 7329 | X77: 14369 | Y77: 1424 | Z77: 6915 | AA77: 25144 | AB77: 15779 | AC77: 2636508 | AD77: 2636508 | AF77: =Q77/W77 -> -8.8529131 | AG77: =R77/X77 -> -4.0508734 | AH77: =U77/W77 -> #VALUE! | AI77: =V77/X77 -> 0.037372121 | AJ77: =Y77/AA77 -> 0.056633789 | AK77: =Z77/AB77 -> 0.4382407 | AL77: =O77/K77 -> -6.1848719 | AM77: =P77/L77 -> -6.6310845 | AN77: =K77/W77 -> 1.1129758 | AO77: =L77/X77 -> 0.48896931 | AP77: =IF(OR(Q77<0, Q77="NA"), 0, 1) -> 0 | AQ77: =IF(OR(S77<0, S77="NA"), 0, 1) -> 1 | AR77: =IFERROR(IF((AF77-AG77)>0,1,0),0) -> 0 | AS77: =IFERROR(IF((S77-Q77)>0,1,0),0) -> 1 | AT77: =IFERROR(IF((AH77-AI77)<0,1,0),0) -> 0 | AU77: =IFERROR(IF((AJ77-AK77)>0,1,0),0) -> 0 | AV77: =IFERROR(IF((AL77-AM77)>0,1,0),0) -> 1 | AW77: =IFERROR(IF((AN77-AO77)>0,1,0),0) -> 1 | AX77: =IFERROR(IF((AC77-AD77)<0,1,0),0) -> 0 | AY77: =SUM(AP77:AX77) -> 4
A78: Adverum Biotechnologies, Inc. (NASDAQCM:ADVM) | B78: 4810761 | C78: NASDAQCM | D78: 4.2 | E78: 87.370345 | F78: Health Care | G78: Pharmaceuticals, Biotechnology and Life Sciences | H78: Biotechnology | I78: Biotechnology | J78: 325414 - Biological Product (except Diagnostic) Manufacturing | K78: 1000 | L78: 0 | M78: -99024 | N78: -103713 | O78: -102876 | P78: -108184 | Q78: -94111 | R78: -99862 | S78: -85541 | T78: -88330 | U78: NA | V78: NA | W78: 234375 | X78: 253803 | Y78: 161080 | Z78: 179418 | AA78: 27657 | AB78: 22461 | AC78: 20801000 | AD78: 20801000 | AF78: =Q78/W78 -> -0.40154027 | AG78: =R78/X78 -> -0.39346265 | AH78: =U78/W78 -> #VALUE! | AI78: =V78/X78 -> #VALUE! | AJ78: =Y78/AA78 -> 5.8242036 | AK78: =Z78/AB78 -> 7.9879792 | AL78: =O78/K78 -> -102.876 | AM78: =P78/L78 -> #DIV/0! | AN78: =K78/W78 -> 0.0042666667 | AO78: =L78/X78 -> 0 | AP78: =IF(OR(Q78<0, Q78="NA"), 0, 1) -> 0 | AQ78: =IF(OR(S78<0, S78="NA"), 0, 1) -> 0 | AR78: =IFERROR(IF((AF78-AG78)>0,1,0),0) -> 0 | AS78: =IFERROR(IF((S78-Q78)>0,1,0),0) -> 1 | AT78: =IFERROR(IF((AH78-AI78)<0,1,0),0) -> 0 | AU78: =IFERROR(IF((AJ78-AK78)>0,1,0),0) -> 0 | AV78: =IFERROR(IF((AL78-AM78)>0,1,0),0) -> 0 | AW78: =IFERROR(IF((AN78-AO78)>0,1,0),0) -> 1 | AX78: =IFERROR(IF((AC78-AD78)<0,1,0),0) -> 0 | AY78: =SUM(AP78:AX78) -> 2
A79: Advisor Managed Portfolios - Optimize Strategy Index ETF (NASDAQGM:OPTZ) | B79: 116212652 | C79: NASDAQGM | D79: 29.19 | E79: 162.8802 | F79: Financials | G79: Financial Services | H79: Capital Markets | I79: Asset Management and Custody Banks | K79: NA | L79: NA | M79: NA | N79: NA | O79: NA | P79: NA | Q79: NA | R79: NA | S79: NA | T79: NA | U79: NA | V79: NA | W79: NA | X79: NA | Y79: NA | Z79: NA | AA79: NA | AB79: NA | AC79: NA | AD79: NA | AF79: =Q79/W79 -> #VALUE! | AG79: =R79/X79 -> #VALUE! | AH79: =U79/W79 -> #VALUE! | AI79: =V79/X79 -> #VALUE! | AJ79: =Y79/AA79 -> #VALUE! | AK79: =Z79/AB79 -> #VALUE! | AL79: =O79/K79 -> #VALUE! | AM79: =P79/L79 -> #VALUE! | AN79: =K79/W79 -> #VALUE! | AO79: =L79/X79 -> #VALUE! | AP79: =IF(OR(Q79<0, Q79="NA"), 0, 1) -> 0 | AQ79: =IF(OR(S79<0, S79="NA"), 0, 1) -> 0 | AR79: =IFERROR(IF((AF79-AG79)>0,1,0),0) -> 0 | AS79: =IFERROR(IF((S79-Q79)>0,1,0),0) -> 0 | AT79: =IFERROR(IF((AH79-AI79)<0,1,0),0) -> 0 | AU79: =IFERROR(IF((AJ79-AK79)>0,1,0),0) -> 0 | AV79: =IFERROR(IF((AL79-AM79)>0,1,0),0) -> 0 | AW79: =IFERROR(IF((AN79-AO79)>0,1,0),0) -> 0 | AX79: =IFERROR(IF((AC79-AD79)<0,1,0),0) -> 0 | AY79: =SUM(AP79:AX79) -> 0
A80: AdvisorShares Trust - AdvisorShares Dorsey Wright ADR ETF (NASDAQGM:AADR) | B80: 5731327 | C80: NASDAQGM | D80: 69.41 | E80: 23.5994 | F80: Financials | G80: Financial Services | H80: Capital Markets | I80: Asset Management and Custody Banks | K80: NA | L80: NA | M80: NA | N80: NA | O80: NA | P80: NA | Q80: NA | R80: NA | S80: NA | T80: NA | U80: NA | V80: NA | W80: NA | X80: NA | Y80: NA | Z80: NA | AA80: NA | AB80: NA | AC80: NA | AD80: NA | AF80: =Q80/W80 -> #VALUE! | AG80: =R80/X80 -> #VALUE! | AH80: =U80/W80 -> #VALUE! | AI80: =V80/X80 -> #VALUE! | AJ80: =Y80/AA80 -> #VALUE! | AK80: =Z80/AB80 -> #VALUE! | AL80: =O80/K80 -> #VALUE! | AM80: =P80/L80 -> #VALUE! | AN80: =K80/W80 -> #VALUE! | AO80: =L80/X80 -> #VALUE! | AP80: =IF(OR(Q80<0, Q80="NA"), 0, 1) -> 0 | AQ80: =IF(OR(S80<0, S80="NA"), 0, 1) -> 0 | AR80: =IFERROR(IF((AF80-AG80)>0,1,0),0) -> 0 | AS80: =IFERROR(IF((S80-Q80)>0,1,0),0) -> 0 | AT80: =IFERROR(IF((AH80-AI80)<0,1,0),0) -> 0 | AU80: =IFERROR(IF((AJ80-AK80)>0,1,0),0) -> 0 | AV80: =IFERROR(IF((AL80-AM80)>0,1,0),0) -> 0 | AW80: =IFERROR(IF((AN80-AO80)>0,1,0),0) -> 0 | AX80: =IFERROR(IF((AC80-AD80)<0,1,0),0) -> 0 | AY80: =SUM(AP80:AX80) -> 0
A81: AdvisorShares Trust - AdvisorShares Dorsey Wright FSM All Cap World ETF (NASDAQGM:DWAW) | B81: 19402512 | C81: NASDAQGM | D81: 40.1 | E81: 82.4055 | F81: Financials | G81: Financial Services | H81: Capital Markets | I81: Asset Management and Custody Banks | K81: NA | L81: NA | M81: NA | N81: NA | O81: NA | P81: NA | Q81: NA | R81: NA | S81: NA | T81: NA | U81: NA | V81: NA | W81: NA | X81: NA | Y81: NA | Z81: NA | AA81: NA | AB81: NA | AC81: NA | AD81: NA | AF81: =Q81/W81 -> #VALUE! | AG81: =R81/X81 -> #VALUE! | AH81: =U81/W81 -> #VALUE! | AI81: =V81/X81 -> #VALUE! | AJ81: =Y81/AA81 -> #VALUE! | AK81: =Z81/AB81 -> #VALUE! | AL81: =O81/K81 -> #VALUE! | AM81: =P81/L81 -> #VALUE! | AN81: =K81/W81 -> #VALUE! | AO81: =L81/X81 -> #VALUE! | AP81: =IF(OR(Q81<0, Q81="NA"), 0, 1) -> 0 | AQ81: =IF(OR(S81<0, S81="NA"), 0, 1) -> 0 | AR81: =IFERROR(IF((AF81-AG81)>0,1,0),0) -> 0 | AS81: =IFERROR(IF((S81-Q81)>0,1,0),0) -> 0 | AT81: =IFERROR(IF((AH81-AI81)<0,1,0),0) -> 0 | AU81: =IFERROR(IF((AJ81-AK81)>0,1,0),0) -> 0 | AV81: =IFERROR(IF((AL81-AM81)>0,1,0),0) -> 0 | AW81: =IFERROR(IF((AN81-AO81)>0,1,0),0) -> 0 | AX81: =IFERROR(IF((AC81-AD81)<0,1,0),0) -> 0 | AY81: =SUM(AP81:AX81) -> 0
A82: AdvisorShares Trust - AdvisorShares Dorsey Wright FSM US Core ETF (NASDAQGM:DWUS) | B82: 19401949 | C82: NASDAQGM | D82: 47.85 | E82: 112.926 | F82: Financials | G82: Financial Services | H82: Capital Markets | I82: Asset Management and Custody Banks | K82: NA | L82: NA | M82: NA | N82: NA | O82: NA | P82: NA | Q82: NA | R82: NA | S82: NA | T82: NA | U82: NA | V82: NA | W82: NA | X82: NA | Y82: NA | Z82: NA | AA82: NA | AB82: NA | AC82: NA | AD82: NA | AF82: =Q82/W82 -> #VALUE! | AG82: =R82/X82 -> #VALUE! | AH82: =U82/W82 -> #VALUE! | AI82: =V82/X82 -> #VALUE! | AJ82: =Y82/AA82 -> #VALUE! | AK82: =Z82/AB82 -> #VALUE! | AL82: =O82/K82 -> #VALUE! | AM82: =P82/L82 -> #VALUE! | AN82: =K82/W82 -> #VALUE! | AO82: =L82/X82 -> #VALUE! | AP82: =IF(OR(Q82<0, Q82="NA"), 0, 1) -> 0 | AQ82: =IF(OR(S82<0, S82="NA"), 0, 1) -> 0 | AR82: =IFERROR(IF((AF82-AG82)>0,1,0),0) -> 0 | AS82: =IFERROR(IF((S82-Q82)>0,1,0),0) -> 0 | AT82: =IFERROR(IF((AH82-AI82)<0,1,0),0) -> 0 | AU82: =IFERROR(IF((AJ82-AK82)>0,1,0),0) -> 0 | AV82: =IFERROR(IF((AL82-AM82)>0,1,0),0) -> 0 | AW82: =IFERROR(IF((AN82-AO82)>0,1,0),0) -> 0 | AX82: =IFERROR(IF((AC82-AD82)<0,1,0),0) -> 0 | AY82: =SUM(AP82:AX82) -> 0
A83: AdvisorShares Trust - AdvisorShares Dorsey Wright Short ETF (NASDAQGM:DWSH) | B83: 10546576 | C83: NASDAQGM | D83: 6.96 | E83: 13.6068 | F83: Financials | G83: Financial Services | H83: Capital Markets | I83: Asset Management and Custody Banks | K83: NA | L83: NA | M83: NA | N83: NA | O83: NA | P83: NA | Q83: NA | R83: NA | S83: NA | T83: NA | U83: NA | V83: NA | W83: NA | X83: NA | Y83: NA | Z83: NA | AA83: NA | AB83: NA | AC83: NA | AD83: NA | AF83: =Q83/W83 -> #VALUE! | AG83: =R83/X83 -> #VALUE! | AH83: =U83/W83 -> #VALUE! | AI83: =V83/X83 -> #VALUE! | AJ83: =Y83/AA83 -> #VALUE! | AK83: =Z83/AB83 -> #VALUE! | AL83: =O83/K83 -> #VALUE! | AM83: =P83/L83 -> #VALUE! | AN83: =K83/W83 -> #VALUE! | AO83: =L83/X83 -> #VALUE! | AP83: =IF(OR(Q83<0, Q83="NA"), 0, 1) -> 0 | AQ83: =IF(OR(S83<0, S83="NA"), 0, 1) -> 0 | AR83: =IFERROR(IF((AF83-AG83)>0,1,0),0) -> 0 | AS83: =IFERROR(IF((S83-Q83)>0,1,0),0) -> 0 | AT83: =IFERROR(IF((AH83-AI83)<0,1,0),0) -> 0 | AU83: =IFERROR(IF((AJ83-AK83)>0,1,0),0) -> 0 | AV83: =IFERROR(IF((AL83-AM83)>0,1,0),0) -> 0 | AW83: =IFERROR(IF((AN83-AO83)>0,1,0),0) -> 0 | AX83: =IFERROR(IF((AC83-AD83)<0,1,0),0) -> 0 | AY83: =SUM(AP83:AX83) -> 0
A84: AECOM (NYSE:ACM) | B84: 4509697 | C84: NYSE | D84: 108.47 | E84: 14368.338 | F84: Industrials | G84: Capital Goods | H84: Construction and Engineering | I84: Construction and Engineering | J84: 541330 - Engineering Services | K84: 16105498 | L84: 15837389 | M84: 1103948 | N84: 1066792 | O84: 932736 | P84: 893141 | Q84: 461588 | R84: 313476 | S84: 827490 | T84: 813899 | U84: 2418230 | V84: 2414844 | W84: 12061669 | X84: 12046598 | Y84: 7176059 | Z84: 7118664 | AA84: 6374081 | AB84: 6289644 | AC84: 132552407 | AD84: 135702623 | AF84: =Q84/W84 -> 0.038268999 | AG84: =R84/X84 -> 0.026021952 | AH84: =U84/W84 -> 0.20048884 | AI84: =V84/X84 -> 0.20045859 | AJ84: =Y84/AA84 -> 1.1258186 | AK84: =Z84/AB84 -> 1.1318071 | AL84: =O84/K84 -> 0.057914136 | AM84: =P84/L84 -> 0.05639446 | AN84: =K84/W84 -> 1.3352628 | AO84: =L84/X84 -> 1.3146773 | AP84: =IF(OR(Q84<0, Q84="NA"), 0, 1) -> 1 | AQ84: =IF(OR(S84<0, S84="NA"), 0, 1) -> 1 | AR84: =IFERROR(IF((AF84-AG84)>0,1,0),0) -> 1 | AS84: =IFERROR(IF((S84-Q84)>0,1,0),0) -> 1 | AT84: =IFERROR(IF((AH84-AI84)<0,1,0),0) -> 0 | AU84: =IFERROR(IF((AJ84-AK84)>0,1,0),0) -> 0 | AV84: =IFERROR(IF((AL84-AM84)>0,1,0),0) -> 1 | AW84: =IFERROR(IF((AN84-AO84)>0,1,0),0) -> 1 | AX84: =IFERROR(IF((AC84-AD84)<0,1,0),0) -> 1 | AY84: =SUM(AP84:AX84) -> 7
A85: Aehr Test Systems, Inc. (NASDAQCM:AEHR) | B85: 4963251 | C85: NASDAQCM | D85: 15.99 | E85: 473.79742 | F85: Information Technology | G85: Semiconductors and Semiconductor Equipment | H85: Semiconductors and Semiconductor Equipment | I85: Semiconductor Materials and Equipment | J85: 334413 - Semiconductor and Related Device Manufacturing | K85: 50735 | L85: 58713 | M85: 468 | N85: 6988 | O85: -859 | P85: 6122 | Q85: 22025 | R85: 29142 | S85: -5093 | T85: 235 | U85: NA | V85: NA | W85: 142280 | X85: 145862 | Y85: 88521 | Z85: 92919 | AA85: 11717 | AB85: 15420 | AC85: 29709000 | AD85: 29584000 | AF85: =Q85/W85 -> 0.15480039 | AG85: =R85/X85 -> 0.19979158 | AH85: =U85/W85 -> #VALUE! | AI85: =V85/X85 -> #VALUE! | AJ85: =Y85/AA85 -> 7.5549202 | AK85: =Z85/AB85 -> 6.0258755 | AL85: =O85/K85 -> -0.016931113 | AM85: =P85/L85 -> 0.10426992 | AN85: =K85/W85 -> 0.35658561 | AO85: =L85/X85 -> 0.4025243 | AP85: =IF(OR(Q85<0, Q85="NA"), 0, 1) -> 1 | AQ85: =IF(OR(S85<0, S85="NA"), 0, 1) -> 0 | AR85: =IFERROR(IF((AF85-AG85)>0,1,0),0) -> 0 | AS85: =IFERROR(IF((S85-Q85)>0,1,0),0) -> 0 | AT85: =IFERROR(IF((AH85-AI85)<0,1,0),0) -> 0 | AU85: =IFERROR(IF((AJ85-AK85)>0,1,0),0) -> 1 | AV85: =IFERROR(IF((AL85-AM85)>0,1,0),0) -> 0 | AW85: =IFERROR(IF((AN85-AO85)>0,1,0),0) -> 0 | AX85: =IFERROR(IF((AC85-AD85)<0,1,0),0) -> 0 | AY85: =SUM(AP85:AX85) -> 2
A86: AerCap Holdings N.V. (NYSE:AER) | B86: 4152754 | C86: NYSE | D86: 94.7 | E86: 17498.936 | F86: Industrials | G86: Capital Goods | H86: Trading Companies and Distributors | I86: Trading Companies and Distributors | J86: 532411 - Commercial Air, Rail, and Water Transportation Equipment Rental and Leasing | K86: 7817256 | L86: 7760794 | M86: 4075643 | N86: 4168787 | O86: 4043666 | P86: 4135432 | Q86: 2534101 | R86: 3268075 | S86: 5551903 | T86: 5489352 | U86: 48352710 | V86: 45697189 | W86: 73824890 | X86: 71106661 | Y86: 8095239 | Z86: 5134134 | AA86: 4083978 | AB86: 3848570 | AC86: 184782849 | AD86: 190184075 | AF86: =Q86/W86 -> 0.034325835 | AG86: =R86/X86 -> 0.045960181 | AH86: =U86/W86 -> 0.65496488 | AI86: =V86/X86 -> 0.64265694 | AJ86: =Y86/AA86 -> 1.9821946 | AK86: =Z86/AB86 -> 1.3340368 | AL86: =O86/K86 -> 0.51727435 | AM86: =P86/L86 -> 0.53286197 | AN86: =K86/W86 -> 0.10588917 | AO86: =L86/X86 -> 0.109143 | AP86: =IF(OR(Q86<0, Q86="NA"), 0, 1) -> 1 | AQ86: =IF(OR(S86<0, S86="NA"), 0, 1) -> 1 | AR86: =IFERROR(IF((AF86-AG86)>0,1,0),0) -> 0 | AS86: =IFERROR(IF((S86-Q86)>0,1,0),0) -> 1 | AT86: =IFERROR(IF((AH86-AI86)<0,1,0),0) -> 0 | AU86: =IFERROR(IF((AJ86-AK86)>0,1,0),0) -> 1 | AV86: =IFERROR(IF((AL86-AM86)>0,1,0),0) -> 0 | AW86: =IFERROR(IF((AN86-AO86)>0,1,0),0) -> 0 | AX86: =IFERROR(IF((AC86-AD86)<0,1,0),0) -> 1 | AY86: =SUM(AP86:AX86) -> 5
A87: AeroVironment, Inc. (NASDAQGS:AVAV) | B87: 4987550 | C87: NASDAQGS | D87: 162.11 | E87: 4539.5431 | F87: Industrials | G87: Capital Goods | H87: Aerospace and Defense | I87: Aerospace and Defense | J87: 336411 - Aircraft Manufacturing | K87: 761498 | L87: 753856 | M87: 90458 | N87: 108064 | O87: 52242 | P87: 70414 | Q87: 48640 | R87: 58937 | S87: 65591 | T87: 60705 | U87: 15000 | V87: 6788 | W87: 1019085 | X87: 999169 | Y87: 514845 | Z87: 500346 | AA87: 111611 | AB87: 117358 | AC87: 28003728 | AD87: 28004971 | AF87: =Q87/W87 -> 0.04772909 | AG87: =R87/X87 -> 0.058986017 | AH87: =U87/W87 -> 0.014719086 | AI87: =V87/X87 -> 0.0067936455 | AJ87: =Y87/AA87 -> 4.6128518 | AK87: =Z87/AB87 -> 4.2634162 | AL87: =O87/K87 -> 0.068604251 | AM87: =P87/L87 -> 0.093405107 | AN87: =K87/W87 -> 0.74723698 | AO87: =L87/X87 -> 0.75448298 | AP87: =IF(OR(Q87<0, Q87="NA"), 0, 1) -> 1 | AQ87: =IF(OR(S87<0, S87="NA"), 0, 1) -> 1 | AR87: =IFERROR(IF((AF87-AG87)>0,1,0),0) -> 0 | AS87: =IFERROR(IF((S87-Q87)>0,1,0),0) -> 1 | AT87: =IFERROR(IF((AH87-AI87)<0,1,0),0) -> 0 | AU87: =IFERROR(IF((AJ87-AK87)>0,1,0),0) -> 1 | AV87: =IFERROR(IF((AL87-AM87)>0,1,0),0) -> 0 | AW87: =IFERROR(IF((AN87-AO87)>0,1,0),0) -> 0 | AX87: =IFERROR(IF((AC87-AD87)<0,1,0),0) -> 1 | AY87: =SUM(AP87:AX87) -> 5
A88: AerSale Corporation (NASDAQCM:ASLE) | B88: 7240660 | C88: NASDAQCM | D88: 6.4 | E88: 340.54939 | F88: Industrials | G88: Capital Goods | H88: Aerospace and Defense | I88: Aerospace and Defense | J88: 33641 - Aerospace Product and Parts Manufacturing | K88: 344747 | L88: 354547 | M88: 17575 | N88: 11655 | O88: 3756 | P88: -169 | Q88: 417 | R88: -240 | S88: -32453 | T88: -81753 | U88: 78889 | V88: 81477 | W88: 601456 | X88: 598694 | Y88: 339736 | Z88: 295828 | AA88: 47114 | AB88: 43008 | AC88: 53210842 | AD88: 53084214 | AF88: =Q88/W88 -> 0.00069331755 | AG88: =R88/X88 -> -0.00040087257 | AH88: =U88/W88 -> 0.13116338 | AI88: =V88/X88 -> 0.13609123 | AJ88: =Y88/AA88 -> 7.2109352 | AK88: =Z88/AB88 -> 6.8784412 | AL88: =O88/K88 -> 0.010894946 | AM88: =P88/L88 -> -0.00047666459 | AN88: =K88/W88 -> 0.5731874 | AO88: =L88/X88 -> 0.59220069 | AP88: =IF(OR(Q88<0, Q88="NA"), 0, 1) -> 1 | AQ88: =IF(OR(S88<0, S88="NA"), 0, 1) -> 0 | AR88: =IFERROR(IF((AF88-AG88)>0,1,0),0) -> 1 | AS88: =IFERROR(IF((S88-Q88)>0,1,0),0) -> 0 | AT88: =IFERROR(IF((AH88-AI88)<0,1,0),0) -> 1 | AU88: =IFERROR(IF((AJ88-AK88)>0,1,0),0) -> 1 | AV88: =IFERROR(IF((AL88-AM88)>0,1,0),0) -> 1 | AW88: =IFERROR(IF((AN88-AO88)>0,1,0),0) -> 0 | AX88: =IFERROR(IF((AC88-AD88)<0,1,0),0) -> 0 | AY88: =SUM(AP88:AX88) -> 5
A89: Affiliated Managers Group, Inc. (NYSE:AMG) | B89: 113618 | C89: NYSE | D89: 178.45 | E89: 5393.6748 | F89: Financials | G89: Financial Services | H89: Capital Markets | I89: Asset Management and Custody Banks | J89: 525910 - Open-End Investment Funds | K89: 2019200 | L89: 2028200 | M89: 694200 | N89: 721800 | O89: 649200 | P89: 671900 | Q89: 763700 | R89: 864000 | S89: 974500 | T89: 1003200 | U89: 2280700 | V89: 2186200 | W89: 8903000 | X89: 8845000 | Y89: 1539800 | Z89: 1494600 | AA89: 10200 | AB89: 19400 | AC89: 30100000 | AD89: 33200000 | AF89: =Q89/W89 -> 0.085780074 | AG89: =R89/X89 -> 0.097682306 | AH89: =U89/W89 -> 0.25617208 | AI89: =V89/X89 -> 0.24716789 | AJ89: =Y89/AA89 -> 150.96078 | AK89: =Z89/AB89 -> 77.041237 | AL89: =O89/K89 -> 0.32151347 | AM89: =P89/L89 -> 0.33127897 | AN89: =K89/W89 -> 0.22679996 | AO89: =L89/X89 -> 0.22930469 | AP89: =IF(OR(Q89<0, Q89="NA"), 0, 1) -> 1 | AQ89: =IF(OR(S89<0, S89="NA"), 0, 1) -> 1 | AR89: =IFERROR(IF((AF89-AG89)>0,1,0),0) -> 0 | AS89: =IFERROR(IF((S89-Q89)>0,1,0),0) -> 1 | AT89: =IFERROR(IF((AH89-AI89)<0,1,0),0) -> 0 | AU89: =IFERROR(IF((AJ89-AK89)>0,1,0),0) -> 1 | AV89: =IFERROR(IF((AL89-AM89)>0,1,0),0) -> 0 | AW89: =IFERROR(IF((AN89-AO89)>0,1,0),0) -> 0 | AX89: =IFERROR(IF((AC89-AD89)<0,1,0),0) -> 1 | AY89: =SUM(AP89:AX89) -> 5
A90: Affinity Bancshares, Inc. (NASDAQCM:AFBI) | B90: 4872031 | C90: NASDAQCM | D90: 17.45 | E90: 111.8969 | F90: Financials | G90: Banks | H90: Banks | I90: Regional Banks | J90: 522110 - Commercial Banking | K90: 30814 | L90: 30365 | M90: NA | N90: NA | O90: 25701 | P90: 24785 | Q90: 5610 | R90: 5503 | S90: 7735 | T90: 5374 | U90: NA | V90: NA | W90: 878561 | X90: 873582 | Y90: NA | Z90: NA | AA90: NA | AB90: NA | AC90: 6412430 | AD90: 6416628 | AF90: =Q90/W90 -> 0.0063854416 | AG90: =R90/X90 -> 0.0062993514 | AH90: =U90/W90 -> #VALUE! | AI90: =V90/X90 -> #VALUE! | AJ90: =Y90/AA90 -> #VALUE! | AK90: =Z90/AB90 -> #VALUE! | AL90: =O90/K90 -> 0.83406893 | AM90: =P90/L90 -> 0.8162358 | AN90: =K90/W90 -> 0.035073262 | AO90: =L90/X90 -> 0.034759187 | AP90: =IF(OR(Q90<0, Q90="NA"), 0, 1) -> 1 | AQ90: =IF(OR(S90<0, S90="NA"), 0, 1) -> 1 | AR90: =IFERROR(IF((AF90-AG90)>0,1,0),0) -> 1 | AS90: =IFERROR(IF((S90-Q90)>0,1,0),0) -> 1 | AT90: =IFERROR(IF((AH90-AI90)<0,1,0),0) -> 0 | AU90: =IFERROR(IF((AJ90-AK90)>0,1,0),0) -> 0 | AV90: =IFERROR(IF((AL90-AM90)>0,1,0),0) -> 1 | AW90: =IFERROR(IF((AN90-AO90)>0,1,0),0) -> 1 | AX90: =IFERROR(IF((AC90-AD90)<0,1,0),0) -> 1 | AY90: =SUM(AP90:AX90) -> 7
A91: Affirm Holdings, Inc. (NASDAQGS:AFRM) | B91: 26472629 | C91: NASDAQGS | D91: 54.69 | E91: 17175.728 | F91: Financials | G91: Financial Services | H91: Financial Services | I91: Transaction and Payment Processing Services | J91: 522291 - Consumer Lending | K91: 2524931 | L91: 2322999 | M91: -291773 | N91: -365213 | O91: -533175 | P91: -607327 | Q91: -446196 | R91: -517757 | S91: 548103 | T91: 450138 | U91: 7084078 | V91: 6574855 | W91: 10139159 | X91: 9519619 | Y91: 2613394 | Z91: 1786596 | AA91: 171898 | AB91: 159344 | AC91: 313977403 | AD91: 311053031 | AF91: =Q91/W91 -> -0.0440072 | AG91: =R91/X91 -> -0.054388416 | AH91: =U91/W91 -> 0.69868497 | AI91: =V91/X91 -> 0.69066367 | AJ91: =Y91/AA91 -> 15.203167 | AK91: =Z91/AB91 -> 11.212195 | AL91: =O91/K91 -> -0.21116419 | AM91: =P91/L91 -> -0.26144092 | AN91: =K91/W91 -> 0.24902766 | AO91: =L91/X91 -> 0.24402227 | AP91: =IF(OR(Q91<0, Q91="NA"), 0, 1) -> 0 | AQ91: =IF(OR(S91<0, S91="NA"), 0, 1) -> 1 | AR91: =IFERROR(IF((AF91-AG91)>0,1,0),0) -> 1 | AS91: =IFERROR(IF((S91-Q91)>0,1,0),0) -> 1 | AT91: =IFERROR(IF((AH91-AI91)<0,1,0),0) -> 0 | AU91: =IFERROR(IF((AJ91-AK91)>0,1,0),0) -> 1 | AV91: =IFERROR(IF((AL91-AM91)>0,1,0),0) -> 1 | AW91: =IFERROR(IF((AN91-AO91)>0,1,0),0) -> 1 | AX91: =IFERROR(IF((AC91-AD91)<0,1,0),0) -> 0 | AY91: =SUM(AP91:AX91) -> 6
A92: Aflac Incorporated (NYSE:AFL) | B92: 103316 | C92: NYSE | D92: 102.49 | E92: 56936.107 | F92: Financials | G92: Insurance | H92: Insurance | I92: Life and Health Insurance | J92: 524113 - Direct Life Insurance Carriers | K92: 17300000 | L92: 19301000 | M92: NA | N92: NA | O92: 4763000 | P92: 6475000 | Q92: 3809000 | R92: 5471000 | S92: 2956000 | T92: 2962000 | U92: 7781000 | V92: 7322000 | W92: 128442000 | X92: 120168000 | Y92: NA | Z92: NA | AA92: NA | AB92: NA | AC92: 556717000 | AD92: 561369000 | AF92: =Q92/W92 -> 0.029655409 | AG92: =R92/X92 -> 0.045527928 | AH92: =U92/W92 -> 0.060579873 | AI92: =V92/X92 -> 0.060931363 | AJ92: =Y92/AA92 -> #VALUE! | AK92: =Z92/AB92 -> #VALUE! | AL92: =O92/K92 -> 0.27531792 | AM92: =P92/L92 -> 0.33547485 | AN92: =K92/W92 -> 0.13469114 | AO92: =L92/X92 -> 0.1606168 | AP92: =IF(OR(Q92<0, Q92="NA"), 0, 1) -> 1 | AQ92: =IF(OR(S92<0, S92="NA"), 0, 1) -> 1 | AR92: =IFERROR(IF((AF92-AG92)>0,1,0),0) -> 0 | AS92: =IFERROR(IF((S92-Q92)>0,1,0),0) -> 0 | AT92: =IFERROR(IF((AH92-AI92)<0,1,0),0) -> 1 | AU92: =IFERROR(IF((AJ92-AK92)>0,1,0),0) -> 0 | AV92: =IFERROR(IF((AL92-AM92)>0,1,0),0) -> 0 | AW92: =IFERROR(IF((AN92-AO92)>0,1,0),0) -> 0 | AX92: =IFERROR(IF((AC92-AD92)<0,1,0),0) -> 1 | AY92: =SUM(AP92:AX92) -> 4
A93: Afya Limited (NASDAQGS:AFYA) | B93: 15170166 | C93: NASDAQGS | D93: 15.2 | E93: 1374.8086 | F93: Consumer Discretionary | G93: Consumer Services | H93: Diversified Consumer Services | I93: Education Services | J93: 611 - Educational Services | K93: 617987.4 | L93: 614179.77 | M93: 222247.72 | N93: 219177.24 | O93: 182288.41 | P93: 178876.09 | Q93: 115737.94 | R93: 114248.42 | S93: 251371.04 | T93: 234922 | U93: 388455.7 | V93: 292044.46 | W93: 1600240 | X93: 1414265.6 | Y93: 271104.83 | Z93: 258393.08 | AA93: 169908.36 | AB93: 175509.58 | AC93: 90229593 | AD93: 90192887 | AF93: =Q93/W93 -> 0.072325362 | AG93: =R93/X93 -> 0.080782857 | AH93: =U93/W93 -> 0.2427484 | AI93: =V93/X93 -> 0.20649901 | AJ93: =Y93/AA93 -> 1.5955944 | AK93: =Z93/AB93 -> 1.4722448 | AL93: =O93/K93 -> 0.29497108 | AM93: =P93/L93 -> 0.29124387 | AN93: =K93/W93 -> 0.38618419 | AO93: =L93/X93 -> 0.43427469 | AP93: =IF(OR(Q93<0, Q93="NA"), 0, 1) -> 1 | AQ93: =IF(OR(S93<0, S93="NA"), 0, 1) -> 1 | AR93: =IFERROR(IF((AF93-AG93)>0,1,0),0) -> 0 | AS93: =IFERROR(IF((S93-Q93)>0,1,0),0) -> 1 | AT93: =IFERROR(IF((AH93-AI93)<0,1,0),0) -> 0 | AU93: =IFERROR(IF((AJ93-AK93)>0,1,0),0) -> 1 | AV93: =IFERROR(IF((AL93-AM93)>0,1,0),0) -> 1 | AW93: =IFERROR(IF((AN93-AO93)>0,1,0),0) -> 0 | AX93: =IFERROR(IF((AC93-AD93)<0,1,0),0) -> 0 | AY93: =SUM(AP93:AX93) -> 5
A94: AG Mortgage Investment Trust, Inc. (NYSE:MITT) | B94: 4281583 | C94: NYSE | D94: 6.21 | E94: 183.25586 | F94: Financials | G94: Financial Services | H94: Mortgage Real Estate Investment Trusts (REITs) | I94: Mortgage REITs | J94: 525990 - Other Financial Vehicles | K94: 80808 | L94: 67902 | M94: 395332 | N94: 336713 | O94: 395332 | P94: 336713 | Q94: 76808 | R94: 58003 | S94: 50198 | T94: 38745 | U94: 5593100 | V94: 5542860 | W94: 6960075 | X94: 7100101 | Y94: NA | Z94: NA | AA94: NA | AB94: NA | AC94: 29493000 | AD94: 29474000 | AF94: =Q94/W94 -> 0.011035513 | AG94: =R94/X94 -> 0.0081693204 | AH94: =U94/W94 -> 0.80359766 | AI94: =V94/X94 -> 0.7806734 | AJ94: =Y94/AA94 -> #VALUE! | AK94: =Z94/AB94 -> #VALUE! | AL94: =O94/K94 -> 4.8922384 | AM94: =P94/L94 -> 4.9588083 | AN94: =K94/W94 -> 0.01161022 | AO94: =L94/X94 -> 0.0095635259 | AP94: =IF(OR(Q94<0, Q94="NA"), 0, 1) -> 1 | AQ94: =IF(OR(S94<0, S94="NA"), 0, 1) -> 1 | AR94: =IFERROR(IF((AF94-AG94)>0,1,0),0) -> 1 | AS94: =IFERROR(IF((S94-Q94)>0,1,0),0) -> 0 | AT94: =IFERROR(IF((AH94-AI94)<0,1,0),0) -> 0 | AU94: =IFERROR(IF((AJ94-AK94)>0,1,0),0) -> 0 | AV94: =IFERROR(IF((AL94-AM94)>0,1,0),0) -> 0 | AW94: =IFERROR(IF((AN94-AO94)>0,1,0),0) -> 1 | AX94: =IFERROR(IF((AC94-AD94)<0,1,0),0) -> 0 | AY94: =SUM(AP94:AX94) -> 4
A95: AGCO Corporation (NYSE:AGCO) | B95: 4309089 | C95: NYSE | D95: 97.09 | E95: 7247.3103 | F95: Industrials | G95: Capital Goods | H95: Machinery | I95: Agricultural and Farm Machinery | J95: 333111 - Farm Machinery and Equipment Manufacturing | K95: 12575300 | L95: 13431500 | M95: 1425900 | N95: 1700500 | O95: 1106200 | P95: 1377300 | Q95: 167000 | R95: 418600 | S95: 792400 | T95: 1333600 | U95: 3610000 | V95: 3595200 | W95: 13506800 | X95: 13614800 | Y95: 6538900 | Z95: 6638700 | AA95: 4280100 | AB95: 4363500 | AC95: 74644933 | AD95: 74634538 | AF95: =Q95/W95 -> 0.012364143 | AG95: =R95/X95 -> 0.030745953 | AH95: =U95/W95 -> 0.26727278 | AI95: =V95/X95 -> 0.26406558 | AJ95: =Y95/AA95 -> 1.5277447 | AK95: =Z95/AB95 -> 1.5214163 | AL95: =O95/K95 -> 0.087966092 | AM95: =P95/L95 -> 0.10254253 | AN95: =K95/W95 -> 0.93103474 | AO95: =L95/X95 -> 0.98653671 | AP95: =IF(OR(Q95<0, Q95="NA"), 0, 1) -> 1 | AQ95: =IF(OR(S95<0, S95="NA"), 0, 1) -> 1 | AR95: =IFERROR(IF((AF95-AG95)>0,1,0),0) -> 0 | AS95: =IFERROR(IF((S95-Q95)>0,1,0),0) -> 1 | AT95: =IFERROR(IF((AH95-AI95)<0,1,0),0) -> 0 | AU95: =IFERROR(IF((AJ95-AK95)>0,1,0),0) -> 1 | AV95: =IFERROR(IF((AL95-AM95)>0,1,0),0) -> 0 | AW95: =IFERROR(IF((AN95-AO95)>0,1,0),0) -> 0 | AX95: =IFERROR(IF((AC95-AD95)<0,1,0),0) -> 0 | AY95: =SUM(AP95:AX95) -> 4
A96: Agilent Technologies, Inc. (NYSE:A) | B96: 4075849 | C96: NYSE | D96: 141.95 | E96: 40540.253 | F96: Health Care | G96: Pharmaceuticals, Biotechnology and Life Sciences | H96: Life Sciences Tools and Services | I96: Life Sciences Tools and Services | J96: 334516 - Analytical Laboratory Instrument Manufacturing | K96: 6510000 | L96: 6497000 | M96: 1801000 | N96: 1564000 | O96: 1544000 | P96: 1314000 | Q96: 1289000 | R96: 1413000 | S96: 1751000 | T96: 1786000 | U96: 3345000 | V96: 2137000 | W96: 11846000 | X96: 10996000 | Y96: 3959000 | Z96: 4256000 | AA96: 1895000 | AB96: 2389000 | AC96: 285193011 | AD96: 287529636 | AF96: =Q96/W96 -> 0.1088131 | AG96: =R96/X96 -> 0.12850127 | AH96: =U96/W96 -> 0.2823738 | AI96: =V96/X96 -> 0.1943434 | AJ96: =Y96/AA96 -> 2.0891821 | AK96: =Z96/AB96 -> 1.7814985 | AL96: =O96/K96 -> 0.23717358 | AM96: =P96/L96 -> 0.20224719 | AN96: =K96/W96 -> 0.54955259 | AO96: =L96/X96 -> 0.59085122 | AP96: =IF(OR(Q96<0, Q96="NA"), 0, 1) -> 1 | AQ96: =IF(OR(S96<0, S96="NA"), 0, 1) -> 1 | AR96: =IFERROR(IF((AF96-AG96)>0,1,0),0) -> 0 | AS96: =IFERROR(IF((S96-Q96)>0,1,0),0) -> 1 | AT96: =IFERROR(IF((AH96-AI96)<0,1,0),0) -> 0 | AU96: =IFERROR(IF((AJ96-AK96)>0,1,0),0) -> 1 | AV96: =IFERROR(IF((AL96-AM96)>0,1,0),0) -> 1 | AW96: =IFERROR(IF((AN96-AO96)>0,1,0),0) -> 0 | AX96: =IFERROR(IF((AC96-AD96)<0,1,0),0) -> 1 | AY96: =SUM(AP96:AX96) -> 6
A97: Agilysys, Inc. (NASDAQGS:AGYS) | B97: 4146470 | C97: NASDAQGS | D97: 127.53 | E97: 3520.451 | F97: Information Technology | G97: Software and Services | H97: Software | I97: Application Software | J97: 513210 - Software Publishers | K97: 254579 | L97: 244917 | M97: 29050 | N97: 25503 | O97: 24090 | P97: 20626 | Q97: 95572 | R97: 98753 | S97: 50404 | T97: 49262 | U97: 50000 | V97: NA | W97: 442010 | X97: 355698 | Y97: 108701 | Z97: 186765 | AA97: 95889 | AB97: 77404 | AC97: 27594379 | AD97: 27505074 | AF97: =Q97/W97 -> 0.21622135 | AG97: =R97/X97 -> 0.27763159 | AH97: =U97/W97 -> 0.11311961 | AI97: =V97/X97 -> #VALUE! | AJ97: =Y97/AA97 -> 1.1336128 | AK97: =Z97/AB97 -> 2.4128598 | AL97: =O97/K97 -> 0.094626815 | AM97: =P97/L97 -> 0.084216286 | AN97: =K97/W97 -> 0.57595756 | AO97: =L97/X97 -> 0.68855321 | AP97: =IF(OR(Q97<0, Q97="NA"), 0, 1) -> 1 | AQ97: =IF(OR(S97<0, S97="NA"), 0, 1) -> 1 | AR97: =IFERROR(IF((AF97-AG97)>0,1,0),0) -> 0 | AS97: =IFERROR(IF((S97-Q97)>0,1,0),0) -> 0 | AT97: =IFERROR(IF((AH97-AI97)<0,1,0),0) -> 0 | AU97: =IFERROR(IF((AJ97-AK97)>0,1,0),0) -> 0 | AV97: =IFERROR(IF((AL97-AM97)>0,1,0),0) -> 1 | AW97: =IFERROR(IF((AN97-AO97)>0,1,0),0) -> 0 | AX97: =IFERROR(IF((AC97-AD97)<0,1,0),0) -> 0 | AY97: =SUM(AP97:AX97) -> 3
A98: Agios Pharmaceuticals, Inc. (NASDAQGS:AGIO) | B98: 4318095 | C98: NASDAQGS | D98: 34.3 | E98: 1956.1357 | F98: Health Care | G98: Pharmaceuticals, Biotechnology and Life Sciences | H98: Biotechnology | I98: Biotechnology | J98: 325412 - Pharmaceutical Preparation Manufacturing | K98: 32871 | L98: 31306 | M98: -401288 | N98: -399096 | O98: -406977 | P98: -405063 | Q98: 674308 | R98: -364931 | S98: -329162 | T98: -306587 | U98: NA | V98: NA | W98: 1791794 | X98: 773063 | Y98: 1074189 | Z98: 632127 | AA98: 119451 | AB98: 62637 | AC98: 57021543 | AD98: 56875079 | AF98: =Q98/W98 -> 0.37633121 | AG98: =R98/X98 -> -0.47205855 | AH98: =U98/W98 -> #VALUE! | AI98: =V98/X98 -> #VALUE! | AJ98: =Y98/AA98 -> 8.9927167 | AK98: =Z98/AB98 -> 10.091911 | AL98: =O98/K98 -> -12.381035 | AM98: =P98/L98 -> -12.93883 | AN98: =K98/W98 -> 0.018345301 | AO98: =L98/X98 -> 0.040496053 | AP98: =IF(OR(Q98<0, Q98="NA"), 0, 1) -> 1 | AQ98: =IF(OR(S98<0, S98="NA"), 0, 1) -> 0 | AR98: =IFERROR(IF((AF98-AG98)>0,1,0),0) -> 1 | AS98: =IFERROR(IF((S98-Q98)>0,1,0),0) -> 0 | AT98: =IFERROR(IF((AH98-AI98)<0,1,0),0) -> 0 | AU98: =IFERROR(IF((AJ98-AK98)>0,1,0),0) -> 0 | AV98: =IFERROR(IF((AL98-AM98)>0,1,0),0) -> 1 | AW98: =IFERROR(IF((AN98-AO98)>0,1,0),0) -> 0 | AX98: =IFERROR(IF((AC98-AD98)<0,1,0),0) -> 0 | AY98: =SUM(AP98:AX98) -> 3
A99: AGNC Investment Corp. (NASDAQGS:AGNC) | B99: 4199629 | C99: NASDAQGS | D99: 9.12 | E99: 8077.0353 | F99: Financials | G99: Financial Services | H99: Mortgage Real Estate Investment Trusts (REITs) | I99: Mortgage REITs | J99: 525990 - Other Financial Vehicles | K99: 1259000 | L99: 514000 | M99: 4285000 | N99: 3437000 | O99: 4285000 | P99: 3437000 | Q99: 1153000 | R99: 415000 | S99: -24000 | T99: -83000 | U99: 69000 | V99: 71000 | W99: 89590000 | X99: 79685000 | Y99: NA | Z99: NA | AA99: NA | AB99: NA | AC99: 844200000 | AD99: 766100000 | AF99: =Q99/W99 -> 0.01286974 | AG99: =R99/X99 -> 0.0052080065 | AH99: =U99/W99 -> 0.00077017524 | AI99: =V99/X99 -> 0.00089100835 | AJ99: =Y99/AA99 -> #VALUE! | AK99: =Z99/AB99 -> #VALUE! | AL99: =O99/K99 -> 3.4034948 | AM99: =P99/L99 -> 6.6867704 | AN99: =K99/W99 -> 0.014052908 | AO99: =L99/X99 -> 0.0064503984 | AP99: =IF(OR(Q99<0, Q99="NA"), 0, 1) -> 1 | AQ99: =IF(OR(S99<0, S99="NA"), 0, 1) -> 0 | AR99: =IFERROR(IF((AF99-AG99)>0,1,0),0) -> 1 | AS99: =IFERROR(IF((S99-Q99)>0,1,0),0) -> 0 | AT99: =IFERROR(IF((AH99-AI99)<0,1,0),0) -> 1 | AU99: =IFERROR(IF((AJ99-AK99)>0,1,0),0) -> 0 | AV99: =IFERROR(IF((AL99-AM99)>0,1,0),0) -> 0 | AW99: =IFERROR(IF((AN99-AO99)>0,1,0),0) -> 1 | AX99: =IFERROR(IF((AC99-AD99)<0,1,0),0) -> 0 | AY99: =SUM(AP99:AX99) -> 4
A100: Agnico Eagle Mines Limited (NYSE:AEM) | B100: 4347844 | C100: NYSE | D100: 82.36 | E100: 41224.132 | F100: Materials | G100: Materials | H100: Metals and Mining | I100: Gold | J100: 212220 - Gold Ore and Silver Ore Mining | K100: 7818693 | L100: 7305495 | M100: 4203646 | N100: 3650466 | O100: 2365313 | P100: 1781287 | Q100: 1012269 | R100: 619954 | S100: 3556904 | T100: 2974460 | U100: 1052233 | V100: 1101670 | W100: 29816489 | X100: 29291206 | Y100: 2907703 | Z100: 2712334 | AA100: 1663797 | AB100: 1791224 | AC100: 501517072 | AD100: 499886288 | AF100: =Q100/W100 -> 0.033949973 | AG100: =R100/X100 -> 0.021165192 | AH100: =U100/W100 -> 0.035290305 | AI100: =V100/X100 -> 0.037610947 | AJ100: =Y100/AA100 -> 1.7476309 | AK100: =Z100/AB100 -> 1.514235 | AL100: =O100/K100 -> 0.30252025 | AM100: =P100/L100 -> 0.24382838 | AN100: =K100/W100 -> 0.26222715 | AO100: =L100/X100 -> 0.24940916 | AP100: =IF(OR(Q100<0, Q100="NA"), 0, 1) -> 1 | AQ100: =IF(OR(S100<0, S100="NA"), 0, 1) -> 1 | AR100: =IFERROR(IF((AF100-AG100)>0,1,0),0) -> 1 | AS100: =IFERROR(IF((S100-Q100)>0,1,0),0) -> 1 | AT100: =IFERROR(IF((AH100-AI100)<0,1,0),0) -> 1 | AU100: =IFERROR(IF((AJ100-AK100)>0,1,0),0) -> 1 | AV100: =IFERROR(IF((AL100-AM100)>0,1,0),0) -> 1 | AW100: =IFERROR(IF((AN100-AO100)>0,1,0),0) -> 1 | AX100: =IFERROR(IF((AC100-AD100)<0,1,0),0) -> 0 | AY100: =SUM(AP100:AX100) -> 8
A101: Agree Realty Corporation (NYSE:ADC) | B101: 103154 | C101: NYSE | D101: 69.52 | E101: 7181.3935 | F101: Real Estate | G101: Equity Real Estate Investment Trusts (REITs) | H101: Retail REITs | I101: Retail REITs | J101: 531110 - Lessors of Residential Buildings and Dwellings | K101: 600525 | L101: 583005 | M101: 494353 | N101: 477096 | O101: 296675 | P101: 285297 | Q101: 190556 | R101: 187685 | S101: 438585 | T101: 407989 | U101: 2680976 | V101: 2668856 | W101: 8184203 | X101: 8000838 | Y101: NA | Z101: NA | AA101: NA | AB101: NA | AC101: 103522677 | AD101: 100624624 | AF101: =Q101/W101 -> 0.023283391 | AG101: =R101/X101 -> 0.023458168 | AH101: =U101/W101 -> 0.32757936 | AI101: =V101/X101 -> 0.33357206 | AJ101: =Y101/AA101 -> #VALUE! | AK101: =Z101/AB101 -> #VALUE! | AL101: =O101/K101 -> 0.49402606 | AM101: =P101/L101 -> 0.48935601 | AN101: =K101/W101 -> 0.073376112 | AO101: =L101/X101 -> 0.072867992 | AP101: =IF(OR(Q101<0, Q101="NA"), 0, 1) -> 1 | AQ101: =IF(OR(S101<0, S101="NA"), 0, 1) -> 1 | AR101: =IFERROR(IF((AF101-AG101)>0,1,0),0) -> 0 | AS101: =IFERROR(IF((S101-Q101)>0,1,0),0) -> 1 | AT101: =IFERROR(IF((AH101-AI101)<0,1,0),0) -> 1 | AU101: =IFERROR(IF((AJ101-AK101)>0,1,0),0) -> 0 | AV101: =IFERROR(IF((AL101-AM101)>0,1,0),0) -> 1 | AW101: =IFERROR(IF((AN101-AO101)>0,1,0),0) -> 1 | AX101: =IFERROR(IF((AC101-AD101)<0,1,0),0) -> 0 | AY101: =SUM(AP101:AX101) -> 6
...
